Workbook

Sheet Prévisions Mois N
B1: ESTIMATION | P1: VARIATION R 16 sur B16 & R15
B2: BASE | E2: CA GENERE | P2: R16 | R2: Variation Réel 16 / B16 | U2: Variation Réel 16 / Réel 15 | X2: Commentaires
B3: LOYER | C3: Plog & Divers | D3: Total BASE | E3: IMAR | F3: HINT | G3: IAER | H3: EAER | I3: AERIEN | J3: EXPORT | K3: SIRT | L3: Afritramp | M3: Meet & Greet | N3: CA GENERE Autres département | O3: CA TOTAL GENERE PAR CLIENT | P3: Sources revenus | Q3: REEL BASE 2016 | R3: Budget 2016 | S3: VAR (FCFA) | T3: Var (%) | U3: Réel BASE 2015 | V3: VAR (FCFA) | W3: Var (%)
A4: Afritramp C/O SAGA | C4: =D4-B4 | I4: =H4+G4 | N4: =J4+I4+F4+E4+L4+M4+K4 | O4: =N4+D4 | P4: Afritramp C/O SAGA | Q4: =D4 | R4: 0 | S4: =Q4-R4 | T4: =Q4/R4-1 | V4: =Q4-U4 | W4: =(Q4/U4-1)
A5: Antrak Ghana (Tullow Oil) | C5: =D5-B5 | I5: =H5+G5 | N5: =J5+I5+F5+E5+L5+M5+K5 | O5: =N5+D5 | P5: Antrak Ghana (Tullow Oil) | Q5: =D5 | R5: 0 | S5: =Q5-R5 | T5: =Q5/R5-1 | V5: =Q5-U5 | W5: =(Q5/U5-1)
A6: Anadarko | C6: =D6-B6 | I6: =H6+G6 | N6: =J6+I6+F6+E6+L6+M6+K6 | O6: =N6+D6 | P6: Anadarko | Q6: =D6 | R6: 10416667 | S6: =Q6-R6 | T6: =Q6/R6-1 | U6: =116080+17732160 | V6: =Q6-U6 | W6: =(Q6/U6-1)
A7: Baker Hugues | C7: =D7-B7 | I7: =H7+G7 | N7: =J7+I7+F7+E7+L7+M7+K7 | O7: =N7+D7 | P7: Baker Hugues | Q7: =D7 | R7: 13833333 | S7: =Q7-R7 | T7: =Q7/R7-1 | U7: 20563873 | V7: =Q7-U7 | W7: =(Q7/U7-1)
A8: BOURBON | C8: =D8-B8 | I8: =H8+G8 | N8: =J8+I8+F8+E8+L8+M8+K8 | O8: =N8+D8 | P8: BOURBON | Q8: =D8 | R8: 0 | S8: =Q8-R8 | T8: =Q8/R8-1 | V8: =Q8-U8 | W8: =(Q8/U8-1)
A9: CGG Veritas | C9: =D9-B9 | I9: =H9+G9 | N9: =J9+I9+F9+E9+L9+M9+K9 | O9: =N9+D9 | P9: CGG Veritas | Q9: =D9 | R9: 0 | S9: =Q9-R9 | T9: =Q9/R9-1 | V9: =Q9-U9 | W9: =(Q9/U9-1)
A10: CIAM | C10: =D10-B10 | I10: =H10+G10 | N10: =J10+I10+F10+E10+L10+M10+K10 | O10: =N10+D10 | P10: CIAM | Q10: =D10 | R10: 2083333.3 | S10: =Q10-R10 | T10: =Q10/R10-1 | U10: 715000 | V10: =Q10-U10 | W10: =(Q10/U10-1)
A11: CNR | C11: =D11-B11 | I11: =H11+G11 | N11: =J11+I11+F11+E11+L11+M11+K11 | O11: =N11+D11 | P11: CNR | Q11: =D11 | R11: 81666667 | S11: =Q11-R11 | T11: =Q11/R11-1 | U11: 91764418 | V11: =Q11-U11 | W11: =(Q11/U11-1)
A12: DIVERS/Various customer | C12: =D12-B12 | I12: =H12+G12 | N12: =J12+I12+F12+E12+L12+M12+K12 | O12: =N12+D12 | P12: DIVERS/Various customer | Q12: =D12 | R12: 39583333 | S12: =Q12-R12 | T12: =Q12/R12-1 | U12: -83126 | V12: =Q12-U12 | W12: =(Q12/U12-1)
A13: dolphin drilling | C13: =D13-B13 | I13: =H13+G13 | N13: =J13+I13+F13+E13+L13+M13+K13 | O13: =N13+D13 | P13: dolphin drilling | Q13: =D13 | R13: 0 | S13: =Q13-R13 | T13: =Q13/R13-1 | V13: =Q13-U13 | W13: =(Q13/U13-1)
A14: ExxonMobil | C14: =D14-B14 | I14: =H14+G14 | N14: =J14+I14+F14+E14+L14+M14+K14 | O14: =N14+D14 | P14: ExxonMobil | Q14: =D14 | R14: 0 | S14: =Q14-R14 | T14: =Q14/R14-1 | V14: =Q14-U14 | W14: =(Q14/U14-1)
A15: EXPRO GROUP NORTH SEA / S-Traitant | C15: =D15-B15 | I15: =H15+G15 | N15: =J15+I15+F15+E15+L15+M15+K15 | O15: =N15+D15 | P15: EXPRO GROUP NORTH SEA / S-Traitant | Q15: =D15 | R15: 8250000 | S15: =Q15-R15 | T15: =Q15/R15-1 | U15: 5122000 | V15: =Q15-U15 | W15: =(Q15/U15-1)
A16: FUGRO | C16: =D16-B16 | I16: =H16+G16 | N16: =J16+I16+F16+E16+L16+M16+K16 | O16: =N16+D16 | P16: FMC / Assistance | Q16: =D16 | R16: 0 | S16: =Q16-R16 | T16: =Q16/R16-1 | V16: =Q16-U16 | W16: =(Q16/U16-1)
A17: FOXTROT | C17: =D17-B17 | I17: =H17+G17 | N17: =J17+I17+F17+E17+L17+M17+K17 | O17: =N17+D17 | P17: FOXTROT | Q17: =D17 | R17: 65416667 | S17: =Q17-R17 | T17: =Q17/R17-1 | U17: 106573674 | V17: =Q17-U17 | W17: =(Q17/U17-1)
A18: Franks International | C18: =D18-B18 | I18: =H18+G18 | N18: =J18+I18+F18+E18+L18+M18+K18 | O18: =N18+D18 | P18: FUGRO / Assistance | Q18: =D18 | R18: 0 | S18: =Q18-R18 | T18: =Q18/R18-1 | V18: =Q18-U18 | W18: =(Q18/U18-1)
A19: GLOBAL ENERGY | C19: =D19-B19 | I19: =H19+G19 | N19: =J19+I19+F19+E19+L19+M19+K19 | O19: =N19+D19 | P19: GLOBAL ENERGY | Q19: =D19 | R19: 4166666.7 | S19: =Q19-R19 | T19: =Q19/R19-1 | U19: 4118387 | V19: =Q19-U19 | W19: =(Q19/U19-1)
A20: GULF OFFSHORE(NS) LTD | C20: =D20-B20 | I20: =H20+G20 | N20: =J20+I20+F20+E20+L20+M20+K20 | O20: =N20+D20 | P20: GULF OFFSHORE(NS) LTD | Q20: =D20 | R20: 0 | S20: =Q20-R20 | T20: =Q20/R20-1 | V20: =Q20-U20 | W20: =(Q20/U20-1)
A21: HALLIBURTON | C21: =D21-B21 | I21: =H21+G21 | N21: =J21+I21+F21+E21+L21+M21+K21 | O21: =N21+D21 | P21: HALLIBURTON | Q21: =D21 | R21: 33333333 | S21: =Q21-R21 | T21: =Q21/R21-1 | U21: 48316159 | V21: =Q21-U21 | W21: =(Q21/U21-1)
A22: SAGA ITALIE | C22: =D22-B22 | I22: =H22+G22 | N22: =J22+I22+F22+E22+L22+M22+K22 | O22: =N22+D22 | P22: INTERSHIP | Q22: =D22 | R22: 0 | S22: =Q22-R22 | T22: =Q22/R22-1 | U22: -327500 | V22: =Q22-U22 | W22: =(Q22/U22-1)
A23: KCA Deutag | C23: =D23-B23 | I23: =H23+G23 | N23: =J23+I23+F23+E23+L23+M23+K23 | O23: =N23+D23 | P23: KCA Deutag | Q23: =D23 | R23: 0 | S23: =Q23-R23 | T23: =Q23/R23-1 | V23: =Q23-U23 | W23: =(Q23/U23-1)
A24: LUKOIL | C24: =D24-B24 | I24: =H24+G24 | N24: =J24+I24+F24+E24+L24+M24+K24 | O24: =N24+D24 | P24: LUKOIL | Q24: =D24 | R24: 0 | S24: =Q24-R24 | T24: =Q24/R24-1 | U24: 86200 | V24: =Q24-U24 | W24: =(Q24/U24-1)
A25: MI | I25: =H25+G25 | N25: =J25+I25+F25+E25+L25+M25+K25 | O25: =N25+D25 | P25: MI | Q25: =D25 | R25: 16666667 | S25: =Q25-R25 | T25: =Q25/R25-1 | U25: 25310375 | V25: =Q25-U25 | W25: =(Q25/U25-1)
A26: National Oilwell Varcouk | C26: =D26-B26 | I26: =H26+G26 | N26: =J26+I26+F26+E26+L26+M26+K26 | O26: =N26+D26 | P26: National Oilwell Varcouk | Q26: =D26 | R26: 0 | S26: =Q26-R26 | T26: =Q26/R26-1 | V26: =Q26-U26 | W26: =(Q26/U26-1)
A27: NOPCI - MODEC | C27: =D27-B27 | I27: =H27+G27 | N27: =J27+I27+F27+E27+L27+M27+K27 | O27: =N27+D27 | P27: NOPCI - MODEC | Q27: =D27 | R27: 833333.33 | S27: =Q27-R27 | T27: =Q27/R27-1 | U27: 80235 | V27: =Q27-U27 | W27: =(Q27/U27-1)
A28: MICOPERI | C28: =D28-B28 | I28: =H28+G28 | N28: =J28+I28+F28+E28+L28+M28+K28 | O28: =N28+D28 | P28: MICOPERI | Q28: =D28 | R28: 0 | S28: =Q28-R28 | T28: =Q28/R28-1 | U28: 10890950 | V28: =Q28-U28 | W28: =(Q28/U28-1)
A29: PENTAGON FREIGHT | C29: =D29-B29 | I29: =H29+G29 | N29: =J29+I29+F29+E29+L29+M29+K29 | O29: =N29+D29 | P29: PENTAGON FREIGHT | Q29: =D29 | R29: 0 | S29: =Q29-R29 | T29: =Q29/R29-1 | V29: =Q29-U29 | W29: =(Q29/U29-1)
A30: Prosafe | C30: =D30-B30 | I30: =H30+G30 | N30: =J30+I30+F30+E30+L30+M30+K30 | O30: =N30+D30 | P30: Prosafe | Q30: =D30 | R30: 41666.667 | S30: =Q30-R30 | T30: =Q30/R30-1 | U30: 223850 | V30: =Q30-U30 | W30: =(Q30/U30-1)
A31: Saphire Driller (Vantage) | C31: =D31-B31 | I31: =H31+G31 | N31: =J31+I31+F31+E31+L31+M31+K31 | O31: =N31+D31 | P31: Saphire Driller (Vantage) | Q31: =D31 | R31: 0 | S31: =Q31-R31 | T31: =Q31/R31-1 | V31: =Q31-U31 | W31: =(Q31/U31-1)
A32: BOLLORE NORWAY (PROSAFE) | C32: =D32-B32 | I32: =H32+G32 | N32: =J32+I32+F32+E32+L32+M32+K32 | O32: =N32+D32 | P32: SDV BELGIUM | Q32: =D32 | R32: 0 | S32: =Q32-R32 | T32: =Q32/R32-1 | V32: =Q32-U32 | W32: =(Q32/U32-1)
A33: SDV GHANA | C33: =D33-B33 | I33: =H33+G33 | N33: =J33+I33+F33+E33+L33+M33+K33 | O33: =N33+D33 | P33: SDV GHANA | Q33: =D33 | R33: 0 | S33: =Q33-R33 | T33: =Q33/R33-1 | V33: =Q33-U33 | W33: =(Q33/U33-1)
A34: SDV Usa | C34: =D34-B34 | I34: =H34+G34 | N34: =J34+I34+F34+E34+L34+M34+K34 | O34: =N34+D34 | P34: SDV Usa | Q34: =D34 | R34: 0 | S34: =Q34-R34 | T34: =Q34/R34-1 | V34: =Q34-U34 | W34: =(Q34/U34-1)
A35: BOLLORE SINGAPORE | C35: =D35-B35 | I35: =H35+G35 | N35: =J35+I35+F35+E35+L35+M35+K35 | O35: =N35+D35 | P35: SDV Logistic Singapore (Prosafe) | Q35: =D35 | R35: 166666.67 | S35: =Q35-R35 | T35: =Q35/R35-1 | U35: 297000 | V35: =Q35-U35 | W35: =(Q35/U35-1)
A36: BOLLORE DIVERS | C36: =D36-B36 | I36: =H36+G36 | N36: =J36+I36+F36+E36+L36+M36+K36 | O36: =N36+D36 | P36: SDV Pau | Q36: =D36 | R36: 0 | S36: =Q36-R36 | T36: =Q36/R36-1 | V36: =Q36-U36 | W36: =(Q36/U36-1)
A37: SUBSEA7 | C37: =D37-B37 | I37: =H37+G37 | N37: =J37+I37+F37+E37+L37+M37+K37 | O37: =N37+D37 | P37: SUBSEA7 | Q37: =D37 | R37: 0 | S37: =Q37-R37 | T37: =Q37/R37-1 | U37: 74500 | V37: =Q37-U37 | W37: =(Q37/U37-1)
A38: SCHLUMBERGER | C38: =D38-B38 | I38: =H38+G38 | N38: =J38+I38+F38+E38+L38+M38+K38 | O38: =N38+D38 | P38: SCHLUMBERGER | Q38: =D38 | R38: 44166667 | S38: =Q38-R38 | T38: =Q38/R38-1 | U38: 72038469 | V38: =Q38-U38 | W38: =(Q38/U38-1)
A39: Sapura Kencana Drilling | C39: =D39-B39 | I39: =H39+G39 | N39: =J39+I39+F39+E39+L39+M39+K39 | O39: =N39+D39 | P39: Sapura Kencana Drilling | Q39: =D39 | R39: 2083333.3 | S39: =Q39-R39 | T39: =Q39/R39-1 | U39: =602906+25000 | V39: =Q39-U39 | W39: =(Q39/U39-1)
A40: SIR P/C Subtec | C40: =D40-B40 | I40: =H40+G40 | N40: =J40+I40+F40+E40+L40+M40+K40 | O40: =N40+D40 | P40: SIR P/C Subtec | Q40: =D40 | R40: 166666.67 | S40: =Q40-R40 | T40: =Q40/R40-1 | U40: 1152605 | V40: =Q40-U40 | W40: =(Q40/U40-1)
A41: SMB | C41: =D41-B41 | I41: =H41+G41 | N41: =J41+I41+F41+E41+L41+M41+K41 | O41: =N41+D41 | P41: SMB | Q41: =D41 | R41: 0 | S41: =Q41-R41 | T41: =Q41/R41-1 | V41: =Q41-U41 | W41: =(Q41/U41-1)
A42: SUBTEC | C42: =D42-B42 | I42: =H42+G42 | N42: =J42+I42+F42+E42+L42+M42+K42 | O42: =N42+D42 | P42: SUBTEC | Q42: =D42 | R42: 1208333.3 | S42: =Q42-R42 | T42: =Q42/R42-1 | U42: 1098670 | V42: =Q42-U42 | W42: =(Q42/U42-1)
A43: Transocean | C43: =D43-B43 | I43: =H43+G43 | N43: =J43+I43+F43+E43+L43+M43+K43 | O43: =N43+D43 | P43: Transocean | Q43: =D43 | R43: 0 | S43: =Q43-R43 | T43: =Q43/R43-1 | V43: =Q43-U43 | W43: =(Q43/U43-1)
A44: Tetra | C44: =D44-B44 | D44: =B44 | I44: =H44+G44 | N44: =J44+I44+F44+E44+L44+M44+K44 | O44: =N44+D44 | P44: Tetra | Q44: =D44 | R44: 9583333.3 | S44: =Q44-R44 | T44: =Q44/R44-1 | U44: 11152340 | V44: =Q44-U44 | W44: =(Q44/U44-1)
A45: TOTAL E&P COTE D'IVOIRE | C45: =D45-B45 | D45: =B45 | I45: =H45+G45 | N45: =J45+I45+F45+E45+L45+M45+K45 | O45: =N45+D45 | P45: TOTAL E&P COTE D'IVOIRE | Q45: =D45 | R45: 18333333 | S45: =Q45-R45 | T45: =Q45/R45-1 | U45: =7553210+7557866 | V45: =Q45-U45 | W45: =(Q45/U45-1)
A46: Tullow Oil | C46: =D46-B46 | D46: =B46 | I46: =H46+G46 | N46: =J46+I46+F46+E46+L46+M46+K46 | O46: =N46+D46 | P46: Tullow Oil | Q46: =D46 | R46: 0 | S46: =Q46-R46 | T46: =Q46/R46-1 | V46: =Q46-U46 | W46: =(Q46/U46-1)
A47: VANCO/Lukoil | C47: =D47-B47 | D47: =B47 | I47: =H47+G47 | N47: =J47+I47+F47+E47+L47+M47+K47 | O47: =N47+D47 | P47: VANCO/Lukoil | Q47: =D47 | R47: 0 | S47: =Q47-R47 | T47: =Q47/R47-1 | V47: =Q47-U47 | W47: =(Q47/U47-1)
A48: Vantage | C48: =D48-B48 | D48: =B48 | I48: =H48+G48 | N48: =J48+I48+F48+E48+L48+M48+K48 | O48: =N48+D48 | P48: Vantage | Q48: =D48 | R48: 0 | S48: =Q48-R48 | T48: =Q48/R48-1 | V48: =Q48-U48 | W48: =(Q48/U48-1)
A49: WEATHERFORD | C49: =D49-B49 | D49: =B49 | I49: =H49+G49 | N49: =J49+I49+F49+E49+L49+M49+K49 | O49: =N49+D49 | P49: WEATHERFORD | Q49: =D49 | R49: 14750000 | S49: =Q49-R49 | T49: =Q49/R49-1 | U49: 29215540 | V49: =Q49-U49 | W49: =(Q49/U49-1)
A50: Weltec | C50: =D50-B50 | D50: =B50 | I50: =H50+G50 | N50: =J50+I50+F50+E50+L50+M50+K50 | O50: =N50+D50 | P50: Weltec | Q50: =D50 | R50: 0 | S50: =Q50-R50 | T50: =Q50/R50-1 | V50: =Q50-U50 | W50: =(Q50/U50-1)
A51: CA TOTAL | B51: =SUM(B4:B50) | C51: =SUM(C4:C50) | D51: =SUM(D4:D50) | E51: =SUM(E4:E50) | F51: =SUM(F5:F50) | G51: =SUM(G5:G50) | H51: =SUM(H5:H50) | I51: =SUM(I5:I50) | J51: =SUM(J5:J50) | L51: =SUM(L5:L50) | M51: =SUM(M5:M50) | N51: =J51+I51+F51+E51+L51+M51+K51 | O51: =N51+D51 | P51: ACTIVITE BASE | Q51: =SUM(Q4:Q50) | R51: =SUM(R4:R50) | S51: =Q51-R51 | T51: =Q51/R51-1 | U51: =SUM(U4:U50) | V51: =Q51-U51 | W51: =(Q51/U51-1)
A52: Rétrocession | D52: =E52+F52+I52+J52 | L52: NP | M52: NP | N52: =J52+I52+F52+E52 | P52: Rétrocessions
A53: Taux Rétrocession | E53: =E52/E51 | F53: =F52/F51 | I53: =I52/I51 | J53: =J52/J51 | N53: =N52/N51 | P53: IMAR | Q53: =E52 | S53: =Q53-R53 | T53: =Q53/R53-1 | U53: 13458008 | V53: =Q53-U53 | W53: =(Q53/U53-1)
A54: TOTAL Après rétrocession | D54: =D52+D51 | E54: =E51-E52 | F54: =F51-F52 | I54: =I51-I52 | J54: =J51-J52 | K54: =K51 | L54: =L51 | M54: =M51 | N54: =SUM(D54:M54) | P54: HINT | Q54: =F52 | S54: =Q54-R54 | T54: =Q54/R54-1 | U54: 0 | V54: =Q54-U54 | W54: =(Q54/U54-1)
P55: AER | Q55: =I52 | S55: =Q55-R55 | T55: =Q55/R55-1 | U55: =15961760-10390000 | V55: =Q55-U55 | W55: =(Q55/U55-1)
P56: EMAR | Q56: =J52 | S56: =Q56-R56 | T56: =Q56/R56-1 | U56: 5594159 | V56: =Q56-U56 | W56: =(Q56/U56-1)
P57: ACTIVITE O&G | Q57: =Q51+Q53+Q54+Q55+Q56 | R57: =R51+R53+R54+R55+R56 | S57: =S51+S53+S54+S55+S56 | T57: =Q57/R57-1 | U57: =U51+U53+U54+U55+U56 | V57: =V51+V53+V54+V55+V56 | W57: =(Q57/U57-1)
P58: R15 | R58: Variation Réel 15 / B15 | U58: Variation Réel 15 / Réel 14

Sheet Occupation (2)
B3: Base 1 (Oil & Gas Vridi) | C3: Oil & Gas ALCI
B4: Base 2 (Extension SEPBA) | C4: Occupied spaces | S4: Finance | Z4: Comments on last tariffs update
B5: SOUS BAIL | C5: Warehousing | F5: Yard Clay | I5: Yard Concrete | L5: Offices | O5: Shed
B6: Clients | C6: Superficie (sqm) | D6: Price per Sqm | E6: Amount | F6: Superficie (sqm) | G6: Price per Sqm | H6: Amount | I6: Superficie (sqm) | J6: Price per Sqm | K6: Amount | L6: Superficie (sqm) | M6: Price per Sqm | N6: Amount | O6: Superficie (sqm) | P6: Price per Sqm | Q6: Amount | R6: Reel2011 | S6: Reel 2011 € | T6: 2012 Forecast | U6: 2012 Forecast € | V6: Monthly Revenue | W6: 2013 Budget € | X6: Actually Invoiced | Y6: Difference
B7: Afritramp | E7: =D7*C7 | H7: =G7*F7 | K7: =J7*I7 | N7: =M7*L7 | Q7: =P7*O7 | R7: 288 | S7: =R7*1000/655.957 | T7: 0 | U7: =T7*1000/655.957 | V7: =Q7+N7+K7+H7+E7 | W7: =V7*1000/655.957 | Y7: =X7-V7
B8: ANADARKO | D8: 5000 | E8: =D8*C8 | F8: 5000 | G8: 1750 | H8: =G8*F8 | K8: =J8*I8 | N8: =M8*L8 | Q8: =P8*O8 | R8: =540+10776+6662 | S8: =R8*1000/655.957 | T8: 46700 | U8: =T8*1000/655.957 | V8: =Q8+N8+K8+H8+E8 | W8: =V8*1000/655.957 | X8: 8750000 | Y8: =X8-V8
B9: ANTRAK GHANA (Tullow Oil) | E9: =D9*C9 | H9: =G9*F9 | K9: =J9*I9 | N9: =M9*L9 | Q9: =P9*O9 | R9: 5851 | S9: =R9*1000/655.957 | T9: 9400 | U9: =T9*1000/655.957 | V9: =Q9+N9+K9+H9+E9 | W9: =V9*1000/655.957 | Y9: =X9-V9
B10: Baker Hugues | C10: 1166 | D10: 572 | E10: =D10*C10 | G10: 750 | H10: =G10*F10 | I10: 1786 | J10: 1150 | K10: =J10*I10 | L10: 92 | M10: 10000 | N10: =M10*L10 | P10: 1150 | Q10: =P10*O10 | R10: 57345 | S10: =R10*1000/655.957 | T10: 125500 | U10: =T10*1000/655.957 | V10: =Q10+N10+K10+H10+E10 | W10: =V10*1000/655.957 | X10: 5611000 | Y10: =X10-V10
B11: BOURBON | E11: =D11*C11 | H11: =G11*F11 | K11: =J11*I11 | N11: =M11*L11 | Q11: =P11*O11 | R11: 180 | S11: =R11*1000/655.957 | T11: 0 | U11: =T11*1000/655.957 | V11: =Q11+N11+K11+H11+E11 | W11: =V11*1000/655.957 | Y11: =X11-V11
B12: CGGVERITAS | E12: =D12*C12 | H12: =G12*F12 | K12: =J12*I12 | N12: =M12*L12 | Q12: =P12*O12 | S12: =R12*1000/655.957 | T12: 23500 | U12: =T12*1000/655.957 | V12: =Q12+N12+K12+H12+E12 | W12: =V12*1000/655.957 | Y12: =X12-V12
B13: CNR | C13: 2800 | D13: 2500 | E13: =D13*C13 | F13: 20000 | G13: 1250 | H13: =G13*F13 | K13: =J13*I13 | N13: =M13*L13 | Q13: =P13*O13 | R13: 95699 | S13: =R13*1000/655.957 | T13: 248000 | U13: =T13*1000/655.957 | V13: =Q13+N13+K13+H13+E13 | W13: =V13*1000/655.957 | X13: 29250000 | Y13: =X13-V13
B14: DIVERS/various custumers | E14: =D14*C14 | H14: =G14*F14 | K14: =J14*I14 | N14: =M14*L14 | Q14: =P14*O14 | R14: =1082+3497+19330 | S14: =R14*1000/655.957 | T14: 28500 | U14: =T14*1000/655.957 | V14: =Q14+N14+K14+H14+E14 | W14: =V14*1000/655.957 | Y14: =X14-V14
B15: DOLPHIN DRILLING | E15: =D15*C15 | H15: =G15*F15 | K15: =J15*I15 | N15: =M15*L15 | Q15: =P15*O15 | S15: =R15*1000/655.957 | T15: 0 | U15: =T15*1000/655.957 | V15: =Q15+N15+K15+H15+E15 | W15: =V15*1000/655.957 | Y15: =X15-V15
B16: EDISON INTERNATIONAL | E16: =D16*C16 | H16: =G16*F16 | K16: =J16*I16 | N16: =M16*L16 | Q16: =P16*O16 | R16: 71 | S16: =R16*1000/655.957 | T16: 0 | U16: =T16*1000/655.957 | V16: =Q16+N16+K16+H16+E16 | W16: =V16*1000/655.957 | Y16: =X16-V16
B17: EMAR | E17: =D17*C17 | H17: =G17*F17 | K17: =J17*I17 | N17: =M17*L17 | Q17: =P17*O17 | S17: =R17*1000/655.957 | U17: =T17*1000/655.957 | V17: =Q17+N17+K17+H17+E17 | W17: =V17*1000/655.957 | Y17: =X17-V17
B18: EXPRO GROUP NORTH SEA / S-Traitant | C18: 217 | E18: =D18*C18 | F18: 562 | H18: =G18*F18 | I18: 2114 | K18: =J18*I18 | L18: 216 | N18: =M18*L18 | O18: 351 | Q18: =P18*O18 | R18: 76767 | S18: =R18*1000/655.957 | T18: 73000 | U18: =T18*1000/655.957 | V18: =Q18+N18+K18+H18+E18 | W18: =V18*1000/655.957 | X18: 4784000 | Y18: =X18-V18
B19: FOXTROT | C19: 4500 | D19: 2500 | E19: =D19*C19 | F19: 1290 | G19: 550 | H19: =G19*F19 | I19: 3262 | J19: 1000 | K19: =J19*I19 | N19: =M19*L19 | Q19: =P19*O19 | R19: 118138 | S19: =R19*1000/655.957 | T19: 394740 | U19: =T19*1000/655.957 | V19: =Q19+N19+K19+H19+E19 | W19: =V19*1000/655.957 | X19: 6609000 | Y19: =X19-V19
B20: GLOBAL ENERGY | C20: 218.5 | D20: 2500 | E20: =D20*C20 | F20: 128 | G20: 1450 | H20: =G20*F20 | I20: 1037 | J20: 1450 | K20: =J20*I20 | L20: 25 | M20: 11500 | N20: =M20*L20 | O20: 103 | Q20: =P20*O20 | R20: 33944 | S20: =R20*1000/655.957 | T20: 77540 | U20: =T20*1000/655.957 | V20: =Q20+N20+K20+H20+E20 | W20: =V20*1000/655.957 | X20: 1890000 | Y20: =X20-V20
B21: Global forwarding DHL | E21: =D21*C21 | H21: =G21*F21 | K21: =J21*I21 | N21: =M21*L21 | Q21: =P21*O21 | R21: 835 | S21: =R21*1000/655.957 | T21: 0 | U21: =T21*1000/655.957 | V21: =Q21+N21+K21+H21+E21 | W21: =V21*1000/655.957 | Y21: =X21-V21
B22: Gulf OFFSHORE | E22: =D22*C22 | H22: =G22*F22 | K22: =J22*I22 | N22: =M22*L22 | Q22: =P22*O22 | S22: =R22*1000/655.957 | T22: 4600 | U22: =T22*1000/655.957 | V22: =Q22+N22+K22+H22+E22 | W22: =V22*1000/655.957 | Y22: =X22-V22
B23: HALLIBURTON | D23: 2500 | E23: =D23*C23 | H23: =G23*F23 | J23: 1570 | K23: =J23*I23 | L23: 94 | M23: 13000 | N23: =M23*L23 | Q23: =P23*O23 | R23: 100629 | S23: =R23*1000/655.957 | T23: 287780 | U23: =T23*1000/655.957 | V23: =Q23+N23+K23+H23+E23 | W23: =V23*1000/655.957 | X23: 7142000 | Y23: =X23-V23
B24: HINTERLAND | E24: =D24*C24 | H24: =G24*F24 | K24: =J24*I24 | N24: =M24*L24 | Q24: =P24*O24 | S24: =R24*1000/655.957 | U24: =T24*1000/655.957 | V24: =Q24+N24+K24+H24+E24 | W24: =V24*1000/655.957 | Y24: =X24-V24
B25: Intership | E25: =D25*C25 | H25: =G25*F25 | K25: =J25*I25 | N25: =M25*L25 | Q25: =P25*O25 | R25: 170 | S25: =R25*1000/655.957 | U25: =T25*1000/655.957 | V25: =Q25+N25+K25+H25+E25 | W25: =V25*1000/655.957 | Y25: =X25-V25
B26: KCAD | E26: =D26*C26 | H26: =G26*F26 | K26: =J26*I26 | N26: =M26*L26 | Q26: =P26*O26 | S26: =R26*1000/655.957 | T26: 43500 | U26: =T26*1000/655.957 | V26: =Q26+N26+K26+H26+E26 | W26: =V26*1000/655.957 | Y26: =X26-V26
B27: LGL | E27: =D27*C27 | H27: =G27*F27 | K27: =J27*I27 | N27: =M27*L27 | Q27: =P27*O27 | R27: 3733 | S27: =R27*1000/655.957 | U27: =T27*1000/655.957 | V27: =Q27+N27+K27+H27+E27 | W27: =V27*1000/655.957 | Y27: =X27-V27
B28: Lukoil | E28: =D28*C28 | H28: =G28*F28 | K28: =J28*I28 | N28: =M28*L28 | Q28: =P28*O28 | S28: =R28*1000/655.957 | T28: 7170 | U28: =T28*1000/655.957 | V28: =Q28+N28+K28+H28+E28 | W28: =V28*1000/655.957 | Y28: =X28-V28
B29: MICOPERI | E29: =D29*C29 | H29: =G29*F29 | K29: =J29*I29 | N29: =M29*L29 | Q29: =P29*O29 | R29: 73644 | S29: =R29*1000/655.957 | T29: 102000 | U29: =T29*1000/655.957 | V29: =Q29+N29+K29+H29+E29 | W29: =V29*1000/655.957 | X29: 12084000 | Y29: =X29-V29
B30: NOPCI - MODEC | E30: =D30*C30 | H30: =G30*F30 | K30: =J30*I30 | L30: 340 | M30: 5374 | N30: =M30*L30 | Q30: =P30*O30 | R30: 28646 | S30: =R30*1000/655.957 | T30: 22300 | U30: =T30*1000/655.957 | V30: =Q30+N30+K30+H30+E30 | W30: =V30*1000/655.957 | X30: =1368000+459096 | Y30: =X30-V30
B31: NOV | E31: =D31*C31 | H31: =G31*F31 | K31: =J31*I31 | N31: =M31*L31 | Q31: =P31*O31 | S31: =R31*1000/655.957 | T31: 1000 | U31: =T31*1000/655.957 | V31: =Q31+N31+K31+H31+E31 | W31: =V31*1000/655.957 | Y31: =X31-V31
B32: Ocean Rig | E32: =D32*C32 | H32: =G32*F32 | K32: =J32*I32 | N32: =M32*L32 | Q32: =P32*O32 | S32: =R32*1000/655.957 | T32: 10200 | U32: =T32*1000/655.957 | V32: =Q32+N32+K32+H32+E32 | W32: =V32*1000/655.957 | Y32: =X32-V32
B33: Rialto | E33: =D33*C33 | H33: =G33*F33 | K33: =J33*I33 | N33: =M33*L33 | Q33: =P33*O33 | S33: =R33*1000/655.957 | U33: =T33*1000/655.957 | V33: =Q33+N33+K33+H33+E33 | W33: =V33*1000/655.957 | Y33: =X33-V33
B34: SAPPHIRE DRILLER COMPANY | E34: =D34*C34 | H34: =G34*F34 | K34: =J34*I34 | N34: =M34*L34 | Q34: =P34*O34 | R34: 3954 | S34: =R34*1000/655.957 | T34: 75000 | U34: =T34*1000/655.957 | V34: =Q34+N34+K34+H34+E34 | W34: =V34*1000/655.957 | Y34: =X34-V34
B35: SAS | E35: =D35*C35 | H35: =G35*F35 | K35: =J35*I35 | N35: =M35*L35 | Q35: =P35*O35 | R35: 250 | S35: =R35*1000/655.957 | U35: =T35*1000/655.957 | V35: =Q35+N35+K35+H35+E35 | W35: =V35*1000/655.957 | Y35: =X35-V35
B36: Schlumberger (sous bail) | C36: 728 | D36: 3500 | E36: =D36*C36 | H36: =G36*F36 | I36: 830 | J36: 2000 | K36: =J36*I36 | V36: =Q36+N36+K36+H36+E36 | X36: 4208000 | Y36: =X36-V36
B37: Schlumberger | C37: 4000 | D37: 3000 | E37: =D37*C37 | F37: 392 | G37: 8000 | H37: =G37*F37 | I37: 2500 | J37: 1200 | K37: =J37*I37 | N37: =M37*L37 | Q37: =P37*O37 | R37: 6417 | S37: =R37*1000/655.957 | T37: 116400 | U37: =T37*1000/655.957 | V37: =Q37+N37+K37+H37+E37 | W37: =V37*1000/655.957 | X37: =15000000+3136000 | Y37: =X37-V37
B38: SDV Logisitc Singapore (Prosafe) | E38: =D38*C38 | H38: =G38*F38 | K38: =J38*I38 | N38: =M38*L38 | Q38: =P38*O38 | R38: 851 | S38: =R38*1000/655.957 | T38: 21000 | U38: =T38*1000/655.957 | V38: =Q38+N38+K38+H38+E38 | W38: =V38*1000/655.957 | Y38: =X38-V38
B39: SDV USA | E39: =D39*C39 | H39: =G39*F39 | K39: =J39*I39 | N39: =M39*L39 | Q39: =P39*O39 | R39: 65 | S39: =R39*1000/655.957 | T39: 8000 | U39: =T39*1000/655.957 | V39: =Q39+N39+K39+H39+E39 | W39: =V39*1000/655.957 | Y39: =X39-V39
B40: SIMEX | E40: =D40*C40 | H40: =G40*F40 | J40: 1000 | K40: =J40*I40 | L40: 26 | M40: 1815 | N40: =M40*L40 | Q40: =P40*O40 | S40: =R40*1000/655.957 | T40: 1430 | U40: =T40*1000/655.957 | V40: =Q40+N40+K40+H40+E40 | W40: =V40*1000/655.957 | X40: 182200 | Y40: =X40-V40 | Z40: Inclus TVA + éléctricité
B41: SIRT | E41: =D41*C41 | H41: =G41*F41 | K41: =J41*I41 | N41: =M41*L41 | Q41: =P41*O41 | S41: =R41*1000/655.957 | U41: =T41*1000/655.957 | V41: =Q41+N41+K41+H41+E41 | W41: =V41*1000/655.957 | Y41: =X41-V41
B42: SMB | E42: =D42*C42 | H42: =G42*F42 | K42: =J42*I42 | N42: =M42*L42 | Q42: =P42*O42 | R42: 15120 | S42: =R42*1000/655.957 | T42: 23000 | U42: =T42*1000/655.957 | V42: =Q42+N42+K42+H42+E42 | W42: =V42*1000/655.957 | Y42: =X42-V42
B43: SUBTEC/SIR | E43: =D43*C43 | F43: 405 | H43: =G43*F43 | I43: 1645 | K43: =J43*I43 | L43: 131 | N43: =M43*L43 | O43: 45 | Q43: =P43*O43 | R43: =1229+9289 | S43: =R43*1000/655.957 | T43: 12340 | U43: =T43*1000/655.957 | V43: 763750 | W43: =V43*1000/655.957 | X43: 763750 | Y43: =X43-V43
B44: Super maritime | E44: =D44*C44 | H44: =G44*F44 | K44: =J44*I44 | N44: =M44*L44 | Q44: =P44*O44 | R44: 394 | S44: =R44*1000/655.957 | U44: =T44*1000/655.957 | V44: =Q44+N44+K44+H44+E44 | W44: =V44*1000/655.957 | Y44: =X44-V44
B45: Tetra | D45: 3200 | E45: =D45*C45 | F45: 0 | G45: 750 | H45: =G45*F45 | I45: 450 | J45: 1500 | K45: =J45*I45 | L45: 16 | M45: 15000 | N45: =M45*L45 | O45: 0 | P45: 1150 | Q45: =P45*O45 | S45: =R45*1000/655.957 | T45: 16500 | U45: =T45*1000/655.957 | V45: =Q45+N45+K45+H45+E45 | W45: =V45*1000/655.957 | X45: 3087500 | Y45: =X45-V45
B46: Total E& P | C46: 200 | D46: 3000 | E46: =D46*C46 | F46: 3000 | G46: 1500 | H46: =G46*F46 | I46: 2500 | J46: 1500 | K46: =J46*I46 | L46: =169+23 | M46: 14000 | N46: =M46*L46 | Q46: =P46*O46 | S46: =R46*1000/655.957 | T46: 137000 | U46: =T46*1000/655.957 | V46: =Q46+N46+K46+H46+E46 | W46: =V46*1000/655.957 | X46: 17090000 | Y46: =X46-V46
B47: Transocean | E47: =D47*C47 | H47: =G47*F47 | K47: =J47*I47 | N47: =M47*L47 | Q47: =P47*O47 | R47: 1531 | S47: =R47*1000/655.957 | T47: 6600 | U47: =T47*1000/655.957 | V47: =Q47+N47+K47+H47+E47 | W47: =V47*1000/655.957 | Y47: =X47-V47
B48: Tullow Oil | E48: =D48*C48 | H48: =G48*F48 | I48: 4243 | J48: 3017 | K48: =J48*I48 | N48: =M48*L48 | Q48: =P48*O48 | V48: =Q48+N48+K48+H48+E48 | X48: 25828309 | Y48: =X48-V48
B49: Vantage | E49: =D49*C49 | H49: =G49*F49 | K49: =J49*I49 | N49: =M49*L49 | Q49: =P49*O49 | S49: =R49*1000/655.957 | U49: =T49*1000/655.957 | V49: =Q49+N49+K49+H49+E49 | W49: =V49*1000/655.957 | Y49: =X49-V49
B50: Weatherford | C50: 1300 | D50: 5000 | E50: =D50*C50 | H50: =G50*F50 | K50: =J50*I50 | L50: 119 | M50: 24000 | N50: =M50*L50 | Q50: =P50*O50 | R50: 220 | S50: =R50*1000/655.957 | U50: =T50*1000/655.957 | V50: =Q50+N50+K50+H50+E50 | W50: =V50*1000/655.957 | Y50: =X50-V50
B51: welltec | C51: 400 | E51: =D51*C51 | H51: =G51*F51 | K51: =J51*I51 | N51: =M51*L51 | Q51: =P51*O51 | S51: =R51*1000/655.957 | T51: 1300 | U51: =T51*1000/655.957 | V51: =Q51+N51+K51+H51+E51 | W51: =V51*1000/655.957 | Y51: =X51-V51
B52: TOTAL | C52: =SUM(C7:C51) | F52: =SUM(F7:F51) | I52: =SUM(I7:I51) | L52: =SUM(L7:L51) | O52: =SUM(O7:O51) | R52: =SUM(R7:R51) | S52: =SUM(S7:S51) | T52: =SUM(T7:T51) | U52: =SUM(U7:U51) | V52: =SUM(V7:V51) | W52: =SUM(W7:W51)
B54: Type Surface | C54: (Prix moyen)FCFA | D54: Surface Occupée(m²)
B55: Warehousing | C55: =AVERAGE(D7:D51) | D55: =C52
B56: Concrete Yard | C56: =AVERAGE(J7:J51) | D56: =I52
B57: Clay Yard | C57: =AVERAGE(G7:G51) | D57: =F52
B58: Offices | C58: =AVERAGE(M7:M51) | D58: =L52
B59: Shed | C59: =AVERAGE(P7:P51) | D59: =O52
D60: =SUM(D55:D59)

Sheet Gestion base logistique
A1: KCFA
B2: Janvier | E2: Février | H2: Mars | K2: Avril | N2: Mai | Q2: Juin | T2: Juillet | W2: Août | Z2: Septembre | AC2: Octobre | AF2: Novembre | AI2: Décembre | AL2: Fin décembre
B3: Prévu | C3: Réel | D3: Variation | E3: Prévu | F3: Réel | G3: Variation | H3: Prévu | I3: Réel | J3: Variation | K3: Prévu | L3: Réel | M3: Variation | N3: Prévu | O3: Réel | P3: Variation | Q3: Prévu | R3: Réel | S3: Variation | T3: Prévu | U3: Réel | V3: Variation | W3: Prévu | X3: Réel | Y3: Variation | Z3: Prévu | AA3: Réel | AB3: Variation | AC3: Prévu | AD3: Réel | AE3: Variation | AF3: Prévu | AG3: Réel | AH3: Variation | AI3: Prévu | AJ3: Réel | AK3: Variation | AL3: Prévu | AM3: Réel | AN3: Variation
A4: CAP NET (+) | B4: 383001.26 | E4: 423324.1 | H4: 370041.77 | K4: 410287.6 | N4: 366429.89 | Q4: 347047.59 | T4: 412800.49 | W4: 368163.67 | Z4: 344917.99 | AC4: 357441.1 | AF4: 474908.08 | AI4: 421438.13 | AL4: 4679801.7
A5: Salaires & charges de personnel (-) | B5: -30458.855 | E5: -30458.855 | H5: -30458.855 | K5: -30458.855 | N5: -30458.855 | Q5: -30458.855 | T5: -30458.855 | W5: -30458.855 | Z5: -30458.855 | AC5: -30458.855 | AF5: -30458.855 | AI5: -30459.006 | AL5: -365506.41
A6: Frais de personnel temporaire (-) | B6: -28759.291 | E6: -28759.291 | H6: -28759.291 | K6: -28759.291 | N6: -28759.291 | Q6: -28759.291 | T6: -28759.291 | W6: -28759.291 | Z6: -28759.291 | AC6: -28759.291 | AF6: -28759.291 | AI6: -28759.431 | AL6: -345111.63
A7: Dotations nettes aux amortissements (+/-) | B7: -18286.979 | E7: -18286.979 | H7: -18286.979 | K7: -18286.979 | N7: -18286.979 | Q7: -18286.979 | T7: -18286.979 | W7: -18286.979 | Z7: -18286.979 | AC7: -18286.979 | AF7: -18286.979 | AI7: -18287.035 | AL7: -219443.81
A8: Frais postaux et télécommunications (-) | B8: -1807.8701 | E8: -1807.8701 | H8: -1807.8701 | K8: -1807.8701 | N8: -1807.8701 | Q8: -1807.8701 | T8: -1807.8701 | W8: -1807.8701 | Z8: -1807.8701 | AC8: -1807.8701 | AF8: -1807.8701 | AI8: -1807.8741 | AL8: -21694.445
A9: Autres locations (-) | B9: -110987.58 | E9: -124861.03 | H9: -110987.58 | K9: -138734.47 | N9: -110987.58 | Q9: -97114.132 | T9: -124861.03 | W9: -110987.58 | Z9: -97114.132 | AC9: -97114.132 | AF9: -152607.92 | AI9: -110987.58 | AL9: -1387344.7
A10: Entretien et réparations (-) | B10: -14115.066 | E10: -15616.301 | H10: -12441.274 | K10: -18756.817 | N10: -13511.12 | Q10: -10853.761 | T10: -15219.423 | W10: -12855.408 | Z10: -11026.317 | AC10: -11492.217 | AF10: -21138.087 | AI10: -15530.023 | AL10: -172555.81
A11: Frais de consommables (-) | B11: -22137.591 | E11: -24492.078 | H11: -19512.474 | K11: -29417.557 | N11: -21190.384 | Q11: -17022.671 | T11: -23869.628 | W11: -20161.987 | Z11: -17293.302 | AC11: -18024.005 | AF11: -33152.261 | AI11: -24356.763 | AL11: -270630.7
A12: Frais de sous-traitance (-) | B12: -20244.808 | E12: -20244.808 | H12: -20244.808 | K12: -20244.808 | N12: -20244.808 | Q12: -20244.808 | T12: -20244.808 | W12: -20244.808 | Z12: -20244.808 | AC12: -20244.808 | AF12: -20244.808 | AI12: -20244.904 | AL12: -242937.79
A13: Assurances (primes, indemnités) (-) | B13: -3040.8863 | E13: -3040.8863 | H13: -3040.8863 | K13: -3040.8863 | N13: -3040.8863 | Q13: -3040.8863 | T13: -3040.8863 | W13: -3040.8863 | Z13: -3040.8863 | AC13: -3040.8863 | AF13: -3040.8863 | AI13: -3040.9063 | AL13: -36490.656
A14: Impôts et taxes (-) | B14: -19732.727 | E14: -19732.727 | H14: -19732.727 | K14: -19732.727 | N14: -19732.727 | Q14: -19732.727 | T14: -11565.518 | W14: -11565.518 | Z14: -11565.518 | AC14: -11565.518 | AF14: -11565.518 | AI14: -11527.968 | AL14: -187751.92
A15: Frais de région (-) | B15: 0 | E15: 0 | H15: 0 | K15: 0 | N15: 0 | Q15: 0 | T15: 0 | W15: 0 | Z15: 0 | AC15: 0 | AF15: 0 | AI15: 0 | AL15: 0
... A34: Résultat opérationnel avant allocation (+/-) | B34: 105498.3 | E34: 128091.98 | H34: 96837.722 | K34: 93116.035 | N34: 90478.091 | Q34: 91794.314 | T34: 126754.9 | W34: 102063.18 | Z34: 97388.731 | AC34: 108715.24 | AF34: 145914.31 | AI34: 148505.3 | AL34: 1335158.1
A35: Part du CA Net annuel | B35: =B4/$AL$4 | E35: =E4/$AL$4 | H35: =H4/$AL$4 | K35: =K4/$AL$4 | N35: =N4/$AL$4 | Q35: =Q4/$AL$4 | T35: =T4/$AL$4 | W35: =W4/$AL$4 | Z35: =Z4/$AL$4 | AC35: =AC4/$AL$4 | AF35: =AF4/$AL$4 | AI35: =AI4/$AL$4

Sheet Récap Global
B1: CAP Généré par Département sur Clients O&G (Après rétrocessions)
C3: Base O&G | D3: Import Maritime | E3: Hinterland | F3: Aérien | G3: Export Maritime | H3: Afritramp | I3: Meet & Greet | J3: SIRT / LEVAGE | K3: TOTAL GENERE
B4: Janvier | C4: =Janvier!$D$54 | D4: =Janvier!$E$54 | E4: =Janvier!$F$54 | F4: =Janvier!$I$54 | G4: =Janvier!$J$54 | H4: =Janvier!$L$54 | I4: =Janvier!$M$54 | J4: =Janvier!$K$54 | K4: =SUM(C4:J4)
B5: Février | C5: =Février!$D$54 | D5: =Février!$E$54 | E5: =Février!$F$54 | F5: =Février!$I$54 | G5: =Février!$J$54 | H5: =Février!$L$54 | I5: =Février!$M$54 | J5: =Février!$K$54 | K5: =SUM(C5:J5)
B6: Mars | C6: =Mars!$D$54 | D6: =Mars!$E$54 | E6: =Mars!$F$54 | F6: =Mars!$I$54 | G6: =Mars!$J$54 | H6: =Mars!$L$54 | I6: =Mars!$M$54 | J6: =Mars!$K$54 | K6: =SUM(C6:J6)
B7: Avril | C7: =Avril!$D$54 | D7: =Avril!$E$54 | E7: =Avril!$F$54 | F7: =Avril!$I$54 | G7: =Avril!$J$54 | H7: =Avril!$L$54 | I7: =Avril!$M$54 | J7: =Avril!$K$54 | K7: =SUM(C7:J7)
B8: Mai | C8: =Mai!$D$54 | D8: =Mai!$E$54 | E8: =Mai!$F$54 | F8: =Mai!$I$54 | G8: =Mai!$J$54 | H8: =Mai!$L$54 | I8: =Mai!$M$54 | J8: =Mai!$K$54 | K8: =SUM(C8:J8)
B9: Juin | C9: =Juin!$D$54 | D9: =Juin!$E$54 | E9: =Juin!$F$54 | F9: =Juin!$I$54 | G9: =Juin!$J$54 | H9: =Juin!$L$54 | I9: =Juin!$M$54 | J9: =Juin!$K$54 | K9: =SUM(C9:J9)
B10: Juillet | C10: =Juillet!$D$54 | D10: =Juillet!$E$54 | E10: =Juillet!$F$54 | F10: =Juillet!$I$54 | G10: =Juillet!$J$54 | H10: =Juillet!$L$54 | I10: =Juillet!$M$54 | J10: =Juillet!$K$54 | K10: =SUM(C10:J10)
B11: Août | C11: =Aout!$D$54 | D11: =Aout!$E$54 | E11: =Aout!$F$54 | F11: =Aout!$I$54 | G11: =Aout!$J$54 | H11: =Aout!$L$54 | I11: =Aout!$M$54 | J11: =Aout!$K$54 | K11: =SUM(C11:J11)
B12: Septembre | C12: =Septembre!$D$54 | D12: =Septembre!$E$54 | E12: =Septembre!$F$54 | F12: =Septembre!$I$54 | G12: =Septembre!$J$54 | H12: =Septembre!$L$54 | I12: =Septembre!$M$54 | J12: =Septembre!$K$54 | K12: =SUM(C12:J12)
B13: Octobre | C13: =Octobre!$D$54 | D13: =Octobre!$E$54 | E13: =Octobre!$F$54 | F13: =Octobre!$I$54 | G13: =Octobre!$J$54 | H13: =Octobre!$L$54 | I13: =Octobre!$M$54 | J13: =Octobre!$K$54 | K13: =SUM(C13:J13)
B14: Novembre | C14: =Novembre!$D$54 | D14: =Novembre!$E$54 | E14: =Novembre!$F$54 | F14: =Novembre!$I$54 | G14: =Novembre!$J$54 | H14: =Novembre!$L$54 | I14: =Novembre!$M$54 | J14: =Novembre!$K$54 | K14: =SUM(C14:J14)
B15: Décembre | C15: =Décembre!$D$54 | D15: =Décembre!$E$54 | E15: =Décembre!$F$54 | F15: =Décembre!$I$54 | G15: =Décembre!$J$54 | H15: =Décembre!$L$54 | I15: =Décembre!$M$54 | J15: =Décembre!$K$54 | K15: =SUM(C15:J15)
B16: Cumul | C16: =SUM(C4:C15) | D16: =SUM(D4:D15) | E16: =SUM(E4:E15) | F16: =SUM(F4:F15) | G16: =SUM(G4:G15) | H16: =SUM(H4:H15) | I16: =SUM(I4:I15) | J16: =SUM(J4:J15) | K16: =SUM(C16:J16)
B17: Part | C17: =C16/$K$16 | D17: =D16/$K$16 | E17: =E16/$K$16 | F17: =F16/$K$16 | G17: =G16/$K$16 | H17: =H16/$K$16 | I17: =I16/$K$16 | J17: =J16/$K$16
B20: RO Généré par Département sur Clients O&G (Après rétrocessions)
C22: Base O&G | D22: Import Maritime | E22: Hinterland | F22: Aérien | G22: Export Maritime | H22: Afritramp | I22: Meet & Greet | J22: SIRT / LEVAGE | K22: TOTAL GENERE
B23: Janvier | K23: =K24/K4
C24: 58198 | D24: =D23*D4 | E24: =E23*E4 | F24: =F23*F4 | G24: =G23*G4 | H24: =H23*H4 | I24: =I23*I4 | J24: =J23*J4 | K24: =SUM(C24:J24)
B25: Février | K25: =K26/K5
C26: 76867 | D26: =D25*D5 | E26: =E25*E5 | F26: =F25*F5 | G26: =G25*G5 | H26: =H25*H5 | I26: =I25*I5 | J26: =J25*J5 | K26: =SUM(C26:J26)
B27: Mars | K27: =K28/K6
C28: 37939 | D28: =D27*D6 | E28: =E27*E6 | F28: =F27*F6 | G28: =G27*G6 | H28: =H27*H6 | I28: =I27*I6 | J28: =J27*J6 | K28: =SUM(C28:J28)
B29: Avril | K29: =K30/#REF!
C30: 39815 | D30: =D29*#REF! | E30: =E29*#REF! | F30: =F29*#REF! | G30: =G29*#REF! | H30: =H29*#REF! | I30: =I29*#REF! | J30: =J29*#REF! | K30: =SUM(C30:J30)
B31: Mai | K31: =K32/#REF!
C32: 59120 | D32: =D31*#REF! | E32: =E31*#REF! | F32: =F31*#REF! | G32: =G31*#REF! | H32: =H31*#REF! | I32: =I31*#REF! | J32: =J31*#REF! | K32: =SUM(C32:J32)
B33: Juin | K33: =K34/#REF!
C34: 44460 | D34: =D33*#REF! | E34: =E33*#REF! | F34: =F33*#REF! | G34: =G33*#REF! | H34: =H33*#REF! | I34: =I33*#REF! | J34: =J33*#REF! | K34: =SUM(C34:J34)
B35: Juillet | K35: =K36/#REF!
C36: 19556 | D36: =D35*#REF! | E36: =E35*#REF! | F36: =F35*#REF! | G36: =G35*#REF! | H36: =H35*#REF! | I36: =I35*#REF! | J36: =J35*#REF! | K36: =SUM(C36:J36)
B37: Août | K37: =K38/#REF!
C38: 41107 | D38: =D37*#REF! | E38: =E37*#REF! | F38: =F37*#REF! | G38: =G37*#REF! | H38: =H37*#REF! | I38: =I37*#REF! | J38: =J37*#REF! | K38: =SUM(C38:J38)
B39: Septembre | K39: =K40/#REF!
C40: 37394 | D40: =D39*#REF! | E40: =E39*#REF! | F40: =F39*#REF! | G40: =G39*#REF! | H40: =H39*#REF! | I40: =I39*#REF! | J40: =J39*#REF! | K40: =SUM(C40:J40)
B41: Octobre | K41: =K42/#REF!
C42: 70199 | D42: =D41*#REF! | E42: =E41*#REF! | F42: =F41*#REF! | G42: =G41*#REF! | H42: =H41*#REF! | I42: =I41*#REF! | J42: =J41*#REF! | K42: =SUM(C42:J42)
B43: Novembre | K43: =K44/#REF!
C44: 41339 | D44: =D43*#REF! | E44: =E43*#REF! | F44: =F43*#REF! | G44: =G43*#REF! | H44: =H43*#REF! | I44: =I43*#REF! | J44: =J43*#REF! | K44: =SUM(C44:J44)
B45: Décembre | K45: =K46/#REF!
C46: =C45*#REF! | D46: =D45*#REF! | E46: =E45*#REF! | F46: =F45*#REF! | G46: =G45*#REF! | H46: =H45*#REF! | I46: =I45*#REF! | J46: =J45*#REF! | K46: =SUM(C46:J46)
B47: Cumul | C47: =C46+C44+C42+C40+C38+C36+C34+C32+C30+C28+C26+C24 | D47: =D46+D44+D42+D40+D38+D36+D34+D32+D30+D28+D26+D24 | E47: =E46+E44+E42+E40+E38+E36+E34+E32+E30+E28+E26+E24 | F47: =F46+F44+F42+F40+F38+F36+F34+F32+F30+F28+F26+F24 | G47: =G46+G44+G42+G40+G38+G36+G34+G32+G30+G28+G26+G24 | H47: =H46+H44+H42+H40+H38+H36+H34+H32+H30+H28+H26+H24 | I47: =I46+I44+I42+I40+I38+I36+I34+I32+I30+I28+I26+I24 | J47: =J46+J44+J42+J40+J38+J36+J34+J32+J30+J28+J26+J24 | K47: =SUM(C47:J47)
B48: Part | C48: =C47/$K$47 | D48: =D47/$K$47 | E48: =E47/$K$47 | F48: =F47/$K$47 | G48: =G47/$K$47 | H48: =H47/$K$47 | I48: =I47/$K$47 | J48: =J47/$K$47
B49: RO cumulé par activité | C49: =C47/C16 | D49: =D47/D16 | E49: =E47/E16 | F49: =F47/F16 | G49: =G47/G16 | H49: =H47/H16 | I49: =I47/I16 | J49: =J47/J16 | K49: =K47/K16

Sheet Cumul annuel
A1: 1 | B1: CAP Cumulé 2021 | O1: VARIATION R 23 sur B23 | AS1: VARIATION R 16 sur PFA 8 + 4 2016
B2: BASE | E2: CA GENERE | N2: GW Margin EURO | O2: R23 Cumulé | S2: Variation Réel 23 Cumulé / B23 Prorata | X2: Variation Réel 23 CUMULE / B23 COMPLET | AD2: Variation Réel 15 CUMULE / PFA 4+ 8 2015 COMPLET | AI2: Variation Réel 15 CUMULE / PFA 8+ 4 2015 COMPLET | AN2: Variation Réel 15 CUMULE / PFA 8+ 4 2015 Prorata | AS2: Variation B 16 PFA 4 + 8 / B16 COMPLET | AX2: Variation Reel 2016 / B 16 PFA 8 + 4 Prorata | BC2: Variation Reel 2016 / B 16 PFA 8 + 4 COMPLET
B3: LOYERS | C3: Plog & Divers | D3: Total BASE | E3: IMAR | F3: HINT | G3: IAER | H3: EAER | I3: AERIEN | J3: EXPORT | K3: SIRT (dédié) | L3: CA Dpt Ext | M3: CA TOTAL GENERE PAR CLIENT | O3: Sources revenus | P3: R23 Loyer | Q3: R21 Log & divers | R3: TOTAL R23 | S3: B20 Loyer | T3: B20 Log & divers | U3: Budget 2023 | V3: VAR (FCFA) | W3: Var (%) | X3: B23 Loyer | Y3: B23Log & divers | Z3: Budget 2023 | AA3: VAR (FCFA) | AB3: Var (%) | AD3: PFA Loyer | AE3: PFA Log & divers | AF3: PFA 4 + 8 2015 | AG3: VAR (FCFA) | AH3: Var (%) | AI3: PFA Loyer | AJ3: PFA Log & divers | AK3: PFA 8 + 4 2015 | AL3: VAR (FCFA) | AM3: Var (%) | AN3: PFA Loyer | AO3: PFA Log & divers | AP3: PFA 8 + 4 2015 | AQ3: VAR (FCFA) | AR3: Var (%) | AS3: PFA Loyer | AT3: PFA Log & divers | AU3: PFA 4 + 8 2016 | AV3: VAR (FCFA) | AW3: Var (%) | AX3: PFA Loyer | AY3: PFA Log & divers | AZ3: PFA 4 + 8 2016 | BA3: VAR (FCFA) | BB3: Var (%) | BC3: PFA Loyer | BD3: PFA Log & divers | BE3: PFA 4 + 8 2016 | BF3: VAR (FCFA) | BG3: Var (%)
A4: NAVITRANS (ex CIAM) | B4: =Janvier!B4+Février!B4+Mars!B4+Avril!B4+Mai!B4+Juin!B4+Juillet!B4+Aout!B4+Septembre!B4+Octobre!B4+Novembre!B4+Décembre!B4 | C4: =Janvier!C4+Février!C4+Mars!C4+Avril!C4+Mai!C4+Juin!C4+Juillet!C4+Aout!C4+Septembre!C4+Octobre!C4+Novembre!C4+Décembre!C4 | D4: =Janvier!D4+Février!D4+Mars!D4+Avril!D4+Mai!D4+Juin!D4+Juillet!D4+Aout!D4+Septembre!D4+Octobre!D4+Novembre!D4+Décembre!D4 | E4: =Janvier!E4+Février!E4+Mars!E4+Avril!E4+Mai!E4+Juin!E4+Juillet!E4+Aout!E4+Septembre!E4+Octobre!E4+Novembre!E4+Décembre!E4 | F4: =Janvier!F4+Février!F4+Mars!F4+Avril!F4+Mai!F4+Juin!F4+Juillet!F4+Aout!F4+Septembre!F4+Octobre!F4+Novembre!F4+Décembre!F4 | G4: =Janvier!G4+Février!G4+Mars!G4+Avril!G4+Mai!G4+Juin!G4+Juillet!G4+Aout!G4+Septembre!G4+Octobre!G4+Novembre!G4+Décembre!G4 | H4: =Janvier!H4+Février!H4+Mars!H4+Avril!H4+Mai!H4+Juin!H4+Juillet!H4+Aout!H4+Septembre!H4+Octobre!H4+Novembre!H4+Décembre!H4 | I4: =Janvier!I4+Février!I4+Mars!I4+Avril!I4+Mai!I4+Juin!I4+Juillet!I4+Aout!I4+Septembre!I4+Octobre!I4+Novembre!I4+Décembre!I4 | J4: =Janvier!J4+Février!J4+Mars!J4+Avril!J4+Mai!J4+Juin!J4+Juillet!J4+Aout!J4+Septembre!J4+Octobre!J4+Novembre!J4+Décembre!J4 | L4: =SUM(E4:F4,I4:K4) | M4: =L4+D4 | N4: =M4/655.957 | O4: =A4 | P4: =B4 | Q4: =C4 | R4: =D4 | S4: =X4/12*$A$1 | T4: =Y4/12*$A$1 | U4: 833333 | V4: =$R4-U4 | W4: =R4/U4-1 | X4: 0 | Y4: 15000000 | Z4: =Y4+X4 | AA4: =R4-Z4 | AB4: =R4/Z4-1 | AC4: =Z4/$Z$57 | AD4: 0 | AE4: =AF4-AD4 | AF4: 0 | AG4: =R4-AF4 | AH4: =R4/AF4-1 | AI4: 0 | AJ4: =AK4-AI4 | AK4: 0 | AL4: =R4-AK4 | AM4: 0 | AN4: =AI4/12*$A$1 | AO4: =AJ4/12*$A$1 | AP4: =AO4+AN4 | AQ4: =R4-AP4 | AR4: 0 | AT4: 20000000 | AU4: =AT4+AS4 | AV4: =AU4-Z4 | AW4: =AU4/Z4-1 | AX4: =BC4/12*$A$1 | AY4: =BD4/12*$A$1 | AZ4: =AY4+AX4 | BA4: =$R4-AZ4 | BB4: =$R4/AZ4-1 | BD4: 30000000 | BE4: =BD4+BC4 | BF4: =$R4-BE4 | BG4: =$R4/BE4-1
A5: DRIL QUIP | B5: =Janvier!B5+Février!B5+Mars!B5+Avril!B5+Mai!B5+Juin!B5+Juillet!B5+Aout!B5+Septembre!B5+Octobre!B5+Novembre!B5+Décembre!B5 | C5: =Janvier!C5+Février!C5+Mars!C5+Avril!C5+Mai!C5+Juin!C5+Juillet!C5+Aout!C5+Septembre!C5+Octobre!C5+Novembre!C5+Décembre!C5 | D5: =Janvier!D5+Février!D5+Mars!D5+Avril!D5+Mai!D5+Juin!D5+Juillet!D5+Aout!D5+Septembre!D5+Octobre!D5+Novembre!D5+Décembre!D5 | E5: =Janvier!E5+Février!E5+Mars!E5+Avril!E5+Mai!E5+Juin!E5+Juillet!E5+Aout!E5+Septembre!E5+Octobre!E5+Novembre!E5+Décembre!E5 | F5: =Janvier!F5+Février!F5+Mars!F5+Avril!F5+Mai!F5+Juin!F5+Juillet!F5+Aout!F5+Septembre!F5+Octobre!F5+Novembre!F5+Décembre!F5 | G5: =Janvier!G5+Février!G5+Mars!G5+Avril!G5+Mai!G5+Juin!G5+Juillet!G5+Aout!G5+Septembre!G5+Octobre!G5+Novembre!G5+Décembre!G5 | H5: =Janvier!H5+Février!H5+Mars!H5+Avril!H5+Mai!H5+Juin!H5+Juillet!H5+Aout!H5+Septembre!H5+Octobre!H5+Novembre!H5+Décembre!H5 | I5: =Janvier!I5+Février!I5+Mars!I5+Avril!I5+Mai!I5+Juin!I5+Juillet!I5+Aout!I5+Septembre!I5+Octobre!I5+Novembre!I5+Décembre!I5 | J5: =Janvier!J5+Février!J5+Mars!J5+Avril!J5+Mai!J5+Juin!J5+Juillet!J5+Aout!J5+Septembre!J5+Octobre!J5+Novembre!J5+Décembre!J5 | L5: =SUM(E5:F5,I5:K5) | M5: =L5+D5 | N5: =M5/655.957 | O5: =A5 | P5: =B5 | Q5: =C5 | R5: =D5 | S5: =X5/12*$A$1 | T5: =Y5/12*$A$1 | U5: 0 | V5: =$R5-U5 | W5: =R5/U5-1 | X5: 0 | Y5: 0 | Z5: =Y5+X5 | AA5: =R5-Z5 | AB5: =R5/Z5-1 | AC5: =Z5/$Z$57 | AE5: =AF5-AD5 | AF5: 220000 | AG5: =R5-AF5 | AH5: =R5/AF5-1 | AJ5: =AK5-AI5 | AK5: 220000 | AL5: =R5-AK5 | AM5: =R5/AK5-1 | AN5: =AI5/12*$A$1 | AO5: =AJ5/12*$A$1 | AP5: =AO5+AN5 | AQ5: =R5-AP5 | AR5: =R5/AP5-1 | AU5: =AT5+AS5 | AV5: =AU5-Z5 | AW5: =AU5/Z5-1 | AX5: =BC5/12*$A$1 | AY5: =BD5/12*$A$1 | AZ5: =AY5+AX5 | BA5: =$R5-AZ5 | BB5: =$R5/AZ5-1 | BE5: =BD5+BC5 | BF5: =$R5-BE5 | BG5: =$R5/BE5-1
A6: BORR GERD | B6: =Janvier!B6+Février!B6+Mars!B6+Avril!B6+Mai!B6+Juin!B6+Juillet!B6+Aout!B6+Septembre!B6+Octobre!B6+Novembre!B6+Décembre!B6 | C6: =Janvier!C6+Février!C6+Mars!C6+Avril!C6+Mai!C6+Juin!C6+Juillet!C6+Aout!C6+Septembre!C6+Octobre!C6+Novembre!C6+Décembre!C6 | D6: =Janvier!D6+Février!D6+Mars!D6+Avril!D6+Mai!D6+Juin!D6+Juillet!D6+Aout!D6+Septembre!D6+Octobre!D6+Novembre!D6+Décembre!D6 | E6: =Janvier!E6+Février!E6+Mars!E6+Avril!E6+Mai!E6+Juin!E6+Juillet!E6+Aout!E6+Septembre!E6+Octobre!E6+Novembre!E6+Décembre!E6 | F6: =Janvier!F6+Février!F6+Mars!F6+Avril!F6+Mai!F6+Juin!F6+Juillet!F6+Aout!F6+Septembre!F6+Octobre!F6+Novembre!F6+Décembre!F6 | G6: =Janvier!G6+Février!G6+Mars!G6+Avril!G6+Mai!G6+Juin!G6+Juillet!G6+Aout!G6+Septembre!G6+Octobre!G6+Novembre!G6+Décembre!G6 | H6: =Janvier!H6+Février!H6+Mars!H6+Avril!H6+Mai!H6+Juin!H6+Juillet!H6+Aout!H6+Septembre!H6+Octobre!H6+Novembre!H6+Décembre!H6 | I6: =Janvier!I6+Février!I6+Mars!I6+Avril!I6+Mai!I6+Juin!I6+Juillet!I6+Aout!I6+Septembre!I6+Octobre!I6+Novembre!I6+Décembre!I6 | J6: =Janvier!J6+Février!J6+Mars!J6+Avril!J6+Mai!J6+Juin!J6+Juillet!J6+Aout!J6+Septembre!J6+Octobre!J6+Novembre!J6+Décembre!J6 | L6: =SUM(E6:F6,I6:K6) | M6: =L6+D6 | N6: =M6/655.957 | O6: =A6 | P6: =B6 | Q6: =C6 | R6: =D6 | S6: =X6/12*$A$1 | T6: =Y6/12*$A$1 | U6: 0 | V6: =$R6-U6 | W6: =R6/U6-1 | X6: 0 | Y6: 10000000 | Z6: =Y6+X6 | AA6: =R6-Z6 | AB6: =R6/Z6-1 | AC6: =Z6/$Z$57 | AD6: 105000000 | AE6: =AF6-AD6 | AF6: 250000000 | AG6: =R6-AF6 | AH6: =R6/AF6-1 | AI6: 105000000 | AJ6: =AK6-AI6 | AK6: 165000000 | AL6: =R6-AK6 | AM6: =R6/AK6-1 | AN6: =AI6/12*$A$1 | AO6: =AJ6/12*$A$1 | AP6: =AO6+AN6 | AQ6: =R6-AP6 | AR6: =R6/AP6-1 | AS6: =8500000*12 | AT6: =28000000+6000000*5 | AU6: =AT6+AS6 | AV6: =AU6-Z6 | AW6: =AU6/Z6-1 | AX6: =BC6/12*$A$1 | AY6: =BD6/12*$A$1 | AZ6: =AY6+AX6 | BA6: =$R6-AZ6 | BB6: =$R6/AZ6-1 | BC6: =8500000*12+600000 | BD6: 270000000 | BE6: =BD6+BC6 | BF6: =$R6-BE6 | BG6: =$R6/BE6-1
A7: BAKER HUGHUES | B7: =Janvier!B7+Février!B7+Mars!B7+Avril!B7+Mai!B7+Juin!B7+Juillet!B7+Aout!B7+Septembre!B7+Octobre!B7+Novembre!B7+Décembre!B7 | C7: =Janvier!C7+Février!C7+Mars!C7+Avril!C7+Mai!C7+Juin!C7+Juillet!C7+Aout!C7+Septembre!C7+Octobre!C7+Novembre!C7+Décembre!C7 | D7: =Janvier!D7+Février!D7+Mars!D7+Avril!D7+Mai!D7+Juin!D7+Juillet!D7+Aout!D7+Septembre!D7+Octobre!D7+Novembre!D7+Décembre!D7 | E7: =Janvier!E7+Février!E7+Mars!E7+Avril!E7+Mai!E7+Juin!E7+Juillet!E7+Aout!E7+Septembre!E7+Octobre!E7+Novembre!E7+Décembre!E7 | F7: =Janvier!F7+Février!F7+Mars!F7+Avril!F7+Mai!F7+Juin!F7+Juillet!F7+Aout!F7+Septembre!F7+Octobre!F7+Novembre!F7+Décembre!F7 | G7: =Janvier!G7+Février!G7+Mars!G7+Avril!G7+Mai!G7+Juin!G7+Juillet!G7+Aout!G7+Septembre!G7+Octobre!G7+Novembre!G7+Décembre!G7 | H7: =Janvier!H7+Février!H7+Mars!H7+Avril!H7+Mai!H7+Juin!H7+Juillet!H7+Aout!H7+Septembre!H7+Octobre!H7+Novembre!H7+Décembre!H7 | I7: =Janvier!I7+Février!I7+Mars!I7+Avril!I7+Mai!I7+Juin!I7+Juillet!I7+Aout!I7+Septembre!I7+Octobre!I7+Novembre!I7+Décembre!I7 | J7: =Janvier!J7+Février!J7+Mars!J7+Avril!J7+Mai!J7+Juin!J7+Juillet!J7+Aout!J7+Septembre!J7+Octobre!J7+Novembre!J7+Décembre!J7 | L7: =SUM(E7:F7,I7:K7) | M7: =L7+D7 | N7: =M7/655.957 | O7: =A7 | P7: =B7 | Q7: =C7 | R7: =D7 | S7: =X7/12*$A$1 | T7: =Y7/12*$A$1 | U7: 7250000 | V7: =$R7-U7 | W7: =R7/U7-1 | X7: 75000000 | Y7: 50000000 | Z7: =Y7+X7 | AA7: =R7-Z7 | AB7: =R7/Z7-1 | AC7: =Z7/$Z$57 | AD7: 86000000 | AE7: =AF7-AD7 | AF7: 140000000 | AG7: =R7-AF7 | AH7: =R7/AF7-1 | AI7: 86000000 | AJ7: =AK7-AI7 | AK7: 111000000 | AL7: =R7-AK7 | AM7: =R7/AK7-1 | AN7: =AI7/12*$A$1 | AO7: =AJ7/12*$A$1 | AP7: =AO7+AN7 | AQ7: =R7-AP7 | AR7: =R7/AP7-1 | AS7: =16833000*4 | AT7: 45000000 | AU7: =AT7+AS7 | AV7: =AU7-Z7 | AW7: =AU7/Z7-1 | AX7: =BC7/12*$A$1 | AY7: =BD7/12*$A$1 | AZ7: =AY7+AX7 | BA7: =$R7-AZ7 | BB7: =$R7/AZ7-1 | BC7: =16833000*4-2000000 | BD7: 70000000 | BE7: =BD7+BC7 | BF7: =$R7-BE7 | BG7: =$R7/BE7-1
A8: ALTERA INFRASTRUCTURE | B8: =Janvier!B8+Février!B8+Mars!B8+Avril!B8+Mai!B8+Juin!B8+Juillet!B8+Aout!B8+Septembre!B8+Octobre!B8+Novembre!B8+Décembre!B8 | C8: =Janvier!C8+Février!C8+Mars!C8+Avril!C8+Mai!C8+Juin!C8+Juillet!C8+Aout!C8+Septembre!C8+Octobre!C8+Novembre!C8+Décembre!C8 | D8: =Janvier!D8+Février!D8+Mars!D8+Avril!D8+Mai!D8+Juin!D8+Juillet!D8+Aout!D8+Septembre!D8+Octobre!D8+Novembre!D8+Décembre!D8 | E8: =Janvier!E8+Février!E8+Mars!E8+Avril!E8+Mai!E8+Juin!E8+Juillet!E8+Aout!E8+Septembre!E8+Octobre!E8+Novembre!E8+Décembre!E8 | F8: =Janvier!F8+Février!F8+Mars!F8+Avril!F8+Mai!F8+Juin!F8+Juillet!F8+Aout!F8+Septembre!F8+Octobre!F8+Novembre!F8+Décembre!F8 | G8: =Janvier!G8+Février!G8+Mars!G8+Avril!G8+Mai!G8+Juin!G8+Juillet!G8+Aout!G8+Septembre!G8+Octobre!G8+Novembre!G8+Décembre!G8 | H8: =Janvier!H8+Février!H8+Mars!H8+Avril!H8+Mai!H8+Juin!H8+Juillet!H8+Aout!H8+Septembre!H8+Octobre!H8+Novembre!H8+Décembre!H8 | I8: =Janvier!I8+Février!I8+Mars!I8+Avril!I8+Mai!I8+Juin!I8+Juillet!I8+Aout!I8+Septembre!I8+Octobre!I8+Novembre!I8+Décembre!I8 | J8: =Janvier!J8+Février!J8+Mars!J8+Avril!J8+Mai!J8+Juin!J8+Juillet!J8+Aout!J8+Septembre!J8+Octobre!J8+Novembre!J8+Décembre!J8 | L8: =SUM(E8:F8,I8:K8) | M8: =L8+D8 | N8: =M8/655.957 | O8: =A8 | P8: =B8 | Q8: =C8 | R8: =D8 | S8: =X8/12*$A$1 | T8: =Y8/12*$A$1 | U8: 0 | V8: =$R8-U8 | W8: =R8/U8-1 | X8: 0 | Y8: 0 | Z8: =Y8+X8 | AA8: =R8-Z8 | AB8: =R8/Z8-1 | AC8: =Z8/$Z$57 | AE8: =AF8-AD8 | AF8: =AC8*4901000000 | AG8: =R8-AF8 | AH8: =R8/AF8-1 | AJ8: =AK8-AI8 | AK8: 0 | AL8: =R8-AK8 | AM8: 0 | AN8: =AI8/12*$A$1 | AO8: =AJ8/12*$A$1 | AP8: =AO8+AN8 | AQ8: =R8-AP8 | AR8: 0 | AU8: =AT8+AS8 | AV8: =AU8-Z8 | AW8: =AU8/Z8-1 | AX8: =BC8/12*$A$1 | AY8: =BD8/12*$A$1 | AZ8: =AY8+AX8 | BA8: =$R8-AZ8 | BB8: =$R8/AZ8-1 | BE8: =BD8+BC8 | BF8: =$R8-BE8 | BG8: =$R8/BE8-1
A9: ICM COTE D'IVOIRE | B9: =Janvier!B9+Février!B9+Mars!B9+Avril!B9+Mai!B9+Juin!B9+Juillet!B9+Aout!B9+Septembre!B9+Octobre!B9+Novembre!B9+Décembre!B9 | C9: =Janvier!C9+Février!C9+Mars!C9+Avril!C9+Mai!C9+Juin!C9+Juillet!C9+Aout!C9+Septembre!C9+Octobre!C9+Novembre!C9+Décembre!C9 | D9: =Janvier!D9+Février!D9+Mars!D9+Avril!D9+Mai!D9+Juin!D9+Juillet!D9+Aout!D9+Septembre!D9+Octobre!D9+Novembre!D9+Décembre!D9 | E9: =Janvier!E9+Février!E9+Mars!E9+Avril!E9+Mai!E9+Juin!E9+Juillet!E9+Aout!E9+Septembre!E9+Octobre!E9+Novembre!E9+Décembre!E9 | F9: =Janvier!F9+Février!F9+Mars!F9+Avril!F9+Mai!F9+Juin!F9+Juillet!F9+Aout!F9+Septembre!F9+Octobre!F9+Novembre!F9+Décembre!F9 | G9: =Janvier!G9+Février!G9+Mars!G9+Avril!G9+Mai!G9+Juin!G9+Juillet!G9+Aout!G9+Septembre!G9+Octobre!G9+Novembre!G9+Décembre!G9 | H9: =Janvier!H9+Février!H9+Mars!H9+Avril!H9+Mai!H9+Juin!H9+Juillet!H9+Aout!H9+Septembre!H9+Octobre!H9+Novembre!H9+Décembre!H9 | I9: =Janvier!I9+Février!I9+Mars!I9+Avril!I9+Mai!I9+Juin!I9+Juillet!I9+Aout!I9+Septembre!I9+Octobre!I9+Novembre!I9+Décembre!I9 | J9: =Janvier!J9+Février!J9+Mars!J9+Avril!J9+Mai!J9+Juin!J9+Juillet!J9+Aout!J9+Septembre!J9+Octobre!J9+Novembre!J9+Décembre!J9 | L9: =SUM(E9:F9,I9:K9) | M9: =L9+D9 | N9: =M9/655.957 | O9: =A9 | P9: =B9 | Q9: =C9 | R9: =D9 | S9: =X9/12*$A$1 | T9: =Y9/12*$A$1 | U9: 0 | V9: =$R9-U9 | W9: =R9/U9-1 | Z9: =Y9+X9 | AA9: =R9-Z9 | AB9: =R9/Z9-1 | AC9: =Z9/$Z$57 | AE9: =AF9-AD9 | AF9: 3140000 | AG9: =R9-AF9 | AH9: =R9/AF9-1 | AJ9: =AK9-AI9 | AK9: 3140000 | AL9: =R9-AK9 | AM9: =R9/AK9-1 | AN9: =AI9/12*$A$1 | AO9: =AJ9/12*$A$1 | AP9: =AO9+AN9 | AQ9: =R9-AP9 | AR9: =R9/AP9-1 | AU9: =AT9+AS9 | AV9: =AU9-Z9 | AW9: =AU9/Z9-1 | AX9: =BC9/12*$A$1 | AY9: =BD9/12*$A$1 | AZ9: =AY9+AX9 | BA9: =$R9-AZ9 | BB9: =$R9/AZ9-1 | BE9: =BD9+BC9 | BF9: =$R9-BE9 | BG9: =$R9/BE9-1
A10: OILFIELD MACHINE SHOP (OMS) | B10: =Janvier!B10+Février!B10+Mars!B10+Avril!B10+Mai!B10+Juin!B10+Juillet!B10+Aout!B10+Septembre!B10+Octobre!B10+Novembre!B10+Décembre!B10 | C10: =Janvier!C10+Février!C10+Mars!C10+Avril!C10+Mai!C10+Juin!C10+Juillet!C10+Aout!C10+Septembre!C10+Octobre!C10+Novembre!C10+Décembre!C10 | D10: =Janvier!D10+Février!D10+Mars!D10+Avril!D10+Mai!D10+Juin!D10+Juillet!D10+Aout!D10+Septembre!D10+Octobre!D10+Novembre!D10+Décembre!D10 | E10: =Janvier!E10+Février!E10+Mars!E10+Avril!E10+Mai!E10+Juin!E10+Juillet!E10+Aout!E10+Septembre!E10+Octobre!E10+Novembre!E10+Décembre!E10 | F10: =Janvier!F10+Février!F10+Mars!F10+Avril!F10+Mai!F10+Juin!F10+Juillet!F10+Aout!F10+Septembre!F10+Octobre!F10+Novembre!F10+Décembre!F10 | G10: =Janvier!G10+Février!G10+Mars!G10+Avril!G10+Mai!G10+Juin!G10+Juillet!G10+Aout!G10+Septembre!G10+Octobre!G10+Novembre!G10+Décembre!G10 | H10: =Janvier!H10+Février!H10+Mars!H10+Avril!H10+Mai!H10+Juin!H10+Juillet!H10+Aout!H10+Septembre!H10+Octobre!H10+Novembre!H10+Décembre!H10 | I10: =Janvier!I10+Février!I10+Mars!I10+Avril!I10+Mai!I10+Juin!I10+Juillet!I10+Aout!I10+Septembre!I10+Octobre!I10+Novembre!I10+Décembre!I10 | J10: =Janvier!J10+Février!J10+Mars!J10+Avril!J10+Mai!J10+Juin!J10+Juillet!J10+Aout!J10+Septembre!J10+Octobre!J10+Novembre!J10+Décembre!J10 | L10: =SUM(E10:F10,I10:K10) | M10: =L10+D10 | N10: =M10/655.957 | O10: =A10 | P10: =B10 | Q10: =C10 | R10: =D10 | S10: =X10/12*$A$1 | T10: =Y10/12*$A$1 | U10: 0 | V10: =$R10-U10 | W10: =R10/U10-1 | Z10: =Y10+X10 | AA10: =R10-Z10 | AB10: =R10/Z10-1 | AC10: =Z10/$Z$57 | AE10: =AF10-AD10 | AF10: 7000000 | AG10: =R10-AF10 | AH10: =R10/AF10-1 | AJ10: =AK10-AI10 | AK10: 35000000 | AL10: =R10-AK10 | AM10: =R10/AK10-1 | AN10: =AI10/12*$A$1 | AO10: =AJ10/12*$A$1 | AP10: =AO10+AN10 | AQ10: =R10-AP10 | AR10: =R10/AP10-1 | AT10: 25000000 | AU10: =AT10+AS10 | AV10: =AU10-Z10 | AW10: =AU10/Z10-1 | AX10: =BC10/12*$A$1 | AY10: =BD10/12*$A$1 | AZ10: =AY10+AX10 | BA10: =$R10-AZ10 | BB10: =$R10/AZ10-1 | BE10: =BD10+BC10 | BF10: =$R10-BE10 | BG10: =$R10/BE10-1
A11: CNR INTERNATIONAL | B11: =Janvier!B11+Février!B11+Mars!B11+Avril!B11+Mai!B11+Juin!B11+Juillet!B11+Aout!B11+Septembre!B11+Octobre!B11+Novembre!B11+Décembre!B11 | C11: =Janvier!C11+Février!C11+Mars!C11+Avril!C11+Mai!C11+Juin!C11+Juillet!C11+Aout!C11+Septembre!C11+Octobre!C11+Novembre!C11+Décembre!C11 | D11: =Janvier!D11+Février!D11+Mars!D11+Avril!D11+Mai!D11+Juin!D11+Juillet!D11+Aout!D11+Septembre!D11+Octobre!D11+Novembre!D11+Décembre!D11 | E11: =Janvier!E11+Février!E11+Mars!E11+Avril!E11+Mai!E11+Juin!E11+Juillet!E11+Aout!E11+Septembre!E11+Octobre!E11+Novembre!E11+Décembre!E11 | F11: =Janvier!F11+Février!F11+Mars!F11+Avril!F11+Mai!F11+Juin!F11+Juillet!F11+Aout!F11+Septembre!F11+Octobre!F11+Novembre!F11+Décembre!F11 | G11: =Janvier!G11+Février!G11+Mars!G11+Avril!G11+Mai!G11+Juin!G11+Juillet!G11+Aout!G11+Septembre!G11+Octobre!G11+Novembre!G11+Décembre!G11 | H11: =Janvier!H11+Février!H11+Mars!H11+Avril!H11+Mai!H11+Juin!H11+Juillet!H11+Aout!H11+Septembre!H11+Octobre!H11+Novembre!H11+Décembre!H11 | I11: =Janvier!I11+Février!I11+Mars!I11+Avril!I11+Mai!I11+Juin!I11+Juillet!I11+Aout!I11+Septembre!I11+Octobre!I11+Novembre!I11+Décembre!I11 | J11: =Janvier!J11+Février!J11+Mars!J11+Avril!J11+Mai!J11+Juin!J11+Juillet!J11+Aout!J11+Septembre!J11+Octobre!J11+Novembre!J11+Décembre!J11 | L11: =SUM(E11:F11,I11:K11) | M11: =L11+D11 | N11: =M11/655.957 | O11: =A11 | P11: =B11 | Q11: =C11 | R11: =D11 | S11: =X11/12*$A$1 | T11: =Y11/12*$A$1 | U11: 12916667 | V11: =$R11-U11 | W11: =R11/U11-1 | X11: 0 | Y11: 70000000 | Z11: =Y11+X11 | AA11: =R11-Z11 | AB11: =R11/Z11-1 | AC11: =Z11/$Z$57 | AD11: 530000000 | AE11: =AF11-AD11 | AF11: =1100000000 | AG11: =R11-AF11 | AH11: =R11/AF11-1 | AI11: 530000000 | AJ11: =AK11-AI11 | AK11: 980000000 | AL11: =R11-AK11 | AM11: =R11/AK11-1 | AN11: =AI11/12*$A$1 | AO11: =AJ11/12*$A$1 | AP11: =AO11+AN11 | AQ11: =R11-AP11 | AR11: =R11/AP11-1 | AS11: =33795000*12 | AT11: =125000000*2 | AU11: =AT11+AS11 | AV11: =AU11-Z11 | AW11: =AU11/Z11-1 | AX11: =BC11/12*$A$1 | AY11: =BD11/12*$A$1 | AZ11: =AY11+AX11 | BA11: =$R11-AZ11 | BB11: =$R11/AZ11-1 | BC11: =33795000*12 | BD11: 450000000 | BE11: =BD11+BC11 | BF11: =$R11-BE11 | BG11: =$R11/BE11-1
A12: DIVERS CLIENTS | B12: =Janvier!B12+Février!B12+Mars!B12+Avril!B12+Mai!B12+Juin!B12+Juillet!B12+Aout!B12+Septembre!B12+Octobre!B12+Novembre!B12+Décembre!B12 | C12: =Janvier!C12+Février!C12+Mars!C12+Avril!C12+Mai!C12+Juin!C12+Juillet!C12+Aout!C12+Septembre!C12+Octobre!C12+Novembre!C12+Décembre!C12 | D12: =Janvier!D12+Février!D12+Mars!D12+Avril!D12+Mai!D12+Juin!D12+Juillet!D12+Aout!D12+Septembre!D12+Octobre!D12+Novembre!D12+Décembre!D12 | E12: =Janvier!E12+Février!E12+Mars!E12+Avril!E12+Mai!E12+Juin!E12+Juillet!E12+Aout!E12+Septembre!E12+Octobre!E12+Novembre!E12+Décembre!E12 | F12: =Janvier!F12+Février!F12+Mars!F12+Avril!F12+Mai!F12+Juin!F12+Juillet!F12+Aout!F12+Septembre!F12+Octobre!F12+Novembre!F12+Décembre!F12 | G12: =Janvier!G12+Février!G12+Mars!G12+Avril!G12+Mai!G12+Juin!G12+Juillet!G12+Aout!G12+Septembre!G12+Octobre!G12+Novembre!G12+Décembre!G12 | H12: =Janvier!H12+Février!H12+Mars!H12+Avril!H12+Mai!H12+Juin!H12+Juillet!H12+Aout!H12+Septembre!H12+Octobre!H12+Novembre!H12+Décembre!H12 | I12: =Janvier!I12+Février!I12+Mars!I12+Avril!I12+Mai!I12+Juin!I12+Juillet!I12+Aout!I12+Septembre!I12+Octobre!I12+Novembre!I12+Décembre!I12 | J12: =Janvier!J12+Février!J12+Mars!J12+Avril!J12+Mai!J12+Juin!J12+Juillet!J12+Aout!J12+Septembre!J12+Octobre!J12+Novembre!J12+Décembre!J12 | L12: =SUM(E12:F12,I12:K12) | M12: =L12+D12 | N12: =M12/655.957 | O12: =A12 | P12: =B12 | Q12: =C12 | R12: =D12 | S12: =X12/12*$A$1 | T12: =Y12/12*$A$1 | U12: 27957000 | V12: =$R12-U12 | W12: =R12/U12-1 | X12: 0 | Y12: 200000000 | Z12: =Y12+X12 | AA12: =R12-Z12 | AB12: =R12/Z12-1 | AC12: =Z12/$Z$57 | AE12: =AF12-AD12 | AF12: 65000000 | AG12: =R12-AF12 | AH12: =R12/AF12-1 | AJ12: =AK12-AI12 | AK12: 110000000 | AL12: =R12-AK12 | AM12: =R12/AK12-1 | AN12: =AI12/12*$A$1 | AO12: =AJ12/12*$A$1 | AP12: =AO12+AN12 | AQ12: =R12-AP12 | AR12: =R12/AP12-1 | AT12: 475000000 | AU12: =AT12+AS12 | AV12: =AU12-Z12 | AW12: =AU12/Z12-1 | AX12: =BC12/12*$A$1 | AY12: =BD12/12*$A$1 | AZ12: =AY12+AX12 | BA12: =$R12-AZ12 | BB12: =$R12/AZ12-1 | BD12: 42000000 | BE12: =BD12+BC12 | BF12: =$R12-BE12 | BG12: =$R12/BE12-1
A13: CNR - ICM CONTRAT BATEAU SURFER | B13: =Janvier!B13+Février!B13+Mars!B13+Avril!B13+Mai!B13+Juin!B13+Juillet!B13+Aout!B13+Septembre!B13+Octobre!B13+Novembre!B13+Décembre!B13 | C13: =Janvier!C13+Février!C13+Mars!C13+Avril!C13+Mai!C13+Juin!C13+Juillet!C13+Aout!C13+Septembre!C13+Octobre!C13+Novembre!C13+Décembre!C13 | D13: =Janvier!D13+Février!D13+Mars!D13+Avril!D13+Mai!D13+Juin!D13+Juillet!D13+Aout!D13+Septembre!D13+Octobre!D13+Novembre!D13+Décembre!D13 | E13: =Janvier!E13+Février!E13+Mars!E13+Avril!E13+Mai!E13+Juin!E13+Juillet!E13+Aout!E13+Septembre!E13+Octobre!E13+Novembre!E13+Décembre!E13 | F13: =Janvier!F13+Février!F13+Mars!F13+Avril!F13+Mai!F13+Juin!F13+Juillet!F13+Aout!F13+Septembre!F13+Octobre!F13+Novembre!F13+Décembre!F13 | G13: =Janvier!G13+Février!G13+Mars!G13+Avril!G13+Mai!G13+Juin!G13+Juillet!G13+Aout!G13+Septembre!G13+Octobre!G13+Novembre!G13+Décembre!G13 | H13: =Janvier!H13+Février!H13+Mars!H13+Avril!H13+Mai!H13+Juin!H13+Juillet!H13+Aout!H13+Septembre!H13+Octobre!H13+Novembre!H13+Décembre!H13 | I13: =Janvier!I13+Février!I13+Mars!I13+Avril!I13+Mai!I13+Juin!I13+Juillet!I13+Aout!I13+Septembre!I13+Octobre!I13+Novembre!I13+Décembre!I13 | J13: =Janvier!J13+Février!J13+Mars!J13+Avril!J13+Mai!J13+Juin!J13+Juillet!J13+Aout!J13+Septembre!J13+Octobre!J13+Novembre!J13+Décembre!J13 | L13: =SUM(E13:F13,I13:K13) | M13: =L13+D13 | N13: =M13/655.957 | O13: =A13 | P13: =B13 | Q13: =C13 | R13: =D13 | S13: =X13/12*$A$1 | T13: =Y13/12*$A$1 | U13: 0 | V13: =$R13-U13 | W13: =R13/U13-1 | X13: 0 | Y13: 0 | Z13: =Y13+X13 | AA13: =R13-Z13 | AB13: =R13/Z13-1 | AC13: =Z13/$Z$57 | AE13: =AF13-AD13 | AF13: =AC13*4901000000 | AG13: =R13-AF13 | AH13: =R13/AF13-1 | AJ13: =AK13-AI13 | AK13: 0 | AL13: =R13-AK13 | AM13: 0 | AN13: =AI13/12*$A$1 | AO13: =AJ13/12*$A$1 | AP13: =AO13+AN13 | AQ13: =R13-AP13 | AR13: 0 | AU13: =AT13+AS13 | AV13: =AU13-Z13 | AW13: =AU13/Z13-1 | AX13: =BC13/12*$A$1 | AY13: =BD13/12*$A$1 | AZ13: =AY13+AX13 | BA13: =$R13-AZ13 | BB13: =$R13/AZ13-1 | BE13: =BD13+BC13 | BF13: =$R13-BE13 | BG13: =$R13/BE13-1
A14: PETRO DISTRIBUTIONS | B14: =Janvier!B14+Février!B14+Mars!B14+Avril!B14+Mai!B14+Juin!B14+Juillet!B14+Aout!B14+Septembre!B14+Octobre!B14+Novembre!B14+Décembre!B14 | C14: =Janvier!C14+Février!C14+Mars!C14+Avril!C14+Mai!C14+Juin!C14+Juillet!C14+Aout!C14+Septembre!C14+Octobre!C14+Novembre!C14+Décembre!C14 | D14: =Janvier!D14+Février!D14+Mars!D14+Avril!D14+Mai!D14+Juin!D14+Juillet!D14+Aout!D14+Septembre!D14+Octobre!D14+Novembre!D14+Décembre!D14 | E14: =Janvier!E14+Février!E14+Mars!E14+Avril!E14+Mai!E14+Juin!E14+Juillet!E14+Aout!E14+Septembre!E14+Octobre!E14+Novembre!E14+Décembre!E14 | F14: =Janvier!F14+Février!F14+Mars!F14+Avril!F14+Mai!F14+Juin!F14+Juillet!F14+Aout!F14+Septembre!F14+Octobre!F14+Novembre!F14+Décembre!F14 | G14: =Janvier!G14+Février!G14+Mars!G14+Avril!G14+Mai!G14+Juin!G14+Juillet!G14+Aout!G14+Septembre!G14+Octobre!G14+Novembre!G14+Décembre!G14 | H14: =Janvier!H14+Février!H14+Mars!H14+Avril!H14+Mai!H14+Juin!H14+Juillet!H14+Aout!H14+Septembre!H14+Octobre!H14+Novembre!H14+Décembre!H14 | I14: =Janvier!I14+Février!I14+Mars!I14+Avril!I14+Mai!I14+Juin!I14+Juillet!I14+Aout!I14+Septembre!I14+Octobre!I14+Novembre!I14+Décembre!I14 | J14: =Janvier!J14+Février!J14+Mars!J14+Avril!J14+Mai!J14+Juin!J14+Juillet!J14+Aout!J14+Septembre!J14+Octobre!J14+Novembre!J14+Décembre!J14 | L14: =SUM(E14:F14,I14:K14) | M14: =L14+D14 | N14: =M14/655.957 | O14: =A14 | P14: =B14 | Q14: =C14 | R14: =D14 | S14: =X14/12*$A$1 | T14: =Y14/12*$A$1 | U14: 2000 | V14: =$R14-U14 | W14: =R14/U14-1 | Z14: =Y14+X14 | AA14: =R14-Z14 | AB14: =R14/Z14-1 | AC14: =Z14/$Z$57 | AD14: 50000000 | AE14: =AF14-AD14 | AF14: 100000000 | AG14: =R14-AF14 | AH14: =R14/AF14-1 | AJ14: =AK14-AI14 | AL14: =R14-AK14 | AM14: 0 | AN14: =AI14/12*$A$1 | AO14: =AJ14/12*$A$1 | AP14: =AO14+AN14 | AQ14: =R14-AP14 | AR14: 0 | AU14: =AT14+AS14 | AV14: =AU14-Z14 | AW14: =AU14/Z14-1 | AX14: =BC14/12*$A$1 | AY14: =BD14/12*$A$1 | AZ14: =AY14+AX14 | BA14: =$R14-AZ14 | BB14: =$R14/AZ14-1 | BE14: =BD14+BC14 | BF14: =$R14-BE14 | BG14: =$R14/BE14-1
A15: EXPRO GROUP | B15: =Janvier!B15+Février!B15+Mars!B15+Avril!B15+Mai!B15+Juin!B15+Juillet!B15+Aout!B15+Septembre!B15+Octobre!B15+Novembre!B15+Décembre!B15 | C15: =Janvier!C15+Février!C15+Mars!C15+Avril!C15+Mai!C15+Juin!C15+Juillet!C15+Aout!C15+Septembre!C15+Octobre!C15+Novembre!C15+Décembre!C15 | D15: =Janvier!D15+Février!D15+Mars!D15+Avril!D15+Mai!D15+Juin!D15+Juillet!D15+Aout!D15+Septembre!D15+Octobre!D15+Novembre!D15+Décembre!D15 | E15: =Janvier!E15+Février!E15+Mars!E15+Avril!E15+Mai!E15+Juin!E15+Juillet!E15+Aout!E15+Septembre!E15+Octobre!E15+Novembre!E15+Décembre!E15 | F15: =Janvier!F15+Février!F15+Mars!F15+Avril!F15+Mai!F15+Juin!F15+Juillet!F15+Aout!F15+Septembre!F15+Octobre!F15+Novembre!F15+Décembre!F15 | G15: =Janvier!G15+Février!G15+Mars!G15+Avril!G15+Mai!G15+Juin!G15+Juillet!G15+Aout!G15+Septembre!G15+Octobre!G15+Novembre!G15+Décembre!G15 | H15: =Janvier!H15+Février!H15+Mars!H15+Avril!H15+Mai!H15+Juin!H15+Juillet!H15+Aout!H15+Septembre!H15+Octobre!H15+Novembre!H15+Décembre!H15 | I15: =Janvier!I15+Février!I15+Mars!I15+Avril!I15+Mai!I15+Juin!I15+Juillet!I15+Aout!I15+Septembre!I15+Octobre!I15+Novembre!I15+Décembre!I15 | J15: =Janvier!J15+Février!J15+Mars!J15+Avril!J15+Mai!J15+Juin!J15+Juillet!J15+Aout!J15+Septembre!J15+Octobre!J15+Novembre!J15+Décembre!J15 | L15: =SUM(E15:F15,I15:K15) | M15: =L15+D15 | N15: =M15/655.957 | O15: =A15 | P15: =B15 | Q15: =C15 | R15: =D15 | S15: =X15/12*$A$1 | T15: =Y15/12*$A$1 | U15: 833000 | V15: =$R15-U15 | W15: =R15/U15-1 | X15: 0 | Y15: 0 | Z15: =Y15+X15 | AA15: =R15-Z15 | AB15: =R15/Z15-1 | AC15: =Z15/$Z$57 | AD15: 70000000 | AE15: =AF15-AD15 | AF15: 78000000 | AG15: =R15-AF15 | AH15: =R15/AF15-1 | AI15: 70000000 | AJ15: =AK15-AI15 | AK15: 78000000 | AL15: =R15-AK15 | AM15: =R15/AK15-1 | AN15: =AI15/12*$A$1 | AO15: =AJ15/12*$A$1 | AP15: =AO15+AN15 | AQ15: =R15-AP15 | AR15: =R15/AP15-1 | AS15: =4784000*2+5076000*10 | AT15: 40000000 | AU15: =AT15+AS15 | AV15: =AU15-Z15 | AW15: =AU15/Z15-1 | AX15: =BC15/12*$A$1 | AY15: =BD15/12*$A$1 | AZ15: =AY15+AX15 | BA15: =$R15-AZ15 | BB15: =$R15/AZ15-1 | BC15: 60000000 | BD15: 70000000 | BE15: =BD15+BC15 | BF15: =$R15-BE15 | BG15: =$R15/BE15-1
A16: SUPERMARITIME | B16: =Janvier!B16+Février!B16+Mars!B16+Avril!B16+Mai!B16+Juin!B16+Juillet!B16+Aout!B16+Septembre!B16+Octobre!B16+Novembre!B16+Décembre!B16 | C16: =Janvier!C16+Février!C16+Mars!C16+Avril!C16+Mai!C16+Juin!C16+Juillet!C16+Aout!C16+Septembre!C16+Octobre!C16+Novembre!C16+Décembre!C16 | D16: =Janvier!D16+Février!D16+Mars!D16+Avril!D16+Mai!D16+Juin!D16+Juillet!D16+Aout!D16+Septembre!D16+Octobre!D16+Novembre!D16+Décembre!D16 | E16: =Janvier!E16+Février!E16+Mars!E16+Avril!E16+Mai!E16+Juin!E16+Juillet!E16+Aout!E16+Septembre!E16+Octobre!E16+Novembre!E16+Décembre!E16 | F16: =Janvier!F16+Février!F16+Mars!F16+Avril!F16+Mai!F16+Juin!F16+Juillet!F16+Aout!F16+Septembre!F16+Octobre!F16+Novembre!F16+Décembre!F16 | G16: =Janvier!G16+Février!G16+Mars!G16+Avril!G16+Mai!G16+Juin!G16+Juillet!G16+Aout!G16+Septembre!G16+Octobre!G16+Novembre!G16+Décembre!G16 | H16: =Janvier!H16+Février!H16+Mars!H16+Avril!H16+Mai!H16+Juin!H16+Juillet!H16+Aout!H16+Septembre!H16+Octobre!H16+Novembre!H16+Décembre!H16 | I16: =Janvier!I16+Février!I16+Mars!I16+Avril!I16+Mai!I16+Juin!I16+Juillet!I16+Aout!I16+Septembre!I16+Octobre!I16+Novembre!I16+Décembre!I16 | J16: =Janvier!J16+Février!J16+Mars!J16+Avril!J16+Mai!J16+Juin!J16+Juillet!J16+Aout!J16+Septembre!J16+Octobre!J16+Novembre!J16+Décembre!J16 | L16: =SUM(E16:F16,I16:K16) | M16: =L16+D16 | N16: =M16/655.957 | O16: =A16 | P16: =B16 | Q16: =C16 | R16: =D16 | S16: =X16/12*$A$1 | T16: =Y16/12*$A$1 | U16: 165000 | V16: =$R16-U16 | W16: =R16/U16-1 | Z16: =Y16+X16 | AA16: =R16-Z16 | AB16: =R16/Z16-1 | AC16: =Z16/$Z$57 | AE16: =AF16-AD16 | AF16: =AC16*4901000000 | AG16: =R16-AF16 | AH16: =R16/AF16-1 | AJ16: =AK16-AI16 | AK16: 0 | AL16: =R16-AK16 | AM16: 0 | AN16: =AI16/12*$A$1 | AO16: =AJ16/12*$A$1 | AP16: =AO16+AN16 | AQ16: =R16-AP16 | AR16: 0 | AU16: =AT16+AS16 | AV16: =AU16-Z16 | AW16: =AU16/Z16-1 | AX16: =BC16/12*$A$1 | AY16: =BD16/12*$A$1 | AZ16: =AY16+AX16 | BA16: =$R16-AZ16 | BB16: =$R16/AZ16-1 | BE16: =BD16+BC16 | BF16: =$R16-BE16 | BG16: =$R16/BE16-1
A17: FOXTROT INTERNATIONAL | B17: =Janvier!B17+Février!B17+Mars!B17+Avril!B17+Mai!B17+Juin!B17+Juillet!B17+Aout!B17+Septembre!B17+Octobre!B17+Novembre!B17+Décembre!B17 | C17: =Janvier!C17+Février!C17+Mars!C17+Avril!C17+Mai!C17+Juin!C17+Juillet!C17+Aout!C17+Septembre!C17+Octobre!C17+Novembre!C17+Décembre!C17 | D17: =Janvier!D17+Février!D17+Mars!D17+Avril!D17+Mai!D17+Juin!D17+Juillet!D17+Aout!D17+Septembre!D17+Octobre!D17+Novembre!D17+Décembre!D17 | E17: =Janvier!E17+Février!E17+Mars!E17+Avril!E17+Mai!E17+Juin!E17+Juillet!E17+Aout!E17+Septembre!E17+Octobre!E17+Novembre!E17+Décembre!E17 | F17: =Janvier!F17+Février!F17+Mars!F17+Avril!F17+Mai!F17+Juin!F17+Juillet!F17+Aout!F17+Septembre!F17+Octobre!F17+Novembre!F17+Décembre!F17 | G17: =Janvier!G17+Février!G17+Mars!G17+Avril!G17+Mai!G17+Juin!G17+Juillet!G17+Aout!G17+Septembre!G17+Octobre!G17+Novembre!G17+Décembre!G17 | H17: =Janvier!H17+Février!H17+Mars!H17+Avril!H17+Mai!H17+Juin!H17+Juillet!H17+Aout!H17+Septembre!H17+Octobre!H17+Novembre!H17+Décembre!H17 | I17: =Janvier!I17+Février!I17+Mars!I17+Avril!I17+Mai!I17+Juin!I17+Juillet!I17+Aout!I17+Septembre!I17+Octobre!I17+Novembre!I17+Décembre!I17 | J17: =Janvier!J17+Février!J17+Mars!J17+Avril!J17+Mai!J17+Juin!J17+Juillet!J17+Aout!J17+Septembre!J17+Octobre!J17+Novembre!J17+Décembre!J17 | L17: =SUM(E17:F17,I17:K17) | M17: =L17+D17 | N17: =M17/655.957 | O17: =A17 | P17: =B17 | Q17: =C17 | R17: =D17 | S17: =X17/12*$A$1 | T17: =Y17/12*$A$1 | U17: 41667000 | V17: =$R17-U17 | W17: =R17/U17-1 | X17: 335000000 | Y17: 300000000 | Z17: =Y17+X17 | AA17: =R17-Z17 | AB17: =R17/Z17-1 | AC17: =Z17/$Z$57 | AD17: =(6900000*6)+(27649000*6) | AE17: =AF17-AD17 | AF17: 600000000 | AG17: =R17-AF17 | AH17: =R17/AF17-1 | AI17: 247294000 | AJ17: =AK17-AI17 | AK17: 787294000 | AL17: =R17-AK17 | AM17: =R17/AK17-1 | AN17: =AI17/12*$A$1 | AO17: =AJ17/12*$A$1 | AP17: =AO17+AN17 | AQ17: =R17-AP17 | AR17: =R17/AP17-1 | AS17: =83748000*4 | AT17: =247000000+6*45000000+25000000+30000000 | AU17: =AT17+AS17 | AV17: =AU17-Z17 | AW17: =AU17/Z17-1 | AX17: =BC17/12*$A$1 | AY17: =BD17/12*$A$1 | AZ17: =AY17+AX17 | BA17: =$R17-AZ17 | BB17: =$R17/AZ17-1 | BC17: 335000000 | BD17: 850000000 | BE17: =BD17+BC17 | BF17: =$R17-BE17 | BG17: =$R17/BE17-1
A18: COMEXAS - CI | B18: =Janvier!B18+Février!B18+Mars!B18+Avril!B18+Mai!B18+Juin!B18+Juillet!B18+Aout!B18+Septembre!B18+Octobre!B18+Novembre!B18+Décembre!B18 | C18: =Janvier!C18+Février!C18+Mars!C18+Avril!C18+Mai!C18+Juin!C18+Juillet!C18+Aout!C18+Septembre!C18+Octobre!C18+Novembre!C18+Décembre!C18 | D18: =Janvier!D18+Février!D18+Mars!D18+Avril!D18+Mai!D18+Juin!D18+Juillet!D18+Aout!D18+Septembre!D18+Octobre!D18+Novembre!D18+Décembre!D18 | E18: =Janvier!E18+Février!E18+Mars!E18+Avril!E18+Mai!E18+Juin!E18+Juillet!E18+Aout!E18+Septembre!E18+Octobre!E18+Novembre!E18+Décembre!E18 | F18: =Janvier!F18+Février!F18+Mars!F18+Avril!F18+Mai!F18+Juin!F18+Juillet!F18+Aout!F18+Septembre!F18+Octobre!F18+Novembre!F18+Décembre!F18 | G18: =Janvier!G18+Février!G18+Mars!G18+Avril!G18+Mai!G18+Juin!G18+Juillet!G18+Aout!G18+Septembre!G18+Octobre!G18+Novembre!G18+Décembre!G18 | H18: =Janvier!H18+Février!H18+Mars!H18+Avril!H18+Mai!H18+Juin!H18+Juillet!H18+Aout!H18+Septembre!H18+Octobre!H18+Novembre!H18+Décembre!H18 | I18: =Janvier!I18+Février!I18+Mars!I18+Avril!I18+Mai!I18+Juin!I18+Juillet!I18+Aout!I18+Septembre!I18+Octobre!I18+Novembre!I18+Décembre!I18 | J18: =Janvier!J18+Février!J18+Mars!J18+Avril!J18+Mai!J18+Juin!J18+Juillet!J18+Aout!J18+Septembre!J18+Octobre!J18+Novembre!J18+Décembre!J18 | L18: =SUM(E18:F18,I18:K18) | M18: =L18+D18 | N18: =M18/655.957 | O18: =A18 | P18: =B18 | Q18: =C18 | R18: =D18 | S18: =X18/12*$A$1 | T18: =Y18/12*$A$1 | U18: 0 | V18: =$R18-U18 | W18: =R18/U18-1 | Z18: =Y18+X18 | AA18: =R18-Z18 | AB18: =R18/Z18-1 | AC18: =Z18/$Z$57 | AE18: =AF18-AD18 | AF18: =AC18*4901000000 | AG18: =R18-AF18 | AH18: =R18/AF18-1 | AJ18: =AK18-AI18 | AK18: 0 | AL18: =R18-AK18 | AM18: 0 | AN18: =AI18/12*$A$1 | AO18: =AJ18/12*$A$1 | AP18: =AO18+AN18 | AQ18: =R18-AP18 | AR18: 0 | AU18: =AT18+AS18 | AV18: =AU18-Z18 | AW18: =AU18/Z18-1 | AX18: =BC18/12*$A$1 | AY18: =BD18/12*$A$1 | AZ18: =AY18+AX18 | BA18: =$R18-AZ18 | BB18: =$R18/AZ18-1 | BE18: =BD18+BC18 | BF18: =$R18-BE18 | BG18: =$R18/BE18-1
A19: GLOBAL ENERGY VENTURES (GEV) | B19: =Janvier!B19+Février!B19+Mars!B19+Avril!B19+Mai!B19+Juin!B19+Juillet!B19+Aout!B19+Septembre!B19+Octobre!B19+Novembre!B19+Décembre!B19 | C19: =Janvier!C19+Février!C19+Mars!C19+Avril!C19+Mai!C19+Juin!C19+Juillet!C19+Aout!C19+Septembre!C19+Octobre!C19+Novembre!C19+Décembre!C19 | D19: =Janvier!D19+Février!D19+Mars!D19+Avril!D19+Mai!D19+Juin!D19+Juillet!D19+Aout!D19+Septembre!D19+Octobre!D19+Novembre!D19+Décembre!D19 | E19: =Janvier!E19+Février!E19+Mars!E19+Avril!E19+Mai!E19+Juin!E19+Juillet!E19+Aout!E19+Septembre!E19+Octobre!E19+Novembre!E19+Décembre!E19 | F19: =Janvier!F19+Février!F19+Mars!F19+Avril!F19+Mai!F19+Juin!F19+Juillet!F19+Aout!F19+Septembre!F19+Octobre!F19+Novembre!F19+Décembre!F19 | G19: =Janvier!G19+Février!G19+Mars!G19+Avril!G19+Mai!G19+Juin!G19+Juillet!G19+Aout!G19+Septembre!G19+Octobre!G19+Novembre!G19+Décembre!G19 | H19: =Janvier!H19+Février!H19+Mars!H19+Avril!H19+Mai!H19+Juin!H19+Juillet!H19+Aout!H19+Septembre!H19+Octobre!H19+Novembre!H19+Décembre!H19 | I19: =Janvier!I19+Février!I19+Mars!I19+Avril!I19+Mai!I19+Juin!I19+Juillet!I19+Aout!I19+Septembre!I19+Octobre!I19+Novembre!I19+Décembre!I19 | J19: =Janvier!J19+Février!J19+Mars!J19+Avril!J19+Mai!J19+Juin!J19+Juillet!J19+Aout!J19+Septembre!J19+Octobre!J19+Novembre!J19+Décembre!J19 | L19: =SUM(E19:F19,I19:K19) | M19: =L19+D19 | N19: =M19/655.957 | O19: =A19 | P19: =B19 | Q19: =C19 | R19: =D19 | S19: =X19/12*$A$1 | T19: =Y19/12*$A$1 | U19: 3723000 | V19: =$R19-U19 | W19: =R19/U19-1 | X19: 24680000 | Y19: 40000000 | Z19: =Y19+X19 | AA19: =R19-Z19 | AB19: =R19/Z19-1 | AC19: =Z19/$Z$57 | AD19: 25000000 | AE19: =AF19-AD19 | AF19: 45000000 | AG19: =R19-AF19 | AH19: =R19/AF19-1 | AI19: 25000000 | AJ19: =AK19-AI19 | AK19: 40000000 | AL19: =R19-AK19 | AM19: =R19/AK19-1 | AN19: =AI19/12*$A$1 | AO19: =AJ19/12*$A$1 | AP19: =AO19+AN19 | AQ19: =R19-AP19 | AR19: =R19/AP19-1 | AS19: =5670000*4 | AT19: 35000000 | AU19: =AT19+AS19 | AV19: =AU19-Z19 | AW19: =AU19/Z19-1 | AX19: =BC19/12*$A$1 | AY19: =BD19/12*$A$1 | AZ19: =AY19+AX19 | BA19: =$R19-AZ19 | BB19: =$R19/AZ19-1 | BC19: =5670000*4 | BD19: 80000000 | BE19: =BD19+BC19 | BF19: =$R19-BE19 | BG19: =$R19/BE19-1
A20: MI OVERSEAS | B20: =Janvier!B20+Février!B20+Mars!B20+Avril!B20+Mai!B20+Juin!B20+Juillet!B20+Aout!B20+Septembre!B20+Octobre!B20+Novembre!B20+Décembre!B20 | C20: =Janvier!C20+Février!C20+Mars!C20+Avril!C20+Mai!C20+Juin!C20+Juillet!C20+Aout!C20+Septembre!C20+Octobre!C20+Novembre!C20+Décembre!C20 | D20: =Janvier!D20+Février!D20+Mars!D20+Avril!D20+Mai!D20+Juin!D20+Juillet!D20+Aout!D20+Septembre!D20+Octobre!D20+Novembre!D20+Décembre!D20 | E20: =Janvier!E20+Février!E20+Mars!E20+Avril!E20+Mai!E20+Juin!E20+Juillet!E20+Aout!E20+Septembre!E20+Octobre!E20+Novembre!E20+Décembre!E20 | F20: =Janvier!F20+Février!F20+Mars!F20+Avril!F20+Mai!F20+Juin!F20+Juillet!F20+Aout!F20+Septembre!F20+Octobre!F20+Novembre!F20+Décembre!F20 | G20: =Janvier!G20+Février!G20+Mars!G20+Avril!G20+Mai!G20+Juin!G20+Juillet!G20+Aout!G20+Septembre!G20+Octobre!G20+Novembre!G20+Décembre!G20 | H20: =Janvier!H20+Février!H20+Mars!H20+Avril!H20+Mai!H20+Juin!H20+Juillet!H20+Aout!H20+Septembre!H20+Octobre!H20+Novembre!H20+Décembre!H20 | I20: =Janvier!I20+Février!I20+Mars!I20+Avril!I20+Mai!I20+Juin!I20+Juillet!I20+Aout!I20+Septembre!I20+Octobre!I20+Novembre!I20+Décembre!I20 | J20: =Janvier!J20+Février!J20+Mars!J20+Avril!J20+Mai!J20+Juin!J20+Juillet!J20+Aout!J20+Septembre!J20+Octobre!J20+Novembre!J20+Décembre!J20 | L20: =SUM(E20:F20,I20:K20) | M20: =L20+D20 | N20: =M20/655.957 | O20: =A20 | P20: =B20 | Q20: =C20 | R20: =D20 | S20: =X20/12*$A$1 | T20: =Y20/12*$A$1 | U20: 0 | V20: =$R20-U20 | W20: =R20/U20-1 | Z20: =Y20+X20 | AA20: =R20-Z20 | AB20: =R20/Z20-1 | AC20: =Z20/$Z$57 | AE20: =AF20-AD20 | AF20: =AC20*4901000000 | AG20: =R20-AF20 | AH20: =R20/AF20-1 | AJ20: =AK20-AI20 | AK20: 0 | AL20: =R20-AK20 | AM20: 0 | AN20: =AI20/12*$A$1 | AO20: =AJ20/12*$A$1 | AP20: =AO20+AN20 | AQ20: =R20-AP20 | AR20: 0 | AU20: =AT20+AS20 | AV20: =AU20-Z20 | AW20: =AU20/Z20-1 | AX20: =BC20/12*$A$1 | AY20: =BD20/12*$A$1 | AZ20: =AY20+AX20 | BA20: =$R20-AZ20 | BB20: =$R20/AZ20-1 | BE20: =BD20+BC20 | BF20: =$R20-BE20 | BG20: =$R20/BE20-1
A21: HALLIBURTON | B21: =Janvier!B21+Février!B21+Mars!B21+Avril!B21+Mai!B21+Juin!B21+Juillet!B21+Aout!B21+Septembre!B21+Octobre!B21+Novembre!B21+Décembre!B21 | C21: =Janvier!C21+Février!C21+Mars!C21+Avril!C21+Mai!C21+Juin!C21+Juillet!C21+Aout!C21+Septembre!C21+Octobre!C21+Novembre!C21+Décembre!C21 | D21: =Janvier!D21+Février!D21+Mars!D21+Avril!D21+Mai!D21+Juin!D21+Juillet!D21+Aout!D21+Septembre!D21+Octobre!D21+Novembre!D21+Décembre!D21 | E21: =Janvier!E21+Février!E21+Mars!E21+Avril!E21+Mai!E21+Juin!E21+Juillet!E21+Aout!E21+Septembre!E21+Octobre!E21+Novembre!E21+Décembre!E21 | F21: =Janvier!F21+Février!F21+Mars!F21+Avril!F21+Mai!F21+Juin!F21+Juillet!F21+Aout!F21+Septembre!F21+Octobre!F21+Novembre!F21+Décembre!F21 | G21: =Janvier!G21+Février!G21+Mars!G21+Avril!G21+Mai!G21+Juin!G21+Juillet!G21+Aout!G21+Septembre!G21+Octobre!G21+Novembre!G21+Décembre!G21 | H21: =Janvier!H21+Février!H21+Mars!H21+Avril!H21+Mai!H21+Juin!H21+Juillet!H21+Aout!H21+Septembre!H21+Octobre!H21+Novembre!H21+Décembre!H21 | I21: =Janvier!I21+Février!I21+Mars!I21+Avril!I21+Mai!I21+Juin!I21+Juillet!I21+Aout!I21+Septembre!I21+Octobre!I21+Novembre!I21+Décembre!I21 | J21: =Janvier!J21+Février!J21+Mars!J21+Avril!J21+Mai!J21+Juin!J21+Juillet!J21+Aout!J21+Septembre!J21+Octobre!J21+Novembre!J21+Décembre!J21 | L21: =SUM(E21:F21,I21:K21) | M21: =L21+D21 | N21: =M21/655.957 | O21: =A21 | P21: =B21 | Q21: =C21 | R21: =D21 | S21: =X21/12*$A$1 | T21: =Y21/12*$A$1 | U21: 7500000 | V21: =$R21-U21 | W21: =R21/U21-1 | Y21: 160000000 | Z21: =Y21+X21 | AA21: =R21-Z21 | AB21: =R21/Z21-1 | AC21: =Z21/$Z$57 | AD21: 149328000 | AE21: =AF21-AD21 | AF21: 430700000 | AG21: =R21-AF21 | AH21: =R21/AF21-1 | AI21: 149328000 | AJ21: =AK21-AI21 | AK21: 479328000 | AL21: =R21-AK21 | AM21: =R21/AK21-1 | AN21: =AI21/12*$A$1 | AO21: =AJ21/12*$A$1 | AP21: =AO21+AN21 | AQ21: =R21-AP21 | AR21: =R21/AP21-1 | AS21: =37333500*2 | AT21: =96000000*1.2+12000000*9 | AU21: =AT21+AS21 | AV21: =AU21-Z21 | AW21: =AU21/Z21-1 | AX21: =BC21/12*$A$1 | AY21: =BD21/12*$A$1 | AZ21: =AY21+AX21 | BA21: =$R21-AZ21 | BB21: =$R21/AZ21-1 | BC21: 49778000 | BD21: 215000000 | BE21: =BD21+BC21 | BF21: =$R21-BE21 | BG21: =$R21/BE21-1
A22: IVOIRE OILFIELD SERVICES (IVOS) | B22: =Janvier!B22+Février!B22+Mars!B22+Avril!B22+Mai!B22+Juin!B22+Juillet!B22+Aout!B22+Septembre!B22+Octobre!B22+Novembre!B22+Décembre!B22 | C22: =Janvier!C22+Février!C22+Mars!C22+Avril!C22+Mai!C22+Juin!C22+Juillet!C22+Aout!C22+Septembre!C22+Octobre!C22+Novembre!C22+Décembre!C22 | D22: =Janvier!D22+Février!D22+Mars!D22+Avril!D22+Mai!D22+Juin!D22+Juillet!D22+Aout!D22+Septembre!D22+Octobre!D22+Novembre!D22+Décembre!D22 | E22: =Janvier!E22+Février!E22+Mars!E22+Avril!E22+Mai!E22+Juin!E22+Juillet!E22+Aout!E22+Septembre!E22+Octobre!E22+Novembre!E22+Décembre!E22 | F22: =Janvier!F22+Février!F22+Mars!F22+Avril!F22+Mai!F22+Juin!F22+Juillet!F22+Aout!F22+Septembre!F22+Octobre!F22+Novembre!F22+Décembre!F22 | G22: =Janvier!G22+Février!G22+Mars!G22+Avril!G22+Mai!G22+Juin!G22+Juillet!G22+Aout!G22+Septembre!G22+Octobre!G22+Novembre!G22+Décembre!G22 | H22: =Janvier!H22+Février!H22+Mars!H22+Avril!H22+Mai!H22+Juin!H22+Juillet!H22+Aout!H22+Septembre!H22+Octobre!H22+Novembre!H22+Décembre!H22 | I22: =Janvier!I22+Février!I22+Mars!I22+Avril!I22+Mai!I22+Juin!I22+Juillet!I22+Aout!I22+Septembre!I22+Octobre!I22+Novembre!I22+Décembre!I22 | J22: =Janvier!J22+Février!J22+Mars!J22+Avril!J22+Mai!J22+Juin!J22+Juillet!J22+Aout!J22+Septembre!J22+Octobre!J22+Novembre!J22+Décembre!J22 | L22: =SUM(E22:F22,I22:K22) | M22: =L22+D22 | N22: =M22/655.957 | O22: =A22 | P22: =B22 | Q22: =C22 | R22: =D22 | S22: =X22/12*$A$1 | T22: =Y22/12*$A$1 | U22: 3500000 | V22: =$R22-U22 | W22: =R22/U22-1 | Z22: =Y22+X22 | AA22: =R22-Z22 | AB22: =R22/Z22-1 | AC22: =Z22/$Z$57 | AE22: =AF22-AD22 | AF22: 35000000 | AG22: =R22-AF22 | AH22: =R22/AF22-1 | AJ22: =AK22-AI22 | AK22: 35000000 | AL22: =R22-AK22 | AM22: =R22/AK22-1 | AN22: =AI22/12*$A$1 | AO22: =AJ22/12*$A$1 | AP22: =AO22+AN22 | AQ22: =R22-AP22 | AR22: =R22/AP22-1 | AU22: =AT22+AS22 | AV22: =AU22-Z22 | AW22: =AU22/Z22-1 | AX22: =BC22/12*$A$1 | AY22: =BD22/12*$A$1 | AZ22: =AY22+AX22 | BA22: =$R22-AZ22 | BB22: =$R22/AZ22-1 | BE22: =BD22+BC22 | BF22: =$R22-BE22 | BG22: =$R22/BE22-1
A23: INTERNL INDUSTRY PROVIDER 2IP | B23: =Janvier!B23+Février!B23+Mars!B23+Avril!B23+Mai!B23+Juin!B23+Juillet!B23+Aout!B23+Septembre!B23+Octobre!B23+Novembre!B23+Décembre!B23 | C23: =Janvier!C23+Février!C23+Mars!C23+Avril!C23+Mai!C23+Juin!C23+Juillet!C23+Aout!C23+Septembre!C23+Octobre!C23+Novembre!C23+Décembre!C23 | D23: =Janvier!D23+Février!D23+Mars!D23+Avril!D23+Mai!D23+Juin!D23+Juillet!D23+Aout!D23+Septembre!D23+Octobre!D23+Novembre!D23+Décembre!D23 | E23: =Janvier!E23+Février!E23+Mars!E23+Avril!E23+Mai!E23+Juin!E23+Juillet!E23+Aout!E23+Septembre!E23+Octobre!E23+Novembre!E23+Décembre!E23 | F23: =Janvier!F23+Février!F23+Mars!F23+Avril!F23+Mai!F23+Juin!F23+Juillet!F23+Aout!F23+Septembre!F23+Octobre!F23+Novembre!F23+Décembre!F23 | G23: =Janvier!G23+Février!G23+Mars!G23+Avril!G23+Mai!G23+Juin!G23+Juillet!G23+Aout!G23+Septembre!G23+Octobre!G23+Novembre!G23+Décembre!G23 | H23: =Janvier!H23+Février!H23+Mars!H23+Avril!H23+Mai!H23+Juin!H23+Juillet!H23+Aout!H23+Septembre!H23+Octobre!H23+Novembre!H23+Décembre!H23 | I23: =Janvier!I23+Février!I23+Mars!I23+Avril!I23+Mai!I23+Juin!I23+Juillet!I23+Aout!I23+Septembre!I23+Octobre!I23+Novembre!I23+Décembre!I23 | J23: =Janvier!J23+Février!J23+Mars!J23+Avril!J23+Mai!J23+Juin!J23+Juillet!J23+Aout!J23+Septembre!J23+Octobre!J23+Novembre!J23+Décembre!J23 | L23: =SUM(E23:F23,I23:K23) | M23: =L23+D23 | N23: =M23/655.957 | O23: =A23 | P23: =B23 | Q23: =C23 | R23: =D23 | S23: =X23/12*$A$1 | T23: =Y23/12*$A$1 | U23: 0 | V23: =$R23-U23 | W23: =R23/U23-1 | Z23: =Y23+X23 | AA23: =R23-Z23 | AB23: =R23/Z23-1 | AC23: =Z23/$Z$57 | AE23: =AF23-AD23 | AF23: =AC23*4901000000 | AG23: =R23-AF23 | AH23: =R23/AF23-1 | AJ23: =AK23-AI23 | AK23: 0 | AL23: =R23-AK23 | AM23: 0 | AN23: =AI23/12*$A$1 | AO23: =AJ23/12*$A$1 | AP23: =AO23+AN23 | AQ23: =R23-AP23 | AR23: 0 | AU23: =AT23+AS23 | AV23: =AU23-Z23 | AW23: =AU23/Z23-1 | AX23: =BC23/12*$A$1 | AY23: =BD23/12*$A$1 | AZ23: =AY23+AX23 | BA23: =$R23-AZ23 | BB23: =$R23/AZ23-1 | BE23: =BD23+BC23 | BF23: =$R23-BE23 | BG23: =$R23/BE23-1
A24: CEVA LOGISTICS UK | B24: =Janvier!B24+Février!B24+Mars!B24+Avril!B24+Mai!B24+Juin!B24+Juillet!B24+Aout!B24+Septembre!B24+Octobre!B24+Novembre!B24+Décembre!B24 | C24: =Janvier!C24+Février!C24+Mars!C24+Avril!C24+Mai!C24+Juin!C24+Juillet!C24+Aout!C24+Septembre!C24+Octobre!C24+Novembre!C24+Décembre!C24 | D24: =Janvier!D24+Février!D24+Mars!D24+Avril!D24+Mai!D24+Juin!D24+Juillet!D24+Aout!D24+Septembre!D24+Octobre!D24+Novembre!D24+Décembre!D24 | E24: =Janvier!E24+Février!E24+Mars!E24+Avril!E24+Mai!E24+Juin!E24+Juillet!E24+Aout!E24+Septembre!E24+Octobre!E24+Novembre!E24+Décembre!E24 | F24: =Janvier!F24+Février!F24+Mars!F24+Avril!F24+Mai!F24+Juin!F24+Juillet!F24+Aout!F24+Septembre!F24+Octobre!F24+Novembre!F24+Décembre!F24 | G24: =Janvier!G24+Février!G24+Mars!G24+Avril!G24+Mai!G24+Juin!G24+Juillet!G24+Aout!G24+Septembre!G24+Octobre!G24+Novembre!G24+Décembre!G24 | H24: =Janvier!H24+Février!H24+Mars!H24+Avril!H24+Mai!H24+Juin!H24+Juillet!H24+Aout!H24+Septembre!H24+Octobre!H24+Novembre!H24+Décembre!H24 | I24: =Janvier!I24+Février!I24+Mars!I24+Avril!I24+Mai!I24+Juin!I24+Juillet!I24+Aout!I24+Septembre!I24+Octobre!I24+Novembre!I24+Décembre!I24 | J24: =Janvier!J24+Février!J24+Mars!J24+Avril!J24+Mai!J24+Juin!J24+Juillet!J24+Aout!J24+Septembre!J24+Octobre!J24+Novembre!J24+Décembre!J24 | L24: =SUM(E24:F24,I24:K24) | M24: =L24+D24 | N24: =M24/655.957 | O24: =A24 | P24: =B24 | Q24: =C24 | R24: =D24 | S24: =X24/12*$A$1 | T24: =Y24/12*$A$1 | U24: 0 | V24: =$R24-U24 | W24: =R24/U24-1 | Z24: =Y24+X24 | AA24: =R24-Z24 | AB24: =R24/Z24-1 | AC24: =Z24/$Z$57 | AE24: =AF24-AD24 | AF24: 23725000 | AG24: =R24-AF24 | AH24: =R24/AF24-1 | AJ24: =AK24-AI24 | AK24: 23725000 | AL24: =R24-AK24 | AM24: =R24/AK24-1 | AN24: =AI24/12*$A$1 | AO24: =AJ24/12*$A$1 | AP24: =AO24+AN24 | AQ24: =R24-AP24 | AR24: =R24/AP24-1 | AU24: =AT24+AS24 | AV24: =AU24-Z24 | AW24: =AU24/Z24-1 | AX24: =BC24/12*$A$1 | AY24: =BD24/12*$A$1 | AZ24: =AY24+AX24 | BA24: =$R24-AZ24 | BB24: =$R24/AZ24-1 | BE24: =BD24+BC24 | BF24: =$R24-BE24 | BG24: =$R24/BE24-1
A25: MECANOFRED | B25: =Janvier!B25+Février!B25+Mars!B25+Avril!B25+Mai!B25+Juin!B25+Juillet!B25+Aout!B25+Septembre!B25+Octobre!B25+Novembre!B25+Décembre!B25 | C25: =Janvier!C25+Février!C25+Mars!C25+Avril!C25+Mai!C25+Juin!C25+Juillet!C25+Aout!C25+Septembre!C25+Octobre!C25+Novembre!C25+Décembre!C25 | D25: =Janvier!D25+Février!D25+Mars!D25+Avril!D25+Mai!D25+Juin!D25+Juillet!D25+Aout!D25+Septembre!D25+Octobre!D25+Novembre!D25+Décembre!D25 | E25: =Janvier!E25+Février!E25+Mars!E25+Avril!E25+Mai!E25+Juin!E25+Juillet!E25+Aout!E25+Septembre!E25+Octobre!E25+Novembre!E25+Décembre!E25 | F25: =Janvier!F25+Février!F25+Mars!F25+Avril!F25+Mai!F25+Juin!F25+Juillet!F25+Aout!F25+Septembre!F25+Octobre!F25+Novembre!F25+Décembre!F25 | G25: =Janvier!G25+Février!G25+Mars!G25+Avril!G25+Mai!G25+Juin!G25+Juillet!G25+Aout!G25+Septembre!G25+Octobre!G25+Novembre!G25+Décembre!G25 | H25: =Janvier!H25+Février!H25+Mars!H25+Avril!H25+Mai!H25+Juin!H25+Juillet!H25+Aout!H25+Septembre!H25+Octobre!H25+Novembre!H25+Décembre!H25 | I25: =Janvier!I25+Février!I25+Mars!I25+Avril!I25+Mai!I25+Juin!I25+Juillet!I25+Aout!I25+Septembre!I25+Octobre!I25+Novembre!I25+Décembre!I25 | J25: =Janvier!J25+Février!J25+Mars!J25+Avril!J25+Mai!J25+Juin!J25+Juillet!J25+Aout!J25+Septembre!J25+Octobre!J25+Novembre!J25+Décembre!J25 | L25: =SUM(E25:F25,I25:K25) | M25: =L25+D25 | N25: =M25/655.957 | O25: =A25 | P25: =B25 | Q25: =C25 | R25: =D25 | S25: =X25/12*$A$1 | T25: =Y25/12*$A$1 | U25: 0 | V25: =$R25-U25 | W25: =R25/U25-1 | Y25: 200000000 | Z25: =Y25+X25 | AA25: =R25-Z25 | AB25: =R25/Z25-1 | AC25: =Z25/$Z$57 | AE25: =AF25-AD25 | AF25: 180000000 | AG25: =R25-AF25 | AH25: =R25/AF25-1 | AJ25: =AK25-AI25 | AK25: 185000000 | AL25: =R25-AK25 | AM25: =R25/AK25-1 | AN25: =AI25/12*$A$1 | AO25: =AJ25/12*$A$1 | AP25: =AO25+AN25 | AQ25: =R25-AP25 | AR25: =R25/AP25-1 | AT25: 200000000 | AU25: =AT25+AS25 | AV25: =AU25-Z25 | AW25: =AU25/Z25-1 | AX25: =BC25/12*$A$1 | AY25: =BD25/12*$A$1 | AZ25: =AY25+AX25 | BA25: =$R25-AZ25 | BB25: =$R25/AZ25-1 | BD25: 270000000 | BE25: =BD25+BC25 | BF25: =$R25-BE25 | BG25: =$R25/BE25-1
A26: NOV OIL & GAS SERVICES GHANA | B26: =Janvier!B26+Février!B26+Mars!B26+Avril!B26+Mai!B26+Juin!B26+Juillet!B26+Aout!B26+Septembre!B26+Octobre!B26+Novembre!B26+Décembre!B26 | C26: =Janvier!C26+Février!C26+Mars!C26+Avril!C26+Mai!C26+Juin!C26+Juillet!C26+Aout!C26+Septembre!C26+Octobre!C26+Novembre!C26+Décembre!C26 | D26: =Janvier!D26+Février!D26+Mars!D26+Avril!D26+Mai!D26+Juin!D26+Juillet!D26+Aout!D26+Septembre!D26+Octobre!D26+Novembre!D26+Décembre!D26 | E26: =Janvier!E26+Février!E26+Mars!E26+Avril!E26+Mai!E26+Juin!E26+Juillet!E26+Aout!E26+Septembre!E26+Octobre!E26+Novembre!E26+Décembre!E26 | F26: =Janvier!F26+Février!F26+Mars!F26+Avril!F26+Mai!F26+Juin!F26+Juillet!F26+Aout!F26+Septembre!F26+Octobre!F26+Novembre!F26+Décembre!F26 | G26: =Janvier!G26+Février!G26+Mars!G26+Avril!G26+Mai!G26+Juin!G26+Juillet!G26+Aout!G26+Septembre!G26+Octobre!G26+Novembre!G26+Décembre!G26 | H26: =Janvier!H26+Février!H26+Mars!H26+Avril!H26+Mai!H26+Juin!H26+Juillet!H26+Aout!H26+Septembre!H26+Octobre!H26+Novembre!H26+Décembre!H26 | I26: =Janvier!I26+Février!I26+Mars!I26+Avril!I26+Mai!I26+Juin!I26+Juillet!I26+Aout!I26+Septembre!I26+Octobre!I26+Novembre!I26+Décembre!I26 | J26: =Janvier!J26+Février!J26+Mars!J26+Avril!J26+Mai!J26+Juin!J26+Juillet!J26+Aout!J26+Septembre!J26+Octobre!J26+Novembre!J26+Décembre!J26 | L26: =SUM(E26:F26,I26:K26) | M26: =L26+D26 | N26: =M26/655.957 | O26: =A26 | P26: =B26 | Q26: =C26 | R26: =D26 | S26: =X26/12*$A$1 | T26: =Y26/12*$A$1 | U26: 0 | V26: =$R26-U26 | W26: =R26/U26-1 | Z26: =Y26+X26 | AA26: =R26-Z26 | AB26: =R26/Z26-1 | AC26: =Z26/$Z$57 | AE26: =AF26-AD26 | AF26: =AC26*4901000000 | AG26: =R26-AF26 | AH26: =R26/AF26-1 | AJ26: =AK26-AI26 | AK26: 0 | AL26: =R26-AK26 | AM26: 0 | AN26: =AI26/12*$A$1 | AO26: =AJ26/12*$A$1 | AP26: =AO26+AN26 | AQ26: =R26-AP26 | AR26: 0 | AU26: =AT26+AS26 | AV26: =AU26-Z26 | AW26: =AU26/Z26-1 | AX26: =BC26/12*$A$1 | AY26: =BD26/12*$A$1 | AZ26: =AY26+AX26 | BA26: =$R26-AZ26 | BB26: =$R26/AZ26-1 | BE26: =BD26+BC26 | BF26: =$R26-BE26 | BG26: =$R26/BE26-1
A27: SAIPEM Portugal (SPCM) | B27: =Janvier!B27+Février!B27+Mars!B27+Avril!B27+Mai!B27+Juin!B27+Juillet!B27+Aout!B27+Septembre!B27+Octobre!B27+Novembre!B27+Décembre!B27 | C27: =Janvier!C27+Février!C27+Mars!C27+Avril!C27+Mai!C27+Juin!C27+Juillet!C27+Aout!C27+Septembre!C27+Octobre!C27+Novembre!C27+Décembre!C27 | D27: =Janvier!D27+Février!D27+Mars!D27+Avril!D27+Mai!D27+Juin!D27+Juillet!D27+Aout!D27+Septembre!D27+Octobre!D27+Novembre!D27+Décembre!D27 | E27: =Janvier!E27+Février!E27+Mars!E27+Avril!E27+Mai!E27+Juin!E27+Juillet!E27+Aout!E27+Septembre!E27+Octobre!E27+Novembre!E27+Décembre!E27 | F27: =Janvier!F27+Février!F27+Mars!F27+Avril!F27+Mai!F27+Juin!F27+Juillet!F27+Aout!F27+Septembre!F27+Octobre!F27+Novembre!F27+Décembre!F27 | G27: =Janvier!G27+Février!G27+Mars!G27+Avril!G27+Mai!G27+Juin!G27+Juillet!G27+Aout!G27+Septembre!G27+Octobre!G27+Novembre!G27+Décembre!G27 | H27: =Janvier!H27+Février!H27+Mars!H27+Avril!H27+Mai!H27+Juin!H27+Juillet!H27+Aout!H27+Septembre!H27+Octobre!H27+Novembre!H27+Décembre!H27 | I27: =Janvier!I27+Février!I27+Mars!I27+Avril!I27+Mai!I27+Juin!I27+Juillet!I27+Aout!I27+Septembre!I27+Octobre!I27+Novembre!I27+Décembre!I27 | J27: =Janvier!J27+Février!J27+Mars!J27+Avril!J27+Mai!J27+Juin!J27+Juillet!J27+Aout!J27+Septembre!J27+Octobre!J27+Novembre!J27+Décembre!J27 | L27: =SUM(E27:F27,I27:K27) | M27: =L27+D27 | N27: =M27/655.957 | O27: =A27 | P27: =B27 | Q27: =C27 | R27: =D27 | S27: =X27/12*$A$1 | T27: =Y27/12*$A$1 | U27: 0 | V27: =$R27-U27 | W27: =R27/U27-1 | Y27: 0 | Z27: =Y27+X27 | AA27: =R27-Z27 | AB27: =R27/Z27-1 | AC27: =Z27/$Z$57 | AD27: 14600000 | AE27: =AF27-AD27 | AF27: 25000000 | AG27: =R27-AF27 | AH27: =R27/AF27-1 | AI27: 14600000 | AJ27: =AK27-AI27 | AK27: 30000000 | AL27: =R27-AK27 | AM27: =R27/AK27-1 | AN27: =AI27/12*$A$1 | AO27: =AJ27/12*$A$1 | AP27: =AO27+AN27 | AQ27: =R27-AP27 | AR27: =R27/AP27-1 | AT27: 4000000 | AU27: =AT27+AS27 | AV27: =AU27-Z27 | AW27: =AU27/Z27-1 | AX27: =BC27/12*$A$1 | AY27: =BD27/12*$A$1 | AZ27: =AY27+AX27 | BA27: =$R27-AZ27 | BB27: =$R27/AZ27-1 | BD27: 20000000 | BE27: =BD27+BC27 | BF27: =$R27-BE27 | BG27: =$R27/BE27-1
A28: OMNI ENERGY | B28: =Janvier!B28+Février!B28+Mars!B28+Avril!B28+Mai!B28+Juin!B28+Juillet!B28+Aout!B28+Septembre!B28+Octobre!B28+Novembre!B28+Décembre!B28 | C28: =Janvier!C28+Février!C28+Mars!C28+Avril!C28+Mai!C28+Juin!C28+Juillet!C28+Aout!C28+Septembre!C28+Octobre!C28+Novembre!C28+Décembre!C28 | D28: =Janvier!D28+Février!D28+Mars!D28+Avril!D28+Mai!D28+Juin!D28+Juillet!D28+Aout!D28+Septembre!D28+Octobre!D28+Novembre!D28+Décembre!D28 | E28: =Janvier!E28+Février!E28+Mars!E28+Avril!E28+Mai!E28+Juin!E28+Juillet!E28+Aout!E28+Septembre!E28+Octobre!E28+Novembre!E28+Décembre!E28 | F28: =Janvier!F28+Février!F28+Mars!F28+Avril!F28+Mai!F28+Juin!F28+Juillet!F28+Aout!F28+Septembre!F28+Octobre!F28+Novembre!F28+Décembre!F28 | G28: =Janvier!G28+Février!G28+Mars!G28+Avril!G28+Mai!G28+Juin!G28+Juillet!G28+Aout!G28+Septembre!G28+Octobre!G28+Novembre!G28+Décembre!G28 | H28: =Janvier!H28+Février!H28+Mars!H28+Avril!H28+Mai!H28+Juin!H28+Juillet!H28+Aout!H28+Septembre!H28+Octobre!H28+Novembre!H28+Décembre!H28 | I28: =Janvier!I28+Février!I28+Mars!I28+Avril!I28+Mai!I28+Juin!I28+Juillet!I28+Aout!I28+Septembre!I28+Octobre!I28+Novembre!I28+Décembre!I28 | J28: =Janvier!J28+Février!J28+Mars!J28+Avril!J28+Mai!J28+Juin!J28+Juillet!J28+Aout!J28+Septembre!J28+Octobre!J28+Novembre!J28+Décembre!J28 | L28: =SUM(E28:F28,I28:K28) | M28: =L28+D28 | N28: =M28/655.957 | O28: =A28 | P28: =B28 | Q28: =C28 | R28: =D28 | S28: =X28/12*$A$1 | T28: =Y28/12*$A$1 | U28: 300000 | V28: =$R28-U28 | W28: =R28/U28-1 | Z28: =Y28+X28 | AA28: =R28-Z28 | AB28: =R28/Z28-1 | AC28: =Z28/$Z$57 | AD28: 17150000 | AE28: =AF28-AD28 | AF28: 270000000 | AG28: =R28-AF28 | AH28: =R28/AF28-1 | AI28: 17150000 | AJ28: =AK28-AI28 | AK28: 312150000 | AL28: =R28-AK28 | AM28: =R28/AK28-1 | AN28: =AI28/12*$A$1 | AO28: =AJ28/12*$A$1 | AP28: =AO28+AN28 | AQ28: =R28-AP28 | AR28: =R28/AP28-1 | AU28: =AT28+AS28 | AV28: =AU28-Z28 | AW28: =AU28/Z28-1 | AX28: =BC28/12*$A$1 | AY28: =BD28/12*$A$1 | AZ28: =AY28+AX28 | BA28: =$R28-AZ28 | BB28: =$R28/AZ28-1 | BE28: =BD28+BC28 | BF28: =$R28-BE28 | BG28: =$R28/BE28-1
A29: SERVIZI ENERGIA ITALIA - SEI | B29: =Janvier!B29+Février!B29+Mars!B29+Avril!B29+Mai!B29+Juin!B29+Juillet!B29+Aout!B29+Septembre!B29+Octobre!B29+Novembre!B29+Décembre!B29 | C29: =Janvier!C29+Février!C29+Mars!C29+Avril!C29+Mai!C29+Juin!C29+Juillet!C29+Aout!C29+Septembre!C29+Octobre!C29+Novembre!C29+Décembre!C29 | D29: =Janvier!D29+Février!D29+Mars!D29+Avril!D29+Mai!D29+Juin!D29+Juillet!D29+Aout!D29+Septembre!D29+Octobre!D29+Novembre!D29+Décembre!D29 | E29: =Janvier!E29+Février!E29+Mars!E29+Avril!E29+Mai!E29+Juin!E29+Juillet!E29+Aout!E29+Septembre!E29+Octobre!E29+Novembre!E29+Décembre!E29 | F29: =Janvier!F29+Février!F29+Mars!F29+Avril!F29+Mai!F29+Juin!F29+Juillet!F29+Aout!F29+Septembre!F29+Octobre!F29+Novembre!F29+Décembre!F29 | G29: =Janvier!G29+Février!G29+Mars!G29+Avril!G29+Mai!G29+Juin!G29+Juillet!G29+Aout!G29+Septembre!G29+Octobre!G29+Novembre!G29+Décembre!G29 | H29: =Janvier!H29+Février!H29+Mars!H29+Avril!H29+Mai!H29+Juin!H29+Juillet!H29+Aout!H29+Septembre!H29+Octobre!H29+Novembre!H29+Décembre!H29 | I29: =Janvier!I29+Février!I29+Mars!I29+Avril!I29+Mai!I29+Juin!I29+Juillet!I29+Aout!I29+Septembre!I29+Octobre!I29+Novembre!I29+Décembre!I29 | J29: =Janvier!J29+Février!J29+Mars!J29+Avril!J29+Mai!J29+Juin!J29+Juillet!J29+Aout!J29+Septembre!J29+Octobre!J29+Novembre!J29+Décembre!J29 | L29: =SUM(E29:F29,I29:K29) | M29: =L29+D29 | N29: =M29/655.957 | O29: =A29 | P29: =B29 | Q29: =C29 | R29: =D29 | S29: =X29/12*$A$1 | T29: =Y29/12*$A$1 | U29: 0 | V29: =$R29-U29 | W29: =R29/U29-1 | Z29: =Y29+X29 | AA29: =R29-Z29 | AB29: =R29/Z29-1 | AC29: =Z29/$Z$57 | AE29: =AF29-AD29 | AF29: 500000 | AG29: =R29-AF29 | AH29: =R29/AF29-1 | AJ29: =AK29-AI29 | AK29: 500000 | AL29: =R29-AK29 | AM29: =R29/AK29-1 | AN29: =AI29/12*$A$1 | AO29: =AJ29/12*$A$1 | AP29: =AO29+AN29 | AQ29: =R29-AP29 | AR29: =R29/AP29-1 | AU29: =AT29+AS29 | AV29: =AU29-Z29 | AW29: =AU29/Z29-1 | AX29: =BC29/12*$A$1 | AY29: =BD29/12*$A$1 | AZ29: =AY29+AX29 | BA29: =$R29-AZ29 | BB29: =$R29/AZ29-1 | BE29: =BD29+BC29 | BF29: =$R29-BE29 | BG29: =$R29/BE29-1
A30: PETROFAC | B30: =Janvier!B30+Février!B30+Mars!B30+Avril!B30+Mai!B30+Juin!B30+Juillet!B30+Aout!B30+Septembre!B30+Octobre!B30+Novembre!B30+Décembre!B30 | C30: =Janvier!C30+Février!C30+Mars!C30+Avril!C30+Mai!C30+Juin!C30+Juillet!C30+Aout!C30+Septembre!C30+Octobre!C30+Novembre!C30+Décembre!C30 | D30: =Janvier!D30+Février!D30+Mars!D30+Avril!D30+Mai!D30+Juin!D30+Juillet!D30+Aout!D30+Septembre!D30+Octobre!D30+Novembre!D30+Décembre!D30 | E30: =Janvier!E30+Février!E30+Mars!E30+Avril!E30+Mai!E30+Juin!E30+Juillet!E30+Aout!E30+Septembre!E30+Octobre!E30+Novembre!E30+Décembre!E30 | F30: =Janvier!F30+Février!F30+Mars!F30+Avril!F30+Mai!F30+Juin!F30+Juillet!F30+Aout!F30+Septembre!F30+Octobre!F30+Novembre!F30+Décembre!F30 | G30: =Janvier!G30+Février!G30+Mars!G30+Avril!G30+Mai!G30+Juin!G30+Juillet!G30+Aout!G30+Septembre!G30+Octobre!G30+Novembre!G30+Décembre!G30 | H30: =Janvier!H30+Février!H30+Mars!H30+Avril!H30+Mai!H30+Juin!H30+Juillet!H30+Aout!H30+Septembre!H30+Octobre!H30+Novembre!H30+Décembre!H30 | I30: =Janvier!I30+Février!I30+Mars!I30+Avril!I30+Mai!I30+Juin!I30+Juillet!I30+Aout!I30+Septembre!I30+Octobre!I30+Novembre!I30+Décembre!I30 | J30: =Janvier!J30+Février!J30+Mars!J30+Avril!J30+Mai!J30+Juin!J30+Juillet!J30+Aout!J30+Septembre!J30+Octobre!J30+Novembre!J30+Décembre!J30 | L30: =SUM(E30:F30,I30:K30) | M30: =L30+D30 | N30: =M30/655.957 | O30: =A30 | P30: =B30 | Q30: =C30 | R30: =D30 | S30: =X30/12*$A$1 | T30: =Y30/12*$A$1 | U30: 0 | V30: =$R30-U30 | W30: =R30/U30-1 | Y30: 50000000 | Z30: =Y30+X30 | AA30: =R30-Z30 | AB30: =R30/Z30-1 | AC30: =Z30/$Z$57 | AE30: =AF30-AD30 | AF30: 215000 | AG30: =R30-AF30 | AH30: =R30/AF30-1 | AJ30: =AK30-AI30 | AK30: 215000 | AL30: =R30-AK30 | AM30: =R30/AK30-1 | AN30: =AI30/12*$A$1 | AO30: =AJ30/12*$A$1 | AP30: =AO30+AN30 | AQ30: =R30-AP30 | AR30: =R30/AP30-1 | AT30: 500000 | AU30: =AT30+AS30 | AV30: =AU30-Z30 | AW30: =AU30/Z30-1 | AX30: =BC30/12*$A$1 | AY30: =BD30/12*$A$1 | AZ30: =AY30+AX30 | BA30: =$R30-AZ30 | BB30: =$R30/AZ30-1 | BD30: 15000000 | BE30: =BD30+BC30 | BF30: =$R30-BE30 | BG30: =$R30/BE30-1
A31: CAPEWEST LOGISTICS | B31: =Janvier!B31+Février!B31+Mars!B31+Avril!B31+Mai!B31+Juin!B31+Juillet!B31+Aout!B31+Septembre!B31+Octobre!B31+Novembre!B31+Décembre!B31 | C31: =Janvier!C31+Février!C31+Mars!C31+Avril!C31+Mai!C31+Juin!C31+Juillet!C31+Aout!C31+Septembre!C31+Octobre!C31+Novembre!C31+Décembre!C31 | D31: =Janvier!D31+Février!D31+Mars!D31+Avril!D31+Mai!D31+Juin!D31+Juillet!D31+Aout!D31+Septembre!D31+Octobre!D31+Novembre!D31+Décembre!D31 | E31: =Janvier!E31+Février!E31+Mars!E31+Avril!E31+Mai!E31+Juin!E31+Juillet!E31+Aout!E31+Septembre!E31+Octobre!E31+Novembre!E31+Décembre!E31 | F31: =Janvier!F31+Février!F31+Mars!F31+Avril!F31+Mai!F31+Juin!F31+Juillet!F31+Aout!F31+Septembre!F31+Octobre!F31+Novembre!F31+Décembre!F31 | G31: =Janvier!G31+Février!G31+Mars!G31+Avril!G31+Mai!G31+Juin!G31+Juillet!G31+Aout!G31+Septembre!G31+Octobre!G31+Novembre!G31+Décembre!G31 | H31: =Janvier!H31+Février!H31+Mars!H31+Avril!H31+Mai!H31+Juin!H31+Juillet!H31+Aout!H31+Septembre!H31+Octobre!H31+Novembre!H31+Décembre!H31 | I31: =Janvier!I31+Février!I31+Mars!I31+Avril!I31+Mai!I31+Juin!I31+Juillet!I31+Aout!I31+Septembre!I31+Octobre!I31+Novembre!I31+Décembre!I31 | J31: =Janvier!J31+Février!J31+Mars!J31+Avril!J31+Mai!J31+Juin!J31+Juillet!J31+Aout!J31+Septembre!J31+Octobre!J31+Novembre!J31+Décembre!J31 | L31: =SUM(E31:F31,I31:K31) | M31: =L31+D31 | N31: =M31/655.957 | O31: =A31 | P31: =B31 | Q31: =C31 | R31: =D31 | S31: =X31/12*$A$1 | T31: =Y31/12*$A$1 | U31: 0 | V31: =$R31-U31 | W31: =R31/U31-1 | Z31: =Y31+X31 | AA31: =R31-Z31 | AB31: =R31/Z31-1 | AC31: =Z31/$Z$57 | AE31: =AF31-AD31 | AF31: =AC31*4901000000 | AG31: =R31-AF31 | AH31: =R31/AF31-1 | AJ31: =AK31-AI31 | AK31: 0 | AL31: =R31-AK31 | AM31: 0 | AN31: =AI31/12*$A$1 | AO31: =AJ31/12*$A$1 | AP31: =AO31+AN31 | AQ31: =R31-AP31 | AR31: 0 | AU31: =AT31+AS31 | AV31: =AU31-Z31 | AW31: =AU31/Z31-1 | AX31: =BC31/12*$A$1 | AY31: =BD31/12*$A$1 | AZ31: =AY31+AX31 | BA31: =$R31-AZ31 | BB31: =$R31/AZ31-1 | BE31: =BD31+BC31 | BF31: =$R31-BE31 | BG31: =$R31/BE31-1
A32: BOLLORE NORWAY (PROSAFE) | B32: =Janvier!B32+Février!B32+Mars!B32+Avril!B32+Mai!B32+Juin!B32+Juillet!B32+Aout!B32+Septembre!B32+Octobre!B32+Novembre!B32+Décembre!B32 | C32: =Janvier!C32+Février!C32+Mars!C32+Avril!C32+Mai!C32+Juin!C32+Juillet!C32+Aout!C32+Septembre!C32+Octobre!C32+Novembre!C32+Décembre!C32 | D32: =Janvier!D32+Février!D32+Mars!D32+Avril!D32+Mai!D32+Juin!D32+Juillet!D32+Aout!D32+Septembre!D32+Octobre!D32+Novembre!D32+Décembre!D32 | E32: =Janvier!E32+Février!E32+Mars!E32+Avril!E32+Mai!E32+Juin!E32+Juillet!E32+Aout!E32+Septembre!E32+Octobre!E32+Novembre!E32+Décembre!E32 | F32: =Janvier!F32+Février!F32+Mars!F32+Avril!F32+Mai!F32+Juin!F32+Juillet!F32+Aout!F32+Septembre!F32+Octobre!F32+Novembre!F32+Décembre!F32 | G32: =Janvier!G32+Février!G32+Mars!G32+Avril!G32+Mai!G32+Juin!G32+Juillet!G32+Aout!G32+Septembre!G32+Octobre!G32+Novembre!G32+Décembre!G32 | H32: =Janvier!H32+Février!H32+Mars!H32+Avril!H32+Mai!H32+Juin!H32+Juillet!H32+Aout!H32+Septembre!H32+Octobre!H32+Novembre!H32+Décembre!H32 | I32: =Janvier!I32+Février!I32+Mars!I32+Avril!I32+Mai!I32+Juin!I32+Juillet!I32+Aout!I32+Septembre!I32+Octobre!I32+Novembre!I32+Décembre!I32 | J32: =Janvier!J32+Février!J32+Mars!J32+Avril!J32+Mai!J32+Juin!J32+Juillet!J32+Aout!J32+Septembre!J32+Octobre!J32+Novembre!J32+Décembre!J32 | L32: =SUM(E32:F32,I32:K32) | M32: =L32+D32 | N32: =M32/655.957 | O32: =A32 | P32: =B32 | Q32: =C32 | R32: =D32 | S32: =X32/12*$A$1 | T32: =Y32/12*$A$1 | U32: 0 | V32: =$R32-U32 | W32: =R32/U32-1 | Y32: 2000000 | Z32: =Y32+X32 | AA32: =R32-Z32 | AB32: =R32/Z32-1 | AC32: =Z32/$Z$57 | AE32: =AF32-AD32 | AF32: =AC32*4901000000 | AG32: =R32-AF32 | AH32: =R32/AF32-1 | AJ32: =AK32-AI32 | AK32: 0 | AL32: =R32-AK32 | AM32: 0 | AN32: =AI32/12*$A$1 | AO32: =AJ32/12*$A$1 | AP32: =AO32+AN32 | AQ32: =R32-AP32 | AR32: 0 | AT32: 25000 | AU32: =AT32+AS32 | AV32: =AU32-Z32 | AW32: =AU32/Z32-1 | AX32: =BC32/12*$A$1 | AY32: =BD32/12*$A$1 | AZ32: =AY32+AX32 | BA32: =$R32-AZ32 | BB32: =$R32/AZ32-1 | BD32: 25000 | BE32: =BD32+BC32 | BF32: =$R32-BE32 | BG32: =$R32/BE32-1
A33: AGL GHANA | B33: =Janvier!B33+Février!B33+Mars!B33+Avril!B33+Mai!B33+Juin!B33+Juillet!B33+Aout!B33+Septembre!B33+Octobre!B33+Novembre!B33+Décembre!B33 | C33: =Janvier!C33+Février!C33+Mars!C33+Avril!C33+Mai!C33+Juin!C33+Juillet!C33+Aout!C33+Septembre!C33+Octobre!C33+Novembre!C33+Décembre!C33 | D33: =Janvier!D33+Février!D33+Mars!D33+Avril!D33+Mai!D33+Juin!D33+Juillet!D33+Aout!D33+Septembre!D33+Octobre!D33+Novembre!D33+Décembre!D33 | E33: =Janvier!E33+Février!E33+Mars!E33+Avril!E33+Mai!E33+Juin!E33+Juillet!E33+Aout!E33+Septembre!E33+Octobre!E33+Novembre!E33+Décembre!E33 | F33: =Janvier!F33+Février!F33+Mars!F33+Avril!F33+Mai!F33+Juin!F33+Juillet!F33+Aout!F33+Septembre!F33+Octobre!F33+Novembre!F33+Décembre!F33 | G33: =Janvier!G33+Février!G33+Mars!G33+Avril!G33+Mai!G33+Juin!G33+Juillet!G33+Aout!G33+Septembre!G33+Octobre!G33+Novembre!G33+Décembre!G33 | H33: =Janvier!H33+Février!H33+Mars!H33+Avril!H33+Mai!H33+Juin!H33+Juillet!H33+Aout!H33+Septembre!H33+Octobre!H33+Novembre!H33+Décembre!H33 | I33: =Janvier!I33+Février!I33+Mars!I33+Avril!I33+Mai!I33+Juin!I33+Juillet!I33+Aout!I33+Septembre!I33+Octobre!I33+Novembre!I33+Décembre!I33 | J33: =Janvier!J33+Février!J33+Mars!J33+Avril!J33+Mai!J33+Juin!J33+Juillet!J33+Aout!J33+Septembre!J33+Octobre!J33+Novembre!J33+Décembre!J33 | L33: =SUM(E33:F33,I33:K33) | M33: =L33+D33 | N33: =M33/655.957 | O33: =A33 | P33: =B33 | Q33: =C33 | R33: =D33 | S33: =X33/12*$A$1 | T33: =Y33/12*$A$1 | U33: 0 | V33: =$R33-U33 | W33: =R33/U33-1 | Z33: =Y33+X33 | AA33: =R33-Z33 | AB33: =R33/Z33-1 | AC33: =Z33/$Z$57 | AE33: =AF33-AD33 | AF33: =AC33*4901000000 | AG33: =R33-AF33 | AH33: =R33/AF33-1 | AJ33: =AK33-AI33 | AK33: 0 | AL33: =R33-AK33 | AM33: 0 | AN33: =AI33/12*$A$1 | AO33: =AJ33/12*$A$1 | AP33: =AO33+AN33 | AQ33: =R33-AP33 | AR33: 0 | AU33: =AT33+AS33 | AV33: =AU33-Z33 | AW33: =AU33/Z33-1 | AX33: =BC33/12*$A$1 | AY33: =BD33/12*$A$1 | AZ33: =AY33+AX33 | BA33: =$R33-AZ33 | BB33: =$R33/AZ33-1 | BE33: =BD33+BC33 | BF33: =$R33-BE33 | BG33: =$R33/BE33-1
A34: OMA CI | B34: =Janvier!B34+Février!B34+Mars!B34+Avril!B34+Mai!B34+Juin!B34+Juillet!B34+Aout!B34+Septembre!B34+Octobre!B34+Novembre!B34+Décembre!B34 | C34: =Janvier!C34+Février!C34+Mars!C34+Avril!C34+Mai!C34+Juin!C34+Juillet!C34+Aout!C34+Septembre!C34+Octobre!C34+Novembre!C34+Décembre!C34 | D34: =Janvier!D34+Février!D34+Mars!D34+Avril!D34+Mai!D34+Juin!D34+Juillet!D34+Aout!D34+Septembre!D34+Octobre!D34+Novembre!D34+Décembre!D34 | E34: =Janvier!E34+Février!E34+Mars!E34+Avril!E34+Mai!E34+Juin!E34+Juillet!E34+Aout!E34+Septembre!E34+Octobre!E34+Novembre!E34+Décembre!E34 | F34: =Janvier!F34+Février!F34+Mars!F34+Avril!F34+Mai!F34+Juin!F34+Juillet!F34+Aout!F34+Septembre!F34+Octobre!F34+Novembre!F34+Décembre!F34 | G34: =Janvier!G34+Février!G34+Mars!G34+Avril!G34+Mai!G34+Juin!G34+Juillet!G34+Aout!G34+Septembre!G34+Octobre!G34+Novembre!G34+Décembre!G34 | H34: =Janvier!H34+Février!H34+Mars!H34+Avril!H34+Mai!H34+Juin!H34+Juillet!H34+Aout!H34+Septembre!H34+Octobre!H34+Novembre!H34+Décembre!H34 | I34: =Janvier!I34+Février!I34+Mars!I34+Avril!I34+Mai!I34+Juin!I34+Juillet!I34+Aout!I34+Septembre!I34+Octobre!I34+Novembre!I34+Décembre!I34 | J34: =Janvier!J34+Février!J34+Mars!J34+Avril!J34+Mai!J34+Juin!J34+Juillet!J34+Aout!J34+Septembre!J34+Octobre!J34+Novembre!J34+Décembre!J34 | L34: =SUM(E34:F34,I34:K34) | M34: =L34+D34 | N34: =M34/655.957 | O34: =A34 | P34: =B34 | Q34: =C34 | R34: =D34 | S34: =X34/12*$A$1 | T34: =Y34/12*$A$1 | U34: 0 | V34: =$R34-U34 | W34: =R34/U34-1 | Z34: =Y34+X34 | AA34: =R34-Z34 | AB34: =R34/Z34-1 | AC34: =Z34/$Z$57 | AE34: =AF34-AD34 | AF34: 500000 | AG34: =R34-AF34 | AH34: =R34/AF34-1 | AJ34: =AK34-AI34 | AK34: 500000 | AL34: =R34-AK34 | AM34: =R34/AK34-1 | AN34: =AI34/12*$A$1 | AO34: =AJ34/12*$A$1 | AP34: =AO34+AN34 | AQ34: =R34-AP34 | AR34: =R34/AP34-1 | AU34: =AT34+AS34 | AV34: =AU34-Z34 | AW34: =AU34/Z34-1 | AX34: =BC34/12*$A$1 | AY34: =BD34/12*$A$1 | AZ34: =AY34+AX34 | BA34: =$R34-AZ34 | BB34: =$R34/AZ34-1 | BE34: =BD34+BC34 | BF34: =$R34-BE34 | BG34: =$R34/BE34-1
A35: AYIMAN LOGISTICS | B35: =Janvier!B35+Février!B35+Mars!B35+Avril!B35+Mai!B35+Juin!B35+Juillet!B35+Aout!B35+Septembre!B35+Octobre!B35+Novembre!B35+Décembre!B35 | C35: =Janvier!C35+Février!C35+Mars!C35+Avril!C35+Mai!C35+Juin!C35+Juillet!C35+Aout!C35+Septembre!C35+Octobre!C35+Novembre!C35+Décembre!C35 | D35: =Janvier!D35+Février!D35+Mars!D35+Avril!D35+Mai!D35+Juin!D35+Juillet!D35+Aout!D35+Septembre!D35+Octobre!D35+Novembre!D35+Décembre!D35 | E35: =Janvier!E35+Février!E35+Mars!E35+Avril!E35+Mai!E35+Juin!E35+Juillet!E35+Aout!E35+Septembre!E35+Octobre!E35+Novembre!E35+Décembre!E35 | F35: =Janvier!F35+Février!F35+Mars!F35+Avril!F35+Mai!F35+Juin!F35+Juillet!F35+Aout!F35+Septembre!F35+Octobre!F35+Novembre!F35+Décembre!F35 | G35: =Janvier!G35+Février!G35+Mars!G35+Avril!G35+Mai!G35+Juin!G35+Juillet!G35+Aout!G35+Septembre!G35+Octobre!G35+Novembre!G35+Décembre!G35 | H35: =Janvier!H35+Février!H35+Mars!H35+Avril!H35+Mai!H35+Juin!H35+Juillet!H35+Aout!H35+Septembre!H35+Octobre!H35+Novembre!H35+Décembre!H35 | I35: =Janvier!I35+Février!I35+Mars!I35+Avril!I35+Mai!I35+Juin!I35+Juillet!I35+Aout!I35+Septembre!I35+Octobre!I35+Novembre!I35+Décembre!I35 | J35: =Janvier!J35+Février!J35+Mars!J35+Avril!J35+Mai!J35+Juin!J35+Juillet!J35+Aout!J35+Septembre!J35+Octobre!J35+Novembre!J35+Décembre!J35 | L35: =SUM(E35:F35,I35:K35) | M35: =L35+D35 | N35: =M35/655.957 | O35: =A35 | P35: =B35 | Q35: =C35 | R35: =D35 | S35: =X35/12*$A$1 | T35: =Y35/12*$A$1 | U35: 0 | V35: =$R35-U35 | W35: =R35/U35-1 | Z35: =Y35+X35 | AA35: =R35-Z35 | AB35: =R35/Z35-1 | AC35: =Z35/$Z$57 | AE35: =AF35-AD35 | AF35: 900000 | AG35: =R35-AF35 | AH35: =R35/AF35-1 | AJ35: =AK35-AI35 | AK35: 900000 | AL35: =R35-AK35 | AM35: =R35/AK35-1 | AN35: =AI35/12*$A$1 | AO35: =AJ35/12*$A$1 | AP35: =AO35+AN35 | AQ35: =R35-AP35 | AR35: =R35/AP35-1 | AT35: 100000 | AU35: =AT35+AS35 | AV35: =AU35-Z35 | AW35: =AU35/Z35-1 | AX35: =BC35/12*$A$1 | AY35: =BD35/12*$A$1 | AZ35: =AY35+AX35 | BA35: =$R35-AZ35 | BB35: =$R35/AZ35-1 | BD35: 132000 | BE35: =BD35+BC35 | BF35: =$R35-BE35 | BG35: =$R35/BE35-1
A36: AGL DIVERS | B36: =Janvier!B36+Février!B36+Mars!B36+Avril!B36+Mai!B36+Juin!B36+Juillet!B36+Aout!B36+Septembre!B36+Octobre!B36+Novembre!B36+Décembre!B36 | C36: =Janvier!C36+Février!C36+Mars!C36+Avril!C36+Mai!C36+Juin!C36+Juillet!C36+Aout!C36+Septembre!C36+Octobre!C36+Novembre!C36+Décembre!C36 | D36: =Janvier!D36+Février!D36+Mars!D36+Avril!D36+Mai!D36+Juin!D36+Juillet!D36+Aout!D36+Septembre!D36+Octobre!D36+Novembre!D36+Décembre!D36 | E36: =Janvier!E36+Février!E36+Mars!E36+Avril!E36+Mai!E36+Juin!E36+Juillet!E36+Aout!E36+Septembre!E36+Octobre!E36+Novembre!E36+Décembre!E36 | F36: =Janvier!F36+Février!F36+Mars!F36+Avril!F36+Mai!F36+Juin!F36+Juillet!F36+Aout!F36+Septembre!F36+Octobre!F36+Novembre!F36+Décembre!F36 | G36: =Janvier!G36+Février!G36+Mars!G36+Avril!G36+Mai!G36+Juin!G36+Juillet!G36+Aout!G36+Septembre!G36+Octobre!G36+Novembre!G36+Décembre!G36 | H36: =Janvier!H36+Février!H36+Mars!H36+Avril!H36+Mai!H36+Juin!H36+Juillet!H36+Aout!H36+Septembre!H36+Octobre!H36+Novembre!H36+Décembre!H36 | I36: =Janvier!I36+Février!I36+Mars!I36+Avril!I36+Mai!I36+Juin!I36+Juillet!I36+Aout!I36+Septembre!I36+Octobre!I36+Novembre!I36+Décembre!I36 | J36: =Janvier!J36+Février!J36+Mars!J36+Avril!J36+Mai!J36+Juin!J36+Juillet!J36+Aout!J36+Septembre!J36+Octobre!J36+Novembre!J36+Décembre!J36 | L36: =SUM(E36:F36,I36:K36) | M36: =L36+D36 | N36: =M36/655.957 | O36: =A36 | P36: =B36 | Q36: =C36 | R36: =D36 | S36: =X36/12*$A$1 | T36: =Y36/12*$A$1 | U36: 300000 | V36: =$R36-U36 | W36: =R36/U36-1 | Z36: =Y36+X36 | AA36: =R36-Z36 | AB36: =R36/Z36-1 | AC36: =Z36/$Z$57 | AE36: =AF36-AD36 | AF36: =AC36*4901000000 | AG36: =R36-AF36 | AH36: =R36/AF36-1 | AJ36: =AK36-AI36 | AK36: 0 | AL36: =R36-AK36 | AM36: 0 | AN36: =AI36/12*$A$1 | AO36: =AJ36/12*$A$1 | AP36: =AO36+AN36 | AQ36: =R36-AP36 | AR36: 0 | AT36: 500000 | AU36: =AT36+AS36 | AV36: =AU36-Z36 | AW36: =AU36/Z36-1 | AX36: =BC36/12*$A$1 | AY36: =BD36/12*$A$1 | AZ36: =AY36+AX36 | BA36: =$R36-AZ36 | BB36: =$R36/AZ36-1 | BD36: 500000 | BE36: =BD36+BC36 | BF36: =$R36-BE36 | BG36: =$R36/BE36-1
A37: 2THEPOINT | B37: =Janvier!B37+Février!B37+Mars!B37+Avril!B37+Mai!B37+Juin!B37+Juillet!B37+Aout!B37+Septembre!B37+Octobre!B37+Novembre!B37+Décembre!B37 | C37: =Janvier!C37+Février!C37+Mars!C37+Avril!C37+Mai!C37+Juin!C37+Juillet!C37+Aout!C37+Septembre!C37+Octobre!C37+Novembre!C37+Décembre!C37 | D37: =Janvier!D37+Février!D37+Mars!D37+Avril!D37+Mai!D37+Juin!D37+Juillet!D37+Aout!D37+Septembre!D37+Octobre!D37+Novembre!D37+Décembre!D37 | E37: =Janvier!E37+Février!E37+Mars!E37+Avril!E37+Mai!E37+Juin!E37+Juillet!E37+Aout!E37+Septembre!E37+Octobre!E37+Novembre!E37+Décembre!E37 | F37: =Janvier!F37+Février!F37+Mars!F37+Avril!F37+Mai!F37+Juin!F37+Juillet!F37+Aout!F37+Septembre!F37+Octobre!F37+Novembre!F37+Décembre!F37 | G37: =Janvier!G37+Février!G37+Mars!G37+Avril!G37+Mai!G37+Juin!G37+Juillet!G37+Aout!G37+Septembre!G37+Octobre!G37+Novembre!G37+Décembre!G37 | H37: =Janvier!H37+Février!H37+Mars!H37+Avril!H37+Mai!H37+Juin!H37+Juillet!H37+Aout!H37+Septembre!H37+Octobre!H37+Novembre!H37+Décembre!H37 | I37: =Janvier!I37+Février!I37+Mars!I37+Avril!I37+Mai!I37+Juin!I37+Juillet!I37+Aout!I37+Septembre!I37+Octobre!I37+Novembre!I37+Décembre!I37 | J37: =Janvier!J37+Février!J37+Mars!J37+Avril!J37+Mai!J37+Juin!J37+Juillet!J37+Aout!J37+Septembre!J37+Octobre!J37+Novembre!J37+Décembre!J37 | L37: =SUM(E37:F37,I37:K37) | M37: =L37+D37 | N37: =M37/655.957 | O37: =A37 | P37: =B37 | Q37: =C37 | R37: =D37 | S37: =X37/12*$A$1 | T37: =Y37/12*$A$1 | U37: 0 | V37: =$R37-U37 | W37: =R37/U37-1 | Y37: 5000000 | Z37: =Y37+X37 | AA37: =R37-Z37 | AB37: =R37/Z37-1 | AC37: =Z37/$Z$57 | AE37: =AF37-AD37 | AF37: 25000000 | AG37: =R37-AF37 | AH37: =R37/AF37-1 | AJ37: =AK37-AI37 | AK37: 25000000 | AL37: =R37-AK37 | AM37: =R37/AK37-1 | AN37: =AI37/12*$A$1 | AO37: =AJ37/12*$A$1 | AP37: =AO37+AN37 | AQ37: =R37-AP37 | AR37: =R37/AP37-1 | AT37: 115000 | AU37: =AT37+AS37 | AV37: =AU37-Z37 | AW37: =AU37/Z37-1 | AX37: =BC37/12*$A$1 | AY37: =BD37/12*$A$1 | AZ37: =AY37+AX37 | BA37: =$R37-AZ37 | BB37: =$R37/AZ37-1 | BD37: 115000 | BE37: =BD37+BC37 | BF37: =$R37-BE37 | BG37: =$R37/BE37-1
A38: SCHLUMBERGER OILFIELD EASTERN | B38: =Janvier!B38+Février!B38+Mars!B38+Avril!B38+Mai!B38+Juin!B38+Juillet!B38+Aout!B38+Septembre!B38+Octobre!B38+Novembre!B38+Décembre!B38 | C38: =Janvier!C38+Février!C38+Mars!C38+Avril!C38+Mai!C38+Juin!C38+Juillet!C38+Aout!C38+Septembre!C38+Octobre!C38+Novembre!C38+Décembre!C38 | D38: =Janvier!D38+Février!D38+Mars!D38+Avril!D38+Mai!D38+Juin!D38+Juillet!D38+Aout!D38+Septembre!D38+Octobre!D38+Novembre!D38+Décembre!D38 | E38: =Janvier!E38+Février!E38+Mars!E38+Avril!E38+Mai!E38+Juin!E38+Juillet!E38+Aout!E38+Septembre!E38+Octobre!E38+Novembre!E38+Décembre!E38 | F38: =Janvier!F38+Février!F38+Mars!F38+Avril!F38+Mai!F38+Juin!F38+Juillet!F38+Aout!F38+Septembre!F38+Octobre!F38+Novembre!F38+Décembre!F38 | G38: =Janvier!G38+Février!G38+Mars!G38+Avril!G38+Mai!G38+Juin!G38+Juillet!G38+Aout!G38+Septembre!G38+Octobre!G38+Novembre!G38+Décembre!G38 | H38: =Janvier!H38+Février!H38+Mars!H38+Avril!H38+Mai!H38+Juin!H38+Juillet!H38+Aout!H38+Septembre!H38+Octobre!H38+Novembre!H38+Décembre!H38 | I38: =Janvier!I38+Février!I38+Mars!I38+Avril!I38+Mai!I38+Juin!I38+Juillet!I38+Aout!I38+Septembre!I38+Octobre!I38+Novembre!I38+Décembre!I38 | J38: =Janvier!J38+Février!J38+Mars!J38+Avril!J38+Mai!J38+Juin!J38+Juillet!J38+Aout!J38+Septembre!J38+Octobre!J38+Novembre!J38+Décembre!J38 | L38: =SUM(E38:F38,I38:K38) | M38: =L38+D38 | N38: =M38/655.957 | O38: =A38 | P38: =B38 | Q38: =C38 | R38: =D38 | S38: =X38/12*$A$1 | T38: =Y38/12*$A$1 | U38: 12500000 | V38: =$R38-U38 | W38: =R38/U38-1 | Y38: 25000000 | Z38: =Y38+X38 | AA38: =R38-Z38 | AB38: =R38/Z38-1 | AC38: =Z38/$Z$57 | AD38: 297000000 | AE38: =AF38-AD38 | AF38: 432000000 | AG38: =R38-AF38 | AH38: =R38/AF38-1 | AI38: 297000000 | AJ38: =AK38-AI38 | AK38: 667000000 | AL38: =R38-AK38 | AM38: =R38/AK38-1 | AN38: =AI38/12*$A$1 | AO38: =AJ38/12*$A$1 | AP38: =AO38+AN38 | AQ38: =R38-AP38 | AR38: =R38/AP38-1 | AS38: 350000000 | AT38: =250000000 | AU38: =AT38+AS38 | AV38: =AU38-Z38 | AW38: =AU38/Z38-1 | AX38: =BC38/12*$A$1 | AY38: =BD38/12*$A$1 | AZ38: =AY38+AX38 | BA38: =$R38-AZ38 | BB38: =$R38/AZ38-1 | BC38: 335000000 | BD38: 280000000 | BE38: =BD38+BC38 | BF38: =$R38-BE38 | BG38: =$R38/BE38-1
A39: STRACT OFFSHORE | B39: =Janvier!B39+Février!B39+Mars!B39+Avril!B39+Mai!B39+Juin!B39+Juillet!B39+Aout!B39+Septembre!B39+Octobre!B39+Novembre!B39+Décembre!B39 | C39: =Janvier!C39+Février!C39+Mars!C39+Avril!C39+Mai!C39+Juin!C39+Juillet!C39+Aout!C39+Septembre!C39+Octobre!C39+Novembre!C39+Décembre!C39 | D39: =Janvier!D39+Février!D39+Mars!D39+Avril!D39+Mai!D39+Juin!D39+Juillet!D39+Aout!D39+Septembre!D39+Octobre!D39+Novembre!D39+Décembre!D39 | E39: =Janvier!E39+Février!E39+Mars!E39+Avril!E39+Mai!E39+Juin!E39+Juillet!E39+Aout!E39+Septembre!E39+Octobre!E39+Novembre!E39+Décembre!E39 | F39: =Janvier!F39+Février!F39+Mars!F39+Avril!F39+Mai!F39+Juin!F39+Juillet!F39+Aout!F39+Septembre!F39+Octobre!F39+Novembre!F39+Décembre!F39 | G39: =Janvier!G39+Février!G39+Mars!G39+Avril!G39+Mai!G39+Juin!G39+Juillet!G39+Aout!G39+Septembre!G39+Octobre!G39+Novembre!G39+Décembre!G39 | H39: =Janvier!H39+Février!H39+Mars!H39+Avril!H39+Mai!H39+Juin!H39+Juillet!H39+Aout!H39+Septembre!H39+Octobre!H39+Novembre!H39+Décembre!H39 | I39: =Janvier!I39+Février!I39+Mars!I39+Avril!I39+Mai!I39+Juin!I39+Juillet!I39+Aout!I39+Septembre!I39+Octobre!I39+Novembre!I39+Décembre!I39 | J39: =Janvier!J39+Février!J39+Mars!J39+Avril!J39+Mai!J39+Juin!J39+Juillet!J39+Aout!J39+Septembre!J39+Octobre!J39+Novembre!J39+Décembre!J39 | L39: =SUM(E39:F39,I39:K39) | M39: =L39+D39 | N39: =M39/655.957 | O39: =A39 | P39: =B39 | Q39: =C39 | R39: =D39 | S39: =X39/12*$A$1 | T39: =Y39/12*$A$1 | U39: 0 | V39: =$R39-U39 | W39: =R39/U39-1 | Z39: =Y39+X39 | AA39: =R39-Z39 | AB39: =R39/Z39-1 | AC39: =Z39/$Z$57 | AE39: =AF39-AD39 | AF39: 15000000 | AG39: =R39-AF39 | AH39: =R39/AF39-1 | AJ39: =AK39-AI39 | AK39: 20000000 | AL39: =R39-AK39 | AM39: =R39/AK39-1 | AN39: =AI39/12*$A$1 | AO39: =AJ39/12*$A$1 | AP39: =AO39+AN39 | AQ39: =R39-AP39 | AR39: =R39/AP39-1 | AT39: 45000000 | AU39: =AT39+AS39 | AV39: =AU39-Z39 | AW39: =AU39/Z39-1 | AX39: =BC39/12*$A$1 | AY39: =BD39/12*$A$1 | AZ39: =AY39+AX39 | BA39: =$R39-AZ39 | BB39: =$R39/AZ39-1 | BD39: 75000000 | BE39: =BD39+BC39 | BF39: =$R39-BE39 | BG39: =$R39/BE39-1
A40: DOF SUBSEA | B40: =Janvier!B40+Février!B40+Mars!B40+Avril!B40+Mai!B40+Juin!B40+Juillet!B40+Aout!B40+Septembre!B40+Octobre!B40+Novembre!B40+Décembre!B40 | C40: =Janvier!C40+Février!C40+Mars!C40+Avril!C40+Mai!C40+Juin!C40+Juillet!C40+Aout!C40+Septembre!C40+Octobre!C40+Novembre!C40+Décembre!C40 | D40: =Janvier!D40+Février!D40+Mars!D40+Avril!D40+Mai!D40+Juin!D40+Juillet!D40+Aout!D40+Septembre!D40+Octobre!D40+Novembre!D40+Décembre!D40 | E40: =Janvier!E40+Février!E40+Mars!E40+Avril!E40+Mai!E40+Juin!E40+Juillet!E40+Aout!E40+Septembre!E40+Octobre!E40+Novembre!E40+Décembre!E40 | F40: =Janvier!F40+Février!F40+Mars!F40+Avril!F40+Mai!F40+Juin!F40+Juillet!F40+Aout!F40+Septembre!F40+Octobre!F40+Novembre!F40+Décembre!F40 | G40: =Janvier!G40+Février!G40+Mars!G40+Avril!G40+Mai!G40+Juin!G40+Juillet!G40+Aout!G40+Septembre!G40+Octobre!G40+Novembre!G40+Décembre!G40 | H40: =Janvier!H40+Février!H40+Mars!H40+Avril!H40+Mai!H40+Juin!H40+Juillet!H40+Aout!H40+Septembre!H40+Octobre!H40+Novembre!H40+Décembre!H40 | I40: =Janvier!I40+Février!I40+Mars!I40+Avril!I40+Mai!I40+Juin!I40+Juillet!I40+Aout!I40+Septembre!I40+Octobre!I40+Novembre!I40+Décembre!I40 | J40: =Janvier!J40+Février!J40+Mars!J40+Avril!J40+Mai!J40+Juin!J40+Juillet!J40+Aout!J40+Septembre!J40+Octobre!J40+Novembre!J40+Décembre!J40 | L40: =SUM(E40:F40,I40:K40) | M40: =L40+D40 | N40: =M40/655.957 | O40: =A40 | P40: =B40 | Q40: =C40 | R40: =D40 | S40: =X40/12*$A$1 | T40: =Y40/12*$A$1 | U40: 0 | V40: =$R40-U40 | W40: =R40/U40-1 | Z40: =Y40+X40 | AA40: =R40-Z40 | AB40: =R40/Z40-1 | AC40: =Z40/$Z$57 | AE40: =AF40-AD40 | AF40: 1500000 | AG40: =R40-AF40 | AH40: =R40/AF40-1 | AJ40: =AK40-AI40 | AK40: 1500000 | AL40: =R40-AK40 | AM40: =R40/AK40-1 | AN40: =AI40/12*$A$1 | AO40: =AJ40/12*$A$1 | AP40: =AO40+AN40 | AQ40: =R40-AP40 | AR40: =R40/AP40-1 | AT40: 8000000 | AU40: =AT40+AS40 | AV40: =AU40-Z40 | AW40: =AU40/Z40-1 | AX40: =BC40/12*$A$1 | AY40: =BD40/12*$A$1 | AZ40: =AY40+AX40 | BA40: =$R40-AZ40 | BB40: =$R40/AZ40-1 | BD40: 8000000 | BE40: =BD40+BC40 | BF40: =$R40-BE40 | BG40: =$R40/BE40-1
A41: ICM COTE D'IVOIRE P/C TRANSOCEAN | B41: =Janvier!B41+Février!B41+Mars!B41+Avril!B41+Mai!B41+Juin!B41+Juillet!B41+Aout!B41+Septembre!B41+Octobre!B41+Novembre!B41+Décembre!B41 | C41: =Janvier!C41+Février!C41+Mars!C41+Avril!C41+Mai!C41+Juin!C41+Juillet!C41+Aout!C41+Septembre!C41+Octobre!C41+Novembre!C41+Décembre!C41 | D41: =Janvier!D41+Février!D41+Mars!D41+Avril!D41+Mai!D41+Juin!D41+Juillet!D41+Aout!D41+Septembre!D41+Octobre!D41+Novembre!D41+Décembre!D41 | E41: =Janvier!E41+Février!E41+Mars!E41+Avril!E41+Mai!E41+Juin!E41+Juillet!E41+Aout!E41+Septembre!E41+Octobre!E41+Novembre!E41+Décembre!E41 | F41: =Janvier!F41+Février!F41+Mars!F41+Avril!F41+Mai!F41+Juin!F41+Juillet!F41+Aout!F41+Septembre!F41+Octobre!F41+Novembre!F41+Décembre!F41 | G41: =Janvier!G41+Février!G41+Mars!G41+Avril!G41+Mai!G41+Juin!G41+Juillet!G41+Aout!G41+Septembre!G41+Octobre!G41+Novembre!G41+Décembre!G41 | H41: =Janvier!H41+Février!H41+Mars!H41+Avril!H41+Mai!H41+Juin!H41+Juillet!H41+Aout!H41+Septembre!H41+Octobre!H41+Novembre!H41+Décembre!H41 | I41: =Janvier!I41+Février!I41+Mars!I41+Avril!I41+Mai!I41+Juin!I41+Juillet!I41+Aout!I41+Septembre!I41+Octobre!I41+Novembre!I41+Décembre!I41 | J41: =Janvier!J41+Février!J41+Mars!J41+Avril!J41+Mai!J41+Juin!J41+Juillet!J41+Aout!J41+Septembre!J41+Octobre!J41+Novembre!J41+Décembre!J41 | L41: =SUM(E41:F41,I41:K41) | M41: =L41+D41 | N41: =M41/655.957 | O41: =A41 | P41: =B41 | Q41: =C41 | R41: =D41 | S41: =X41/12*$A$1 | T41: =Y41/12*$A$1 | U41: 0 | V41: =$R41-U41 | W41: =R41/U41-1 | Z41: =Y41+X41 | AA41: =R41-Z41 | AB41: =R41/Z41-1 | AC41: =Z41/$Z$57 | AE41: =AF41-AD41 | AF41: 0 | AG41: =R41-AF41 | AH41: =R41/AF41-1 | AJ41: =AK41-AI41 | AK41: 0 | AL41: =R41-AK41 | AM41: 0 | AN41: =AI41/12*$A$1 | AO41: =AJ41/12*$A$1 | AP41: =AO41+AN41 | AQ41: =R41-AP41 | AR41: 0 | AU41: =AT41+AS41 | AV41: =AU41-Z41 | AW41: =AU41/Z41-1 | AX41: =BC41/12*$A$1 | AY41: =BD41/12*$A$1 | AZ41: =AY41+AX41 | BA41: =$R41-AZ41 | BB41: =$R41/AZ41-1 | BE41: =BD41+BC41 | BF41: =$R41-BE41 | BG41: =$R41/BE41-1
A42: SUBTEC | B42: =Janvier!B42+Février!B42+Mars!B42+Avril!B42+Mai!B42+Juin!B42+Juillet!B42+Aout!B42+Septembre!B42+Octobre!B42+Novembre!B42+Décembre!B42 | C42: =Janvier!C42+Février!C42+Mars!C42+Avril!C42+Mai!C42+Juin!C42+Juillet!C42+Aout!C42+Septembre!C42+Octobre!C42+Novembre!C42+Décembre!C42 | D42: =Janvier!D42+Février!D42+Mars!D42+Avril!D42+Mai!D42+Juin!D42+Juillet!D42+Aout!D42+Septembre!D42+Octobre!D42+Novembre!D42+Décembre!D42 | E42: =Janvier!E42+Février!E42+Mars!E42+Avril!E42+Mai!E42+Juin!E42+Juillet!E42+Aout!E42+Septembre!E42+Octobre!E42+Novembre!E42+Décembre!E42 | F42: =Janvier!F42+Février!F42+Mars!F42+Avril!F42+Mai!F42+Juin!F42+Juillet!F42+Aout!F42+Septembre!F42+Octobre!F42+Novembre!F42+Décembre!F42 | G42: =Janvier!G42+Février!G42+Mars!G42+Avril!G42+Mai!G42+Juin!G42+Juillet!G42+Aout!G42+Septembre!G42+Octobre!G42+Novembre!G42+Décembre!G42 | H42: =Janvier!H42+Février!H42+Mars!H42+Avril!H42+Mai!H42+Juin!H42+Juillet!H42+Aout!H42+Septembre!H42+Octobre!H42+Novembre!H42+Décembre!H42 | I42: =Janvier!I42+Février!I42+Mars!I42+Avril!I42+Mai!I42+Juin!I42+Juillet!I42+Aout!I42+Septembre!I42+Octobre!I42+Novembre!I42+Décembre!I42 | J42: =Janvier!J42+Février!J42+Mars!J42+Avril!J42+Mai!J42+Juin!J42+Juillet!J42+Aout!J42+Septembre!J42+Octobre!J42+Novembre!J42+Décembre!J42 | L42: =SUM(E42:F42,I42:K42) | M42: =L42+D42 | N42: =M42/655.957 | O42: =A42 | P42: =B42 | Q42: =C42 | R42: =D42 | S42: =X42/12*$A$1 | T42: =Y42/12*$A$1 | U42: 765000 | V42: =$R42-U42 | W42: =R42/U42-1 | X42: 9165000 | Y42: 3000000 | Z42: =Y42+X42 | AA42: =R42-Z42 | AB42: =R42/Z42-1 | AC42: =Z42/$Z$57 | AD42: 12000000 | AE42: =AF42-AD42 | AF42: 15000000 | AG42: =R42-AF42 | AH42: =R42/AF42-1 | AI42: 12000000 | AJ42: =AK42-AI42 | AK42: 15000000 | AL42: =R42-AK42 | AM42: =R42/AK42-1 | AN42: =AI42/12*$A$1 | AO42: =AJ42/12*$A$1 | AP42: =AO42+AN42 | AQ42: =R42-AP42 | AR42: =R42/AP42-1 | AS42: 9165000 | AT42: 3500000 | AU42: =AT42+AS42 | AV42: =AU42-Z42 | AW42: =AU42/Z42-1 | AX42: =BC42/12*$A$1 | AY42: =BD42/12*$A$1 | AZ42: =AY42+AX42 | BA42: =$R42-AZ42 | BB42: =$R42/AZ42-1 | BC42: 9165000 | BD42: 5000000 | BE42: =BD42+BC42 | BF42: =$R42-BE42 | BG42: =$R42/BE42-1
A43: SAPURA DRILLING HOLDING | B43: =Janvier!B43+Février!B43+Mars!B43+Avril!B43+Mai!B43+Juin!B43+Juillet!B43+Aout!B43+Septembre!B43+Octobre!B43+Novembre!B43+Décembre!B43 | C43: =Janvier!C43+Février!C43+Mars!C43+Avril!C43+Mai!C43+Juin!C43+Juillet!C43+Aout!C43+Septembre!C43+Octobre!C43+Novembre!C43+Décembre!C43 | D43: =Janvier!D43+Février!D43+Mars!D43+Avril!D43+Mai!D43+Juin!D43+Juillet!D43+Aout!D43+Septembre!D43+Octobre!D43+Novembre!D43+Décembre!D43 | E43: =Janvier!E43+Février!E43+Mars!E43+Avril!E43+Mai!E43+Juin!E43+Juillet!E43+Aout!E43+Septembre!E43+Octobre!E43+Novembre!E43+Décembre!E43 | F43: =Janvier!F43+Février!F43+Mars!F43+Avril!F43+Mai!F43+Juin!F43+Juillet!F43+Aout!F43+Septembre!F43+Octobre!F43+Novembre!F43+Décembre!F43 | G43: =Janvier!G43+Février!G43+Mars!G43+Avril!G43+Mai!G43+Juin!G43+Juillet!G43+Aout!G43+Septembre!G43+Octobre!G43+Novembre!G43+Décembre!G43 | H43: =Janvier!H43+Février!H43+Mars!H43+Avril!H43+Mai!H43+Juin!H43+Juillet!H43+Aout!H43+Septembre!H43+Octobre!H43+Novembre!H43+Décembre!H43 | I43: =Janvier!I43+Février!I43+Mars!I43+Avril!I43+Mai!I43+Juin!I43+Juillet!I43+Aout!I43+Septembre!I43+Octobre!I43+Novembre!I43+Décembre!I43 | J43: =Janvier!J43+Février!J43+Mars!J43+Avril!J43+Mai!J43+Juin!J43+Juillet!J43+Aout!J43+Septembre!J43+Octobre!J43+Novembre!J43+Décembre!J43 | L43: =SUM(E43:F43,I43:K43) | M43: =L43+D43 | N43: =M43/655.957 | O43: =A43 | P43: =B43 | Q43: =C43 | R43: =D43 | S43: =X43/12*$A$1 | T43: =Y43/12*$A$1 | U43: 0 | V43: =$R43-U43 | W43: =R43/U43-1 | Z43: =Y43+X43 | AA43: =R43-Z43 | AB43: =R43/Z43-1 | AC43: =Z43/$Z$57 | AE43: =AF43-AD43 | AF43: =AC43*4901000000 | AG43: =R43-AF43 | AH43: =R43/AF43-1 | AJ43: =AK43-AI43 | AK43: 0 | AL43: =R43-AK43 | AM43: 0 | AN43: =AI43/12*$A$1 | AO43: =AJ43/12*$A$1 | AP43: =AO43+AN43 | AQ43: =R43-AP43 | AR43: 0 | AU43: =AT43+AS43 | AV43: =AU43-Z43 | AW43: =AU43/Z43-1 | AX43: =BC43/12*$A$1 | AY43: =BD43/12*$A$1 | AZ43: =AY43+AX43 | BA43: =$R43-AZ43 | BB43: =$R43/AZ43-1 | BE43: =BD43+BC43 | BF43: =$R43-BE43 | BG43: =$R43/BE43-1
A44: BOSKALIS | B44: =Janvier!B44+Février!B44+Mars!B44+Avril!B44+Mai!B44+Juin!B44+Juillet!B44+Aout!B44+Septembre!B44+Octobre!B44+Novembre!B44+Décembre!B44 | C44: =Janvier!C44+Février!C44+Mars!C44+Avril!C44+Mai!C44+Juin!C44+Juillet!C44+Aout!C44+Septembre!C44+Octobre!C44+Novembre!C44+Décembre!C44 | D44: =Janvier!D44+Février!D44+Mars!D44+Avril!D44+Mai!D44+Juin!D44+Juillet!D44+Aout!D44+Septembre!D44+Octobre!D44+Novembre!D44+Décembre!D44 | E44: =Janvier!E44+Février!E44+Mars!E44+Avril!E44+Mai!E44+Juin!E44+Juillet!E44+Aout!E44+Septembre!E44+Octobre!E44+Novembre!E44+Décembre!E44 | F44: =Janvier!F44+Février!F44+Mars!F44+Avril!F44+Mai!F44+Juin!F44+Juillet!F44+Aout!F44+Septembre!F44+Octobre!F44+Novembre!F44+Décembre!F44 | G44: =Janvier!G44+Février!G44+Mars!G44+Avril!G44+Mai!G44+Juin!G44+Juillet!G44+Aout!G44+Septembre!G44+Octobre!G44+Novembre!G44+Décembre!G44 | H44: =Janvier!H44+Février!H44+Mars!H44+Avril!H44+Mai!H44+Juin!H44+Juillet!H44+Aout!H44+Septembre!H44+Octobre!H44+Novembre!H44+Décembre!H44 | I44: =Janvier!I44+Février!I44+Mars!I44+Avril!I44+Mai!I44+Juin!I44+Juillet!I44+Aout!I44+Septembre!I44+Octobre!I44+Novembre!I44+Décembre!I44 | J44: =Janvier!J44+Février!J44+Mars!J44+Avril!J44+Mai!J44+Juin!J44+Juillet!J44+Aout!J44+Septembre!J44+Octobre!J44+Novembre!J44+Décembre!J44 | L44: =SUM(E44:F44,I44:K44) | M44: =L44+D44 | N44: =M44/655.957 | O44: =A44 | P44: =B44 | Q44: =C44 | R44: =D44 | S44: =X44/12*$A$1 | T44: =Y44/12*$A$1 | U44: 0 | V44: =$R44-U44 | W44: =R44/U44-1 | Z44: =Y44+X44 | AA44: =R44-Z44 | AB44: =R44/Z44-1 | AC44: =Z44/$Z$57 | AD44: 48000000 | AE44: =AF44-AD44 | AF44: 75000000 | AG44: =R44-AF44 | AH44: =R44/AF44-1 | AI44: 48000000 | AJ44: =AK44-AI44 | AK44: 80000000 | AL44: =R44-AK44 | AM44: =R44/AK44-1 | AN44: =AI44/12*$A$1 | AO44: =AJ44/12*$A$1 | AP44: =AO44+AN44 | AQ44: =R44-AP44 | AR44: =R44/AP44-1 | AS44: 18000000 | AT44: 18000000 | AU44: =AT44+AS44 | AV44: =AU44-Z44 | AW44: =AU44/Z44-1 | AX44: =BC44/12*$A$1 | AY44: =BD44/12*$A$1 | AZ44: =AY44+AX44 | BA44: =$R44-AZ44 | BB44: =$R44/AZ44-1 | BC44: 12350000 | BD44: 20000000 | BE44: =BD44+BC44 | BF44: =$R44-BE44 | BG44: =$R44/BE44-1
A45: ENI COTE D'IVOIRE | B45: =Janvier!B45+Février!B45+Mars!B45+Avril!B45+Mai!B45+Juin!B45+Juillet!B45+Aout!B45+Septembre!B45+Octobre!B45+Novembre!B45+Décembre!B45 | C45: =Janvier!C45+Février!C45+Mars!C45+Avril!C45+Mai!C45+Juin!C45+Juillet!C45+Aout!C45+Septembre!C45+Octobre!C45+Novembre!C45+Décembre!C45 | D45: =Janvier!D45+Février!D45+Mars!D45+Avril!D45+Mai!D45+Juin!D45+Juillet!D45+Aout!D45+Septembre!D45+Octobre!D45+Novembre!D45+Décembre!D45 | E45: =Janvier!E45+Février!E45+Mars!E45+Avril!E45+Mai!E45+Juin!E45+Juillet!E45+Aout!E45+Septembre!E45+Octobre!E45+Novembre!E45+Décembre!E45 | F45: =Janvier!F45+Février!F45+Mars!F45+Avril!F45+Mai!F45+Juin!F45+Juillet!F45+Aout!F45+Septembre!F45+Octobre!F45+Novembre!F45+Décembre!F45 | G45: =Janvier!G45+Février!G45+Mars!G45+Avril!G45+Mai!G45+Juin!G45+Juillet!G45+Aout!G45+Septembre!G45+Octobre!G45+Novembre!G45+Décembre!G45 | H45: =Janvier!H45+Février!H45+Mars!H45+Avril!H45+Mai!H45+Juin!H45+Juillet!H45+Aout!H45+Septembre!H45+Octobre!H45+Novembre!H45+Décembre!H45 | I45: =Janvier!I45+Février!I45+Mars!I45+Avril!I45+Mai!I45+Juin!I45+Juillet!I45+Aout!I45+Septembre!I45+Octobre!I45+Novembre!I45+Décembre!I45 | J45: =Janvier!J45+Février!J45+Mars!J45+Avril!J45+Mai!J45+Juin!J45+Juillet!J45+Aout!J45+Septembre!J45+Octobre!J45+Novembre!J45+Décembre!J45 | L45: =SUM(E45:F45,I45:K45) | M45: =L45+D45 | N45: =M45/655.957 | O45: =A45 | P45: =B45 | Q45: =C45 | R45: =D45 | S45: =X45/12*$A$1 | T45: =Y45/12*$A$1 | U45: 500000 | V45: =$R45-U45 | W45: =R45/U45-1 | X45: 0 | Y45: 100000000 | Z45: =Y45+X45 | AA45: =R45-Z45 | AB45: =R45/Z45-1 | AC45: =Z45/$Z$57 | AD45: 96992000 | AE45: =AF45-AD45 | AF45: 350000000 | AG45: =R45-AF45 | AH45: =R45/AF45-1 | AI45: 120000000 | AJ45: =AK45-AI45 | AK45: 240000000 | AL45: =R45-AK45 | AM45: =R45/AK45-1 | AN45: =AI45/12*$A$1 | AO45: =AJ45/12*$A$1 | AP45: =AO45+AN45 | AQ45: =R45-AP45 | AR45: =R45/AP45-1 | AS45: 120000000 | AT45: 80000000 | AU45: =AT45+AS45 | AV45: =AU45-Z45 | AW45: =AU45/Z45-1 | AX45: =BC45/12*$A$1 | AY45: =BD45/12*$A$1 | AZ45: =AY45+AX45 | BA45: =$R45-AZ45 | BB45: =$R45/AZ45-1 | BC45: 165000000 | BD45: 120000000 | BE45: =BD45+BC45 | BF45: =$R45-BE45 | BG45: =$R45/BE45-1
A46: COMPAGNIE IVOIRIENNE D'INSPECTION | B46: =Janvier!B46+Février!B46+Mars!B46+Avril!B46+Mai!B46+Juin!B46+Juillet!B46+Aout!B46+Septembre!B46+Octobre!B46+Novembre!B46+Décembre!B46 | C46: =Janvier!C46+Février!C46+Mars!C46+Avril!C46+Mai!C46+Juin!C46+Juillet!C46+Aout!C46+Septembre!C46+Octobre!C46+Novembre!C46+Décembre!C46 | D46: =Janvier!D46+Février!D46+Mars!D46+Avril!D46+Mai!D46+Juin!D46+Juillet!D46+Aout!D46+Septembre!D46+Octobre!D46+Novembre!D46+Décembre!D46 | E46: =Janvier!E46+Février!E46+Mars!E46+Avril!E46+Mai!E46+Juin!E46+Juillet!E46+Aout!E46+Septembre!E46+Octobre!E46+Novembre!E46+Décembre!E46 | F46: =Janvier!F46+Février!F46+Mars!F46+Avril!F46+Mai!F46+Juin!F46+Juillet!F46+Aout!F46+Septembre!F46+Octobre!F46+Novembre!F46+Décembre!F46 | G46: =Janvier!G46+Février!G46+Mars!G46+Avril!G46+Mai!G46+Juin!G46+Juillet!G46+Aout!G46+Septembre!G46+Octobre!G46+Novembre!G46+Décembre!G46 | H46: =Janvier!H46+Février!H46+Mars!H46+Avril!H46+Mai!H46+Juin!H46+Juillet!H46+Aout!H46+Septembre!H46+Octobre!H46+Novembre!H46+Décembre!H46 | I46: =Janvier!I46+Février!I46+Mars!I46+Avril!I46+Mai!I46+Juin!I46+Juillet!I46+Aout!I46+Septembre!I46+Octobre!I46+Novembre!I46+Décembre!I46 | J46: =Janvier!J46+Février!J46+Mars!J46+Avril!J46+Mai!J46+Juin!J46+Juillet!J46+Aout!J46+Septembre!J46+Octobre!J46+Novembre!J46+Décembre!J46 | L46: =SUM(E46:F46,I46:K46) | M46: =L46+D46 | N46: =M46/655.957 | O46: =A46 | P46: =B46 | Q46: =C46 | R46: =D46 | S46: =X46/12*$A$1 | T46: =Y46/12*$A$1 | U46: 0 | V46: =$R46-U46 | W46: =R46/U46-1 | Z46: =Y46+X46 | AA46: =R46-Z46 | AB46: =R46/Z46-1 | AC46: =Z46/$Z$57 | AD46: 68000000 | AE46: =AF46-AD46 | AF46: 180000000 | AG46: =R46-AF46 | AH46: =R46/AF46-1 | AI46: 68000000 | AJ46: =AK46-AI46 | AK46: 177000000 | AL46: =R46-AK46 | AM46: =R46/AK46-1 | AN46: =AI46/12*$A$1 | AO46: =AJ46/12*$A$1 | AP46: =AO46+AN46 | AQ46: =R46-AP46 | AR46: =R46/AP46-1 | AU46: =AT46+AS46 | AV46: =AU46-Z46 | AW46: =AU46/Z46-1 | AX46: =BC46/12*$A$1 | AY46: =BD46/12*$A$1 | AZ46: =AY46+AX46 | BA46: =$R46-AZ46 | BB46: =$R46/AZ46-1 | BE46: =BD46+BC46 | BF46: =$R46-BE46 | BG46: =$R46/BE46-1
A47: PETRO-SEA LOGISTICS | B47: =Janvier!B47+Février!B47+Mars!B47+Avril!B47+Mai!B47+Juin!B47+Juillet!B47+Aout!B47+Septembre!B47+Octobre!B47+Novembre!B47+Décembre!B47 | C47: =Janvier!C47+Février!C47+Mars!C47+Avril!C47+Mai!C47+Juin!C47+Juillet!C47+Aout!C47+Septembre!C47+Octobre!C47+Novembre!C47+Décembre!C47 | D47: =Janvier!D47+Février!D47+Mars!D47+Avril!D47+Mai!D47+Juin!D47+Juillet!D47+Aout!D47+Septembre!D47+Octobre!D47+Novembre!D47+Décembre!D47 | E47: =Janvier!E47+Février!E47+Mars!E47+Avril!E47+Mai!E47+Juin!E47+Juillet!E47+Aout!E47+Septembre!E47+Octobre!E47+Novembre!E47+Décembre!E47 | F47: =Janvier!F47+Février!F47+Mars!F47+Avril!F47+Mai!F47+Juin!F47+Juillet!F47+Aout!F47+Septembre!F47+Octobre!F47+Novembre!F47+Décembre!F47 | G47: =Janvier!G47+Février!G47+Mars!G47+Avril!G47+Mai!G47+Juin!G47+Juillet!G47+Aout!G47+Septembre!G47+Octobre!G47+Novembre!G47+Décembre!G47 | H47: =Janvier!H47+Février!H47+Mars!H47+Avril!H47+Mai!H47+Juin!H47+Juillet!H47+Aout!H47+Septembre!H47+Octobre!H47+Novembre!H47+Décembre!H47 | I47: =Janvier!I47+Février!I47+Mars!I47+Avril!I47+Mai!I47+Juin!I47+Juillet!I47+Aout!I47+Septembre!I47+Octobre!I47+Novembre!I47+Décembre!I47 | J47: =Janvier!J47+Février!J47+Mars!J47+Avril!J47+Mai!J47+Juin!J47+Juillet!J47+Aout!J47+Septembre!J47+Octobre!J47+Novembre!J47+Décembre!J47 | L47: =SUM(E47:F47,I47:K47) | M47: =L47+D47 | N47: =M47/655.957 | O47: =A47 | P47: =B47 | Q47: =C47 | R47: =D47 | S47: =X47/12*$A$1 | T47: =Y47/12*$A$1 | U47: 0 | V47: =$R47-U47 | W47: =R47/U47-1 | Z47: =Y47+X47 | AA47: =R47-Z47 | AB47: =R47/Z47-1 | AC47: =Z47/$Z$57 | AE47: =AF47-AD47 | AF47: =AC47*4901000000 | AG47: =R47-AF47 | AH47: =R47/AF47-1 | AJ47: =AK47-AI47 | AK47: 0 | AL47: =R47-AK47 | AM47: 0 | AN47: =AI47/12*$A$1 | AO47: =AJ47/12*$A$1 | AP47: =AO47+AN47 | AQ47: =R47-AP47 | AR47: 0 | AU47: =AT47+AS47 | AV47: =AU47-Z47 | AW47: =AU47/Z47-1 | AX47: =BC47/12*$A$1 | AY47: =BD47/12*$A$1 | AZ47: =AY47+AX47 | BA47: =$R47-AZ47 | BB47: =$R47/AZ47-1 | BE47: =BD47+BC47 | BF47: =$R47-BE47 | BG47: =$R47/BE47-1
A48: OMASUP ENERGY | B48: =Janvier!B48+Février!B48+Mars!B48+Avril!B48+Mai!B48+Juin!B48+Juillet!B48+Aout!B48+Septembre!B48+Octobre!B48+Novembre!B48+Décembre!B48 | C48: =Janvier!C48+Février!C48+Mars!C48+Avril!C48+Mai!C48+Juin!C48+Juillet!C48+Aout!C48+Septembre!C48+Octobre!C48+Novembre!C48+Décembre!C48 | D48: =Janvier!D48+Février!D48+Mars!D48+Avril!D48+Mai!D48+Juin!D48+Juillet!D48+Aout!D48+Septembre!D48+Octobre!D48+Novembre!D48+Décembre!D48 | E48: =Janvier!E48+Février!E48+Mars!E48+Avril!E48+Mai!E48+Juin!E48+Juillet!E48+Aout!E48+Septembre!E48+Octobre!E48+Novembre!E48+Décembre!E48 | F48: =Janvier!F48+Février!F48+Mars!F48+Avril!F48+Mai!F48+Juin!F48+Juillet!F48+Aout!F48+Septembre!F48+Octobre!F48+Novembre!F48+Décembre!F48 | G48: =Janvier!G48+Février!G48+Mars!G48+Avril!G48+Mai!G48+Juin!G48+Juillet!G48+Aout!G48+Septembre!G48+Octobre!G48+Novembre!G48+Décembre!G48 | H48: =Janvier!H48+Février!H48+Mars!H48+Avril!H48+Mai!H48+Juin!H48+Juillet!H48+Aout!H48+Septembre!H48+Octobre!H48+Novembre!H48+Décembre!H48 | I48: =Janvier!I48+Février!I48+Mars!I48+Avril!I48+Mai!I48+Juin!I48+Juillet!I48+Aout!I48+Septembre!I48+Octobre!I48+Novembre!I48+Décembre!I48 | J48: =Janvier!J48+Février!J48+Mars!J48+Avril!J48+Mai!J48+Juin!J48+Juillet!J48+Aout!J48+Septembre!J48+Octobre!J48+Novembre!J48+Décembre!J48 | L48: =SUM(E48:F48,I48:K48) | M48: =L48+D48 | N48: =M48/655.957 | O48: =A48 | P48: =B48 | Q48: =C48 | R48: =D48 | S48: =X48/12*$A$1 | T48: =Y48/12*$A$1 | U48: 290000 | V48: =$R48-U48 | W48: =R48/U48-1 | Z48: =Y48+X48 | AA48: =R48-Z48 | AB48: =R48/Z48-1 | AC48: =Z48/$Z$57 | AE48: =AF48-AD48 | AF48: =AC48*4901000000 | AG48: =R48-AF48 | AH48: =R48/AF48-1 | AJ48: =AK48-AI48 | AK48: 0 | AL48: =R48-AK48 | AM48: 0 | AN48: =AI48/12*$A$1 | AO48: =AJ48/12*$A$1 | AP48: =AO48+AN48 | AQ48: =R48-AP48 | AR48: 0 | AU48: =AT48+AS48 | AV48: =AU48-Z48 | AW48: =AU48/Z48-1 | AX48: =BC48/12*$A$1 | AY48: =BD48/12*$A$1 | AZ48: =AY48+AX48 | BA48: =$R48-AZ48 | BB48: =$R48/AZ48-1 | BE48: =BD48+BC48 | BF48: =$R48-BE48 | BG48: =$R48/BE48-1
A49: MURPHY OIL | B49: =Janvier!B49+Février!B49+Mars!B49+Avril!B49+Mai!B49+Juin!B49+Juillet!B49+Aout!B49+Septembre!B49+Octobre!B49+Novembre!B49+Décembre!B49 | C49: =Janvier!C49+Février!C49+Mars!C49+Avril!C49+Mai!C49+Juin!C49+Juillet!C49+Aout!C49+Septembre!C49+Octobre!C49+Novembre!C49+Décembre!C49 | D49: =Janvier!D49+Février!D49+Mars!D49+Avril!D49+Mai!D49+Juin!D49+Juillet!D49+Aout!D49+Septembre!D49+Octobre!D49+Novembre!D49+Décembre!D49 | E49: =Janvier!E49+Février!E49+Mars!E49+Avril!E49+Mai!E49+Juin!E49+Juillet!E49+Aout!E49+Septembre!E49+Octobre!E49+Novembre!E49+Décembre!E49 | F49: =Janvier!F49+Février!F49+Mars!F49+Avril!F49+Mai!F49+Juin!F49+Juillet!F49+Aout!F49+Septembre!F49+Octobre!F49+Novembre!F49+Décembre!F49 | G49: =Janvier!G49+Février!G49+Mars!G49+Avril!G49+Mai!G49+Juin!G49+Juillet!G49+Aout!G49+Septembre!G49+Octobre!G49+Novembre!G49+Décembre!G49 | H49: =Janvier!H49+Février!H49+Mars!H49+Avril!H49+Mai!H49+Juin!H49+Juillet!H49+Aout!H49+Septembre!H49+Octobre!H49+Novembre!H49+Décembre!H49 | I49: =Janvier!I49+Février!I49+Mars!I49+Avril!I49+Mai!I49+Juin!I49+Juillet!I49+Aout!I49+Septembre!I49+Octobre!I49+Novembre!I49+Décembre!I49 | J49: =Janvier!J49+Février!J49+Mars!J49+Avril!J49+Mai!J49+Juin!J49+Juillet!J49+Aout!J49+Septembre!J49+Octobre!J49+Novembre!J49+Décembre!J49 | L49: =SUM(E49:F49,I49:K49) | M49: =L49+D49 | N49: =M49/655.957 | O49: =A49 | P49: =B49 | Q49: =C49 | R49: =D49 | S49: =X49/12*$A$1 | T49: =Y49/12*$A$1 | U49: 0 | V49: =$R49-U49 | W49: =R49/U49-1 | Z49: =Y49+X49 | AA49: =R49-Z49 | AB49: =R49/Z49-1 | AC49: =Z49/$Z$57 | AD49: 121272000 | AE49: =AF49-AD49 | AF49: 175000000 | AG49: =R49-AF49 | AH49: =R49/AF49-1 | AI49: 121272000 | AJ49: =AK49-AI49 | AK49: 131272000 | AL49: =R49-AK49 | AM49: =R49/AK49-1 | AN49: =AI49/12*$A$1 | AO49: =AJ49/12*$A$1 | AP49: =AO49+AN49 | AQ49: =R49-AP49 | AR49: =R49/AP49-1 | AS49: 25000000 | AT49: 3000000 | AU49: =AT49+AS49 | AV49: =AU49-Z49 | AW49: =AU49/Z49-1 | AX49: =BC49/12*$A$1 | AY49: =BD49/12*$A$1 | AZ49: =AY49+AX49 | BA49: =$R49-AZ49 | BB49: =$R49/AZ49-1 | BC49: 12720000 | BD49: 8000000 | BE49: =BD49+BC49 | BF49: =$R49-BE49 | BG49: =$R49/BE49-1
A50: WELLTEC OILFIELD SERVICES | B50: =Janvier!B50+Février!B50+Mars!B50+Avril!B50+Mai!B50+Juin!B50+Juillet!B50+Aout!B50+Septembre!B50+Octobre!B50+Novembre!B50+Décembre!B50 | C50: =Janvier!C50+Février!C50+Mars!C50+Avril!C50+Mai!C50+Juin!C50+Juillet!C50+Aout!C50+Septembre!C50+Octobre!C50+Novembre!C50+Décembre!C50 | D50: =Janvier!D50+Février!D50+Mars!D50+Avril!D50+Mai!D50+Juin!D50+Juillet!D50+Aout!D50+Septembre!D50+Octobre!D50+Novembre!D50+Décembre!D50 | E50: =Janvier!E50+Février!E50+Mars!E50+Avril!E50+Mai!E50+Juin!E50+Juillet!E50+Aout!E50+Septembre!E50+Octobre!E50+Novembre!E50+Décembre!E50 | F50: =Janvier!F50+Février!F50+Mars!F50+Avril!F50+Mai!F50+Juin!F50+Juillet!F50+Aout!F50+Septembre!F50+Octobre!F50+Novembre!F50+Décembre!F50 | G50: =Janvier!G50+Février!G50+Mars!G50+Avril!G50+Mai!G50+Juin!G50+Juillet!G50+Aout!G50+Septembre!G50+Octobre!G50+Novembre!G50+Décembre!G50 | H50: =Janvier!H50+Février!H50+Mars!H50+Avril!H50+Mai!H50+Juin!H50+Juillet!H50+Aout!H50+Septembre!H50+Octobre!H50+Novembre!H50+Décembre!H50 | I50: =Janvier!I50+Février!I50+Mars!I50+Avril!I50+Mai!I50+Juin!I50+Juillet!I50+Aout!I50+Septembre!I50+Octobre!I50+Novembre!I50+Décembre!I50 | J50: =Janvier!J50+Février!J50+Mars!J50+Avril!J50+Mai!J50+Juin!J50+Juillet!J50+Aout!J50+Septembre!J50+Octobre!J50+Novembre!J50+Décembre!J50 | L50: =SUM(E50:F50,I50:K50) | M50: =L50+D50 | N50: =M50/655.957 | O50: =A50 | P50: =B50 | Q50: =C50 | R50: =D50 | S50: =X50/12*$A$1 | T50: =Y50/12*$A$1 | U50: 0 | V50: =$R50-U50 | W50: =R50/U50-1 | Z50: =Y50+X50 | AA50: =R50-Z50 | AB50: =R50/Z50-1 | AC50: =Z50/$Z$57 | AE50: =AF50-AD50 | AF50: 0 | AG50: =R50-AF50 | AH50: =R50/AF50-1 | AJ50: =AK50-AI50 | AK50: 0 | AL50: =R50-AK50 | AM50: 0 | AN50: =AI50/12*$A$1 | AO50: =AJ50/12*$A$1 | AP50: =AO50+AN50 | AQ50: =R50-AP50 | AR50: 0 | AU50: =AT50+AS50 | AV50: =AU50-Z50 | AW50: =AU50/Z50-1 | AX50: =BC50/12*$A$1 | AY50: =BD50/12*$A$1 | AZ50: =AY50+AX50 | BA50: =$R50-AZ50 | BB50: =$R50/AZ50-1 | BE50: =BD50+BC50 | BF50: =$R50-BE50 | BG50: =$R50/BE50-1
A51: CA TOTAL GENERE PAR ACTIVITE | B51: =SUM(B4:B50) | C51: =SUM(C4:C50) | D51: =SUM(D4:D50) | E51: =SUM(E4:E50) | F51: =SUM(F4:F50) | G51: =SUM(G4:G50) | H51: =SUM(H4:H50) | I51: =SUM(I4:I50) | J51: =SUM(J4:J50) | K51: =Janvier!K51+Février!K51+Mars!K51+Avril!K51+Mai!K51+Juin!K51+Juillet!K51+Aout!K51+Septembre!K51+Octobre!K51+Novembre!K51+Décembre!K51 | L51: =SUM(L4:L50)+K51 | M51: =SUM(M4:M50) | N51: =M51/655.957 | O51: ACTIVITE BASE | P51: =SUM(P4:P50) | Q51: =SUM(Q4:Q50) | R51: =SUM(R4:R50) | U51: =SUM(U4:U50) | V51: =$R51-U51 | W51: =R51/U51-1 | X51: =SUM(X4:X50) | Y51: =SUM(Y4:Y50) | Z51: =SUM(Z4:Z50) | AA51: =R51-Z51 | AB51: =R51/Z51-1 | AD51: =SUM(AD4:AD50) | AE51: =SUM(AE4:AE50) | AF51: =SUM(AF4:AF50) | AG51: =R51-AF51 | AH51: =R51/AF51-1 | AI51: =SUM(AI4:AI50) | AJ51: =SUM(AJ4:AJ50) | AK51: =SUM(AK4:AK50) | AL51: =R51-AK51 | AM51: =R51/AK51-1 | AN51: =SUM(AN4:AN50) | AO51: =SUM(AO4:AO50) | AP51: =AO51+AN51 | AQ51: =R51-AP51 | AR51: =R51/AP51-1 | AS51: =SUM(AS4:AS50) | AT51: =SUM(AT4:AT50) | AU51: =SUM(AU4:AU50) | AV51: =AU51-Z51 | AW51: =AU51/Z51-1 | AX51: =SUM(AX4:AX50) | AY51: =SUM(AY4:AY50) | AZ51: =SUM(AZ4:AZ50) | BA51: =$R51-AZ51 | BB51: =$R51/AZ51-1 | BC51: =SUM(BC4:BC50) | BD51: =SUM(BD4:BD50) | BE51: =SUM(BE4:BE50) | BF51: =$R51-BE51 | BG51: =$R51/BE51-1
A52: Rétrocession | D52: =E52+F52+I52+J52 | E52: =Janvier!E52+Février!E52+Mars!E52+Avril!E52+Mai!E52+Juin!E52+Juillet!E52+Aout!E52+Septembre!E52+Octobre!E52+Novembre!E52+Décembre!E52 | F52: =Janvier!F52+Février!F52+Mars!F52+Avril!F52+Mai!F52+Juin!F52+Juillet!F52+Aout!F52+Septembre!F52+Octobre!F52+Novembre!F52+Décembre!F52 | G52: =Janvier!G52+Février!G52+Mars!G52+Avril!G52+Mai!G52+Juin!G52+Juillet!G52+Aout!G52+Septembre!G52+Octobre!G50+Novembre!G50+Décembre!G50 | H52: =Janvier!H52+Février!H52+Mars!H52+Avril!H52+Mai!H52+Juin!H52+Juillet!H52+Aout!H52+Septembre!H52+Octobre!H50+Novembre!H50+Décembre!H50 | I52: =Janvier!I52+Février!I52+Mars!I52+Avril!I52+Mai!I52+Juin!I52+Juillet!I52+Aout!I52+Septembre!I52+Octobre!I52+Novembre!I52+Décembre!I52 | J52: =Janvier!J52+Février!J52+Mars!J52+Avril!J52+Mai!J52+Juin!J52+Juillet!J52+Aout!J52+Septembre!J52+Octobre!J52+Novembre!J52+Décembre!J52 | M52: =SUM(E52:K52) | O52: Rétrocessions | AV52: =AU52-Z52 | BF52: =$R52-BE52 | BG52: =$R52/BE52-1
A53: Taux Rétrocession | E53: =E52/E51 | F53: =F52/F51 | I53: =I52/I51 | J53: =J52/J51 | L53: =M52/L51 | M53: =M52/M51 | O53: IMAR | R53: =E52 | U53: 6667000 | V53: =$R53-U53 | W53: =R53/U53-1 | Z53: 80000000 | AA53: =R53-Z53 | AB53: =R53/Z53-1 | AC53: =Z53/$Z$57 | AF53: =100000000 | AG53: =R53-AF53 | AH53: =R53/AF53-1 | AK53: =100000000 | AL53: =U53-AK53 | AM53: =U53/AK53-1 | AP53: =AK53/12*$A$1 | AQ53: =Z53-AP53 | AR53: =Z53/AP53-1 | AU53: 50000000 | AV53: =AU53-Z53 | AW53: =AU53/Z53-1 | AZ53: =AU53/12*$A$1 | BA53: =$R53-AZ53 | BB53: =$R53/AZ53-1 | BE53: 80000000 | BF53: =$R53-BE53 | BG53: =$R53/BE53-1
A54: TOTAL Après rétrocession | D54: =D52+D51 | E54: =E51-E52 | F54: =F51-F52 | I54: =I51-I52 | J54: =J51-J52 | K54: =K52 | M54: =D54 | O54: HINT | R54: =F52 | U54: 800000 | V54: =$R54-U54 | W54: =R54/U54-1 | Z54: 10000000 | AA54: =R54-Z54 | AB54: =R54/Z54-1 | AC54: =Z54/$Z$57 | AF54: =9600000 | AG54: =R54-AF54 | AH54: =R54/AF54-1 | AK54: =9600000 | AL54: =U54-AK54 | AM54: =U54/AK54-1 | AP54: =AK54/12*$A$1 | AQ54: =Z54-AP54 | AR54: =Z54/AP54-1 | AU54: 5000000 | AV54: =AU54-Z54 | AW54: =AU54/Z54-1 | AZ54: =AU54/12*$A$1 | BA54: =$R54-AZ54 | BB54: =$R54/AZ54-1 | BE54: 8000000 | BF54: =$R54-BE54 | BG54: =$R54/BE54-1
O55: AER | R55: =I52 | U55: 4100000 | V55: =$R55-U55 | W55: =R55/U55-1 | Z55: 35000000 | AA55: =R55-Z55 | AB55: =R55/Z55-1 | AC55: =Z55/$Z$57 | AF55: =108000000 | AG55: =R55-AF55 | AH55: =R55/AF55-1 | AK55: 130000000 | AL55: =U55-AK55 | AM55: =U55/AK55-1 | AP55: =AK55/12*$A$1 | AQ55: =Z55-AP55 | AR55: =Z55/AP55-1 | AU55: 100000000 | AV55: =AU55-Z55 | AW55: =AU55/Z55-1 | AZ55: =AU55/12*$A$1 | BA55: =$R55-AZ55 | BB55: =$R55/AZ55-1 | BE55: 80000000 | BF55: =$R55-BE55 | BG55: =$R55/BE55-1
O56: EMAR | R56: =J52 | U56: 2500000 | V56: =$R56-U56 | W56: =R56/U56-1 | Z56: 50000000 | AA56: =R56-Z56 | AB56: =R56/Z56-1 | AC56: =Z56/$Z$57 | AF56: =60000000 | AG56: =R56-AF56 | AH56: =R56/AF56-1 | AK56: =60000000 | AL56: =U56-AK56 | AM56: =U56/AK56-1 | AP56: =AK56/12*$A$1 | AQ56: =Z56-AP56 | AR56: =Z56/AP56-1 | AU56: 16000000 | AV56: =AU56-Z56 | AW56: =AU56/Z56-1 | AZ56: =AU56/12*$A$1 | BA56: =$R56-AZ56 | BB56: =$R56/AZ56-1 | BE56: 30000000 | BF56: =$R56-BE56 | BG56: =$R56/BE56-1
O57: ACTIVITE O&G | R57: =R51+R53+R54+R55+R56 | U57: =U51+U53+U54+U55+U56 | V57: =V51+V53+V54+V55+V56 | W57: =R57/U57-1 | Z57: =Z51+Z53+Z54+Z55+Z56 | AA57: =AA51+AA53+AA54+AA55+AA56 | AB57: =R57/Z57-1 | AF57: =AF51+AF53+AF54+AF55+AF56 | AG57: =AG51+AG53+AG54+AG55+AG56 | AH57: =R57/AF57-1 | AK57: =AK51+AK53+AK54+AK55+AK56 | AL57: =AL51+AL53+AL54+AL55+AL56 | AM57: =R57/AK57-1 | AP57: =AP51+AP53+AP54+AP55+AP56 | AQ57: =AQ51+AQ53+AQ54+AQ55+AQ56 | AR57: =R57/AP57-1 | AU57: =AU51+AU53+AU54+AU55+AU56 | AV57: =AU57-Z57 | AW57: =AU57/Z57-1 | AZ57: =AZ51+AZ53+AZ54+AZ55+AZ56 | BA57: =$R57-AZ57 | BB57: =$R57/AZ57-1 | BE57: =BE51+BE53+BE54+BE55+BE56 | BF57: =$R57-BE57 | BG57: =$R57/BE57-1
O58: R20 | AF58: Variation Réel 15 / B15 | AK58: Variation Réel 15 / B15 | AP58: Variation Réel 15 / B15 | AU58: Variation Réel 15 / B15
Z59: =Z57/12 | AB59: =1+AB57
AK63: ,

Sheet Janvier
B1: CAP Janvier | P1: VARIATION R 26 sur B26 & R25
B2: BASE | E2: CA GENERE | P2: R25 | R2: Variation Réel 26 / B26 | U2: Variation Réel 26 / Réel 25 | X2: Commentaires
B3: LOYER | C3: Plog & Divers | D3: Total BASE | E3: IMAR | F3: HINT | G3: IAER | H3: EAER | I3: AERIEN | J3: EXPORT | K3: SIRT | L3: Afritramp | M3: Meet & Greet | N3: CA GENERE Autres département | O3: CA TOTAL GENERE PAR CLIENT | P3: Sources revenus | Q3: REEL BASE 2026 | R3: Budget 2026 | S3: VAR (FCFA) | T3: Var (%) | U3: Réel BASE 2025 | V3: VAR (FCFA) | W3: Var (%)
A4: ='Cumul annuel'!A4 | C4: =D4-B4 | D4: 5402000 | I4: =G4+H4 | N4: =E4+F4+I4+J4+K4+L4+M4 | O4: =N4+D4 | P4: ='Cumul annuel'!A4 | Q4: =D4 | R4: 5000000 | S4: =Q4-R4 | T4: =Q4/R4-1 | U4: 0 | V4: =Q4-U4 | W4: =(Q4/U4-1) | Z4: Afritramp C/O SAGA | AA4: project | AB4: Gest. Base Logistique | AC4: ABJ | AD4: 40B00 | AH4: =SUM(AE4:AG4)
A5: ='Cumul annuel'!A5 | C5: =D5-B5 | I5: =G5+H5 | N5: =E5+F5+I5+J5+K5+L5+M5 | O5: =N5+D5 | P5: ='Cumul annuel'!A5 | Q5: =D5 | R5: 6666666.7 | S5: =Q5-R5 | T5: =Q5/R5-1 | U5: 17397770 | V5: =Q5-U5 | W5: =(Q5/U5-1) | Z5: Anadarko | AA5: project | AB5: Gest. Base Logistique | AC5: ABJ | AD5: 40B00 | AH5: =SUM(AE5:AG5)
A6: ='Cumul annuel'!A6 | C6: =D6-B6 | I6: =G6+H6 | N6: =E6+F6+I6+J6+K6+L6+M6 | O6: =N6+D6 | P6: ='Cumul annuel'!A6 | Q6: =D6 | R6: 10750000 | S6: =Q6-R6 | T6: =Q6/R6-1 | U6: 0 | V6: =Q6-U6 | W6: =(Q6/U6-1) | Z6: Baker Hugues | AA6: project | AB6: Gest. Base Logistique | AC6: ABJ | AD6: 40B00 | AF6: 25000 | AH6: =SUM(AE6:AG6)
A7: ='Cumul annuel'!A7 | B7: 121125000 | C7: =D7-B7 | D7: 136700312 | I7: =G7+H7 | N7: =E7+F7+I7+J7+K7+L7+M7 | O7: =N7+D7 | P7: ='Cumul annuel'!A7 | Q7: =D7 | R7: 50000000 | S7: =Q7-R7 | T7: =Q7/R7-1 | U7: 152560147 | V7: =Q7-U7 | W7: =(Q7/U7-1) | Z7: CIAM | AA7: project | AB7: Gest. Base Logistique | AC7: ABJ | AD7: 40B00 | AH7: =SUM(AE7:AG7)
A8: ='Cumul annuel'!A8 | C8: =D8-B8 | D8: 2803680 | G8: 10296182 | H8: 512298 | I8: =G8+H8 | N8: =E8+F8+I8+J8+K8+L8+M8 | O8: =N8+D8 | P8: ='Cumul annuel'!A8 | Q8: =D8 | R8: 2800000 | S8: =Q8-R8 | T8: =Q8/R8-1 | U8: 0 | V8: =Q8-U8 | W8: =(Q8/U8-1) | Z8: CNR | AA8: project | AB8: Gest. Base Logistique | AC8: ABJ | AD8: 40B00 | AF8: 90000 | AH8: =SUM(AE8:AG8)
A9: ='Cumul annuel'!A9 | C9: =D9-B9 | D9: 1363000 | I9: =G9+H9 | N9: =E9+F9+I9+J9+K9+L9+M9 | O9: =N9+D9 | P9: ='Cumul annuel'!A9 | Q9: =D9 | R9: 833333.33 | S9: =Q9-R9 | T9: =Q9/R9-1 | U9: 0 | V9: =Q9-U9 | W9: =(Q9/U9-1) | Z9: DIVERS/Various customer | AA9: project | AB9: Gest. Base Logistique | AC9: ABJ | AD9: 40B00 | AE9: 33840 | AF9: 179596 | AH9: =SUM(AE9:AG9)
A10: ='Cumul annuel'!A10 | C10: =D10-B10 | I10: =G10+H10 | N10: =E10+F10+I10+J10+K10+L10+M10 | O10: =N10+D10 | P10: ='Cumul annuel'!A10 | Q10: =D10 | R10: 4600000 | S10: =Q10-R10 | T10: =Q10/R10-1 | U10: 0 | V10: =Q10-U10 | W10: =(Q10/U10-1) | Z10: EXPRO GROUP NORTH SEA / S-Traitant | AA10: project | AB10: Gest. Base Logistique | AC10: ABJ | AD10: 40B00 | AF10: 5000 | AH10: =SUM(AE10:AG10)
A11: ='Cumul annuel'!A11 | C11: =D11-B11 | G11: 11198009 | I11: =G11+H11 | K11: 21000000 | L11: 2368000 | N11: =E11+F11+I11+J11+K11+L11+M11 | O11: =N11+D11 | P11: ='Cumul annuel'!A11 | Q11: =D11 | R11: 5833333.3 | S11: =Q11-R11 | T11: =Q11/R11-1 | U11: 0 | V11: =Q11-U11 | W11: =(Q11/U11-1) | Z11: FOXTROT | AA11: project | AB11: Gest. Base Logistique | AC11: ABJ | AD11: 40B00 | AF11: 600000 | AH11: =SUM(AE11:AG11)
A12: DIVERS CLIENTS | C12: =D12-B12 | H12: 432890 | I12: =G12+H12 | L12: 902006 | N12: =E12+F12+I12+J12+K12+L12+M12 | O12: =N12+D12 | P12: ='Cumul annuel'!A12 | Q12: =D12 | R12: 25341612 | S12: =Q12-R12 | T12: =Q12/R12-1 | U12: 1050000 | V12: =Q12-U12 | W12: =(Q12/U12-1) | Z12: GLOBAL ENERGY | AA12: project | AB12: Gest. Base Logistique | AC12: ABJ | AD12: 40B00 | AE12: 24672 | AF12: 5328 | AH12: =SUM(AE12:AG12)
A13: CNR - ICM CONTRAT BATEAU SURFER | C13: =D13-B13 | I13: =G13+H13 | N13: =E13+F13+I13+J13+K13+L13+M13 | O13: =N13+D13 | P13: ='Cumul annuel'!A13 | Q13: =D13 | R13: 55100388 | S13: =Q13-R13 | T13: =Q13/R13-1 | U13: 0 | V13: =Q13-U13 | W13: =(Q13/U13-1) | Z13: HALLIBURTON | AA13: project | AB13: Gest. Base Logistique | AC13: ABJ | AD13: 40B00 | AF13: 20000 | AH13: =SUM(AE13:AG13)
A14: ='Cumul annuel'!A14 | C14: =D14-B14 | I14: =G14+H14 | N14: =E14+F14+I14+J14+K14+L14+M14 | O14: =N14+D14 | P14: ='Cumul annuel'!A14 | Q14: =D14 | R14: 0 | S14: =Q14-R14 | T14: =Q14/R14-1 | U14: 0 | V14: =Q14-U14 | W14: =(Q14/U14-1) | Z14: MI | AA14: project | AB14: Gest. Base Logistique | AC14: ABJ | AD14: 40B00 | AH14: =SUM(AE14:AG14)
A15: ='Cumul annuel'!A15 | B15: 13750000 | C15: =D15-B15 | D15: 22461100 | I15: =G15+H15 | M15: 35576 | N15: =E15+F15+I15+J15+K15+L15+M15 | O15: =N15+D15 | P15: ='Cumul annuel'!A15 | Q15: =D15 | R15: 20833333 | S15: =Q15-R15 | T15: =Q15/R15-1 | U15: 4270000 | V15: =Q15-U15 | W15: =(Q15/U15-1) | Z15: NOPCI - MODEC | AA15: project | AB15: Gest. Base Logistique | AC15: ABJ | AD15: 40B00 | AF15: 30000 | AH15: =SUM(AE15:AG15)
A16: ='Cumul annuel'!A16 | C16: =D16-B16 | I16: =G16+H16 | N16: =E16+F16+I16+J16+K16+L16+M16 | O16: =N16+D16 | P16: ='Cumul annuel'!A16 | Q16: =D16 | R16: 833333.33 | S16: =Q16-R16 | T16: =Q16/R16-1 | U16: 1200000 | V16: =Q16-U16 | W16: =(Q16/U16-1) | Z16: Prosafe | AA16: project | AB16: Gest. Base Logistique | AC16: ABJ | AD16: 40B00 | AF16: 50000 | AH16: =SUM(AE16:AG16)
A17: ='Cumul annuel'!A17 | B17: 54314000 | C17: =D17-B17 | D17: 85206984 | I17: =G17+H17 | L17: 219758 | N17: =E17+F17+I17+J17+K17+L17+M17 | O17: =N17+D17 | P17: ='Cumul annuel'!A17 | Q17: =D17 | R17: 175000000 | S17: =Q17-R17 | T17: =Q17/R17-1 | U17: 58927025 | V17: =Q17-U17 | W17: =(Q17/U17-1) | Z17: SDV Logistic Singapore (Prosafe) | AA17: project | AB17: Gest. Base Logistique | AC17: ABJ | AD17: 40B00 | AH17: =SUM(AE17:AG17)
A18: ='Cumul annuel'!A18 | C18: =D18-B18 | D18: 7082824 | I18: =G18+H18 | N18: =E18+F18+I18+J18+K18+L18+M18 | O18: =N18+D18 | P18: ='Cumul annuel'!A18 | Q18: =D18 | R18: 7000000 | S18: =Q18-R18 | T18: =Q18/R18-1 | U18: 0 | V18: =Q18-U18 | W18: =(Q18/U18-1) | Z18: SCHLUMBERGER | AA18: project | AB18: Gest. Base Logistique | AC18: ABJ | AD18: 40B00 | AF18: 100000 | AH18: =SUM(AE18:AG18)
A19: ='Cumul annuel'!A19 | B19: 2966000 | C19: =D19-B19 | D19: 4447279 | I19: =G19+H19 | N19: =E19+F19+I19+J19+K19+L19+M19 | O19: =N19+D19 | P19: ='Cumul annuel'!A19 | Q19: =D19 | R19: 5000000 | S19: =Q19-R19 | T19: =Q19/R19-1 | U19: 5749730 | V19: =Q19-U19 | W19: =(Q19/U19-1) | Z19: SIR P/C Subtec | AA19: project | AB19: Gest. Base Logistique | AC19: ABJ | AD19: 40B00 | AH19: =SUM(AE19:AG19)
A20: ='Cumul annuel'!A20 | C20: =D20-B20 | D20: 3184000 | I20: =G20+H20 | N20: =E20+F20+I20+J20+K20+L20+M20 | O20: =N20+D20 | P20: ='Cumul annuel'!A20 | Q20: =D20 | R20: 3180000 | S20: =Q20-R20 | T20: =Q20/R20-1 | U20: 0 | V20: =Q20-U20 | W20: =(Q20/U20-1) | Z20: SUBTEC | AA20: project | AB20: Gest. Base Logistique | AC20: ABJ | AD20: 40B00 | AE20: 9159 | AF20: 2841 | AH20: =SUM(AE20:AG20)
A21: ='Cumul annuel'!A21 | B21: 41300000 | C21: =D21-B21 | D21: 46617365 | E21: 2801201 | G21: 16006847 | H21: 467758 | I21: =G21+H21 | J21: 403263 | N21: =E21+F21+I21+J21+K21+L21+M21 | O21: =N21+D21 | P21: ='Cumul annuel'!A21 | Q21: =D21 | R21: 20833333 | S21: =Q21-R21 | T21: =Q21/R21-1 | U21: 26628131 | V21: =Q21-U21 | W21: =(Q21/U21-1) | Z21: Tetra | AA21: project | AB21: Gest. Base Logistique | AC21: ABJ | AD21: 40B00 | AH21: =SUM(AE21:AG21)
A22: ='Cumul annuel'!A22 | B22: 1470000 | C22: =D22-B22 | D22: 6800202 | I22: =G22+H22 | N22: =E22+F22+I22+J22+K22+L22+M22 | O22: =N22+D22 | P22: ='Cumul annuel'!A22 | Q22: =D22 | R22: 13333333 | S22: =Q22-R22 | T22: =Q22/R22-1 | U22: 5674214 | V22: =Q22-U22 | W22: =(Q22/U22-1) | Z22: TOTAL E&P COTE D'IVOIRE | AA22: project | AB22: Gest. Base Logistique | AC22: ABJ | AD22: 40B00 | AF22: 150000 | AH22: =SUM(AE22:AG22)
A23: ='Cumul annuel'!A23 | C23: =D23-B23 | D23: 450000 | I23: =G23+H23 | N23: =E23+F23+I23+J23+K23+L23+M23 | O23: =N23+D23 | P23: ='Cumul annuel'!A23 | Q23: =D23 | R23: 450000 | S23: =Q23-R23 | T23: =Q23/R23-1 | U23: 0 | V23: =Q23-U23 | W23: =(Q23/U23-1) | Z23: WEATHERFORD | AA23: project | AB23: Gest. Base Logistique | AC23: ABJ | AD23: 40B00 | AH23: =SUM(AE23:AG23)
A24: ='Cumul annuel'!A24 | C24: =D24-B24 | G24: 717489 | I24: =G24+H24 | N24: =E24+F24+I24+J24+K24+L24+M24 | O24: =N24+D24 | P24: ='Cumul annuel'!A24 | Q24: =D24 | R24: 0 | S24: =Q24-R24 | T24: =Q24/R24-1 | U24: 74975 | V24: =Q24-U24 | W24: =(Q24/U24-1) | Z24: IMAR | AA24: project | AB24: Gest. Base Logistique | AC24: ABJ | AD24: 40B00 | AG24: 50000 | AH24: =SUM(AE24:AG24)
A25: ='Cumul annuel'!A25 | C25: =D25-B25 | D25: 480000 | I25: =G25+H25 | N25: =E25+F25+I25+J25+K25+L25+M25 | O25: =N25+D25 | P25: ='Cumul annuel'!A25 | Q25: =D25 | R25: 480000 | S25: =Q25-R25 | T25: =Q25/R25-1 | U25: 0 | V25: =Q25-U25 | W25: =(Q25/U25-1) | Z25: EMAR | AA25: project | AB25: Gest. Base Logistique | AC25: ABJ | AD25: 40B00 | AG25: 40000 | AH25: =SUM(AE25:AG25)
A26: ='Cumul annuel'!A26 | C26: =D26-B26 | I26: =G26+H26 | N26: =E26+F26+I26+J26+K26+L26+M26 | O26: =N26+D26 | P26: ='Cumul annuel'!A26 | Q26: =D26 | R26: 833333.33 | S26: =Q26-R26 | T26: =Q26/R26-1 | U26: -3635400 | V26: =Q26-U26 | W26: =(Q26/U26-1) | Z26: IAER/EAER | AA26: project | AB26: Gest. Base Logistique | AC26: ABJ | AD26: 40B00 | AG26: 50000 | AH26: =SUM(AE26:AG26)
A27: ='Cumul annuel'!A27 | C27: =D27-B27 | I27: =G27+H27 | N27: =E27+F27+I27+J27+K27+L27+M27 | O27: =N27+D27 | P27: ='Cumul annuel'!A27 | Q27: =D27 | R27: 4166666.7 | S27: =Q27-R27 | T27: =Q27/R27-1 | U27: 0 | V27: =Q27-U27 | W27: =(Q27/U27-1) | Z27: HINTERLAND | AA27: project | AB27: Gest. Base Logistique | AC27: ABJ | AD27: 40B00 | AG27: 15000 | AH27: =SUM(AE27:AG27)
A28: ='Cumul annuel'!A28 | B28: 1450000 | C28: =D28-B28 | D28: 3602000 | I28: =G28+H28 | N28: =E28+F28+I28+J28+K28+L28+M28 | O28: =N28+D28 | P28: ='Cumul annuel'!A28 | Q28: =D28 | R28: 5000000 | S28: =Q28-R28 | T28: =Q28/R28-1 | U28: 1714500 | V28: =Q28-U28 | W28: =(Q28/U28-1) | Z28: Sapura Kencana Drilling | AA28: project | AB28: Gest. Base Logistique | AC28: ABJ | AD28: 40B00 | AH28: =SUM(AE28:AG28)
A29: ='Cumul annuel'!A29 | C29: =D29-B29 | I29: =G29+H29 | N29: =E29+F29+I29+J29+K29+L29+M29 | O29: =N29+D29 | P29: ='Cumul annuel'!A29 | Q29: =D29 | R29: 37500000 | S29: =Q29-R29 | T29: =Q29/R29-1 | U29: 233319061 | V29: =Q29-U29 | W29: =(Q29/U29-1) | Z29: Divers projets | AF29: 120000 | AH29: =SUM(AE29:AG29)
A30: ='Cumul annuel'!A30 | C30: =D30-B30 | I30: =G30+H30 | N30: =E30+F30+I30+J30+K30+L30+M30 | O30: =N30+D30 | P30: ='Cumul annuel'!A30 | Q30: =D30 | R30: 0 | S30: =Q30-R30 | T30: =Q30/R30-1 | U30: 0 | V30: =Q30-U30 | W30: =(Q30/U30-1)
A31: ='Cumul annuel'!A31 | C31: =D31-B31 | I31: =G31+H31 | N31: =E31+F31+I31+J31+K31+L31+M31 | O31: =N31+D31 | P31: ='Cumul annuel'!A31 | Q31: =D31 | R31: 0 | S31: =Q31-R31 | T31: =Q31/R31-1 | U31: 0 | V31: =Q31-U31 | W31: =(Q31/U31-1)
A32: ='Cumul annuel'!A32 | C32: =D32-B32 | I32: =G32+H32 | N32: =E32+F32+I32+J32+K32+L32+M32 | O32: =N32+D32 | P32: ='Cumul annuel'!A32 | Q32: =D32 | R32: 0 | S32: =Q32-R32 | T32: =Q32/R32-1 | U32: 0 | V32: =Q32-U32 | W32: =(Q32/U32-1)
A33: ='Cumul annuel'!A33 | C33: =D33-B33 | I33: =G33+H33 | N33: =E33+F33+I33+J33+K33+L33+M33 | O33: =N33+D33 | P33: ='Cumul annuel'!A33 | Q33: =D33 | R33: 0 | S33: =Q33-R33 | T33: =Q33/R33-1 | U33: 0 | V33: =Q33-U33 | W33: =(Q33/U33-1)
A34: ='Cumul annuel'!A34 | C34: =D34-B34 | I34: =G34+H34 | N34: =E34+F34+I34+J34+K34+L34+M34 | O34: =N34+D34 | P34: ='Cumul annuel'!A34 | Q34: =D34 | R34: 0 | S34: =Q34-R34 | T34: =Q34/R34-1 | U34: 0 | V34: =Q34-U34 | W34: =(Q34/U34-1)
A35: ='Cumul annuel'!A35 | C35: =D35-B35 | G35: 240415 | H35: 605227 | I35: =G35+H35 | N35: =E35+F35+I35+J35+K35+L35+M35 | O35: =N35+D35 | P35: ='Cumul annuel'!A35 | Q35: =D35 | R35: 66666.667 | S35: =Q35-R35 | T35: =Q35/R35-1 | U35: 0 | V35: =Q35-U35 | W35: =(Q35/U35-1)
A36: ='Cumul annuel'!A36 | C36: =D36-B36 | G36: 134144 | I36: =G36+H36 | N36: =E36+F36+I36+J36+K36+L36+M36 | O36: =N36+D36 | P36: ='Cumul annuel'!A36 | Q36: =D36 | R36: 0 | S36: =Q36-R36 | T36: =Q36/R36-1 | U36: 6792435 | V36: =Q36-U36 | W36: =(Q36/U36-1)
A37: ='Cumul annuel'!A37 | C37: =D37-B37 | I37: =G37+H37 | J37: 403263 | N37: =E37+F37+I37+J37+K37+L37+M37 | O37: =N37+D37 | P37: ='Cumul annuel'!A37 | Q37: =D37 | R37: 833333.33 | S37: =Q37-R37 | T37: =Q37/R37-1 | U37: 0 | V37: =Q37-U37 | W37: =(Q37/U37-1)
A38: ='Cumul annuel'!A38 | B38: 20000000 | C38: =D38-B38 | D38: 60126620 | I38: =G38+H38 | K38: 4400000 | N38: =E38+F38+I38+J38+K38+L38+M38 | O38: =N38+D38 | P38: ='Cumul annuel'!A38 | Q38: =D38 | R38: 55833333 | S38: =Q38-R38 | T38: =Q38/R38-1 | U38: 35357900 | V38: =Q38-U38 | W38: =(Q38/U38-1)
A39: ='Cumul annuel'!A39 | C39: =D39-B39 | D39: 1000000 | I39: =G39+H39 | N39: =E39+F39+I39+J39+K39+L39+M39 | O39: =N39+D39 | P39: ='Cumul annuel'!A39 | Q39: =D39 | R39: 200000 | S39: =Q39-R39 | T39: =Q39/R39-1 | U39: 0 | V39: =Q39-U39 | W39: =(Q39/U39-1)
A40: DOF SUBSEA | C40: =D40-B40 | I40: =G40+H40 | N40: =E40+F40+I40+J40+K40+L40+M40 | O40: =N40+D40 | P40: ='Cumul annuel'!A40 | Q40: =D40 | R40: 0 | S40: =Q40-R40 | T40: =Q40/R40-1 | U40: 361080 | V40: =Q40-U40 | W40: =(Q40/U40-1)
A41: ='Cumul annuel'!A41 | C41: =D41-B41 | I41: =G41+H41 | N41: =E41+F41+I41+J41+K41+L41+M41 | O41: =N41+D41 | P41: ='Cumul annuel'!A41 | Q41: =D41 | R41: 0 | S41: =Q41-R41 | T41: =Q41/R41-1 | U41: 0 | V41: =Q41-U41 | W41: =(Q41/U41-1)
A42: ='Cumul annuel'!A42 | B42: 763750 | C42: =D42-B42 | D42: 1527500 | I42: =G42+H42 | N42: =E42+F42+I42+J42+K42+L42+M42 | O42: =N42+D42 | P42: ='Cumul annuel'!A42 | Q42: =D42 | R42: 1000000 | S42: =Q42-R42 | T42: =Q42/R42-1 | U42: 763750 | V42: =Q42-U42 | W42: =(Q42/U42-1)
A43: ='Cumul annuel'!A43 | C43: =D43-B43 | I43: =G43+H43 | N43: =E43+F43+I43+J43+K43+L43+M43 | O43: =N43+D43 | P43: ='Cumul annuel'!A43 | Q43: =D43 | R43: 0 | S43: =Q43-R43 | T43: =Q43/R43-1 | U43: 0 | V43: =Q43-U43 | W43: =(Q43/U43-1)
A44: ='Cumul annuel'!A44 | C44: =D44-B44 | G44: 955726 | I44: =G44+H44 | N44: =E44+F44+I44+J44+K44+L44+M44 | O44: =N44+D44 | P44: ='Cumul annuel'!A44 | Q44: =D44 | R44: 0 | S44: =Q44-R44 | T44: =Q44/R44-1 | U44: 0 | V44: =Q44-U44 | W44: =(Q44/U44-1)
A45: ='Cumul annuel'!A45 | B45: 22467500 | C45: =D45-B45 | D45: 56452638 | I45: =G45+H45 | N45: =E45+F45+I45+J45+K45+L45+M45 | O45: =N45+D45 | P45: ='Cumul annuel'!A45 | Q45: =D45 | R45: 25000000 | S45: =Q45-R45 | T45: =Q45/R45-1 | U45: 55186128 | V45: =Q45-U45 | W45: =(Q45/U45-1)
A46: ='Cumul annuel'!A46 | C46: =D46-B46 | I46: =G46+H46 | N46: =E46+F46+I46+J46+K46+L46+M46 | O46: =N46+D46 | P46: ='Cumul annuel'!A46 | Q46: =D46 | R46: 0 | S46: =Q46-R46 | T46: =Q46/R46-1 | U46: 0 | V46: =Q46-U46 | W46: =(Q46/U46-1)
A47: ='Cumul annuel'!A47 | C47: =D47-B47 | D47: 18000000 | I47: =G47+H47 | N47: =E47+F47+I47+J47+K47+L47+M47 | O47: =N47+D47 | P47: ='Cumul annuel'!A47 | Q47: =D47 | R47: 17916667 | S47: =Q47-R47 | T47: =Q47/R47-1 | U47: 18000000 | V47: =Q47-U47 | W47: =(Q47/U47-1)
A48: ='Cumul annuel'!A48 | C48: =D48-B48 | I48: =G48+H48 | N48: =E48+F48+I48+J48+K48+L48+M48 | O48: =N48+D48 | P48: ='Cumul annuel'!A48 | Q48: =D48 | R48: 400000 | S48: =Q48-R48 | T48: =Q48/R48-1 | U48: 1355000 | V48: =Q48-U48 | W48: =(Q48/U48-1)
A49: ='Cumul annuel'!A49 | C49: =D49-B49 | D49: 373904825 | I49: =G49+H49 | K49: 82000000 | L49: 6385000 | N49: =E49+F49+I49+J49+K49+L49+M49 | O49: =N49+D49 | P49: ='Cumul annuel'!A49 | Q49: =D49 | R49: 1.9133333e+08 | S49: =Q49-R49 | T49: =Q49/R49-1 | U49: 0 | V49: =Q49-U49 | W49: =(Q49/U49-1)
A50: ='Cumul annuel'!A50 | C50: =D50-B50 | I50: =G50+H50 | N50: =E50+F50+I50+J50+K50+L50+M50 | O50: =N50+D50 | P50: ='Cumul annuel'!A50 | Q50: =D50 | R50: 0 | S50: =Q50-R50 | T50: =Q50/R50-1 | U50: 0 | V50: =Q50-U50 | W50: =(Q50/U50-1)
A51: CA TOTAL | B51: =SUM(B4:B50) | C51: =SUM(C4:C50) | D51: =SUM(D4:D50) | E51: =SUM(E4:E50) | F51: =SUM(F5:F50) | G51: =SUM(G5:G50) | H51: =SUM(H5:H50) | I51: =SUM(I5:I50) | J51: =SUM(J5:J50) | K51: =SUM(K5:K50) | L51: =SUM(L5:L50) | M51: =SUM(M5:M50) | N51: =J51+I51+F51+E51+K51+L51+M51 | O51: =N51+D51 | P51: ACTIVITE BASE | Q51: =SUM(Q4:Q50) | R51: =SUM(R4:R50) | S51: =Q51-R51 | T51: =Q51/R51-1 | U51: =SUM(U4:U50) | V51: =Q51-U51 | W51: =(Q51/U51-1)
A52: Rétrocession | N52: =J52+I52+F52+E52 | O52: =N52+D52 | P52: Rétrocessions | R52: =SUM(R53:R56)
A53: Taux Rétrocession | E53: =E52/E51 | F53: =F52/F51 | I53: =I52/I51 | J53: =J52/J51 | N53: =N52/N51 | P53: IMAR | Q53: =E52 | S53: =Q53-R53 | T53: =Q53/R53-1 | U53: 0 | V53: =Q53-U53 | W53: =(Q53/U53-1)
A54: TOTAL Après rétrocession | D54: =D52+D51 | E54: =E51-E52 | F54: =F51-F52 | I54: =I51-I52 | J54: =J51-J52 | K54: =K51 | L54: =L51 | M54: =M51 | N54: =SUM(D54:M54) | P54: HINT | Q54: =F52 | S54: =Q54-R54 | T54: =Q54/R54-1 | U54: 2773579 | V54: =Q54-U54 | W54: =(Q54/U54-1)
P55: AER | Q55: =I52 | S55: =Q55-R55 | T55: =Q55/R55-1 | U55: 3081072 | V55: =Q55-U55 | W55: =(Q55/U55-1)
P56: EMAR | T56: =Q56/R56-1 | U56: 188650 | V56: =Q56-U56 | W56: =(Q56/U56-1)
P57: ACTIVITE O&G | Q57: =Q51+Q53+Q54+Q55+Q56 | R57: =R51+R52 | S57: =S51+S53+S54+S55+S56 | T57: =Q57/R57-1 | U57: =U51+U53+U54+U55+U56 | V57: =V51+V53+V54+V55+V56 | W57: =(Q57/U57-1)
A58: Loyer | B58: =B51 | C58: =B58/$B$61 | P58: R23 | R58: Variation Réel 26 / B26 | U58: Variation Réel 26 / Réel 25
A59: LOGP | B59: =C51 | C59: =B59/$B$61 | R59: 753952000
A60: Rétrocessions | B60: =D52 | C60: =B60/$B$61
A61: Total CAP | B61: =D54 | C61: =B61/$B$61
R62: =R59-R57

Sheet Février
B1: CAP Février | P1: VARIATION R 26 sur B26 & R25
B2: BASE | E2: CA GENERE | P2: R26 | R2: Variation Réel 26 / B26 | U2: Variation Réel 26 / Réel 25 | X2: Commentaires
B3: LOYER | C3: Plog & Divers | D3: Total BASE | E3: IMAR | F3: HINT | G3: IAER | H3: EAER | I3: AERIEN | J3: EXPORT | K3: SIRT | L3: Afritramp | M3: Meet & Greet | N3: CA GENERE Autres Départements | O3: CA TOTAL GENERE PAR CLIENT | P3: Sources revenus | Q3: REEL BASE 2026 | R3: Budget 2026 | S3: VAR (FCFA) | T3: Var (%) | U3: Réel BASE 2025 | V3: VAR (FCFA) | W3: Var (%)
A4: ='Cumul annuel'!A4 | C4: =D4-B4 | D4: 7272500 | I4: =G4+H4 | N4: =J4+I4+F4+E4+L4+M4+K4 | O4: =N4+D4 | P4: ='Cumul annuel'!A4 | Q4: =D4 | R4: 0 | S4: =Q4-R4 | T4: =Q4/R4-1 | U4: 0 | V4: =Q4-U4 | W4: =(Q4/U4-1)
A5: ='Cumul annuel'!A5 | C5: =D5-B5 | D5: 3419052 | I5: =G5+H5 | N5: =J5+I5+F5+E5+L5+M5+K5 | O5: =N5+D5 | P5: ='Cumul annuel'!A5 | Q5: =D5 | R5: 6666666.7 | S5: =Q5-R5 | T5: =Q5/R5-1 | U5: 1185308 | V5: =Q5-U5 | W5: =(Q5/U5-1)
A6: ='Cumul annuel'!A6 | C6: =D6-B6 | I6: =G6+H6 | N6: =J6+I6+F6+E6+L6+M6+K6 | O6: =N6+D6 | P6: ='Cumul annuel'!A6 | Q6: =D6 | R6: 10750000 | S6: =Q6-R6 | T6: =Q6/R6-1 | U6: 61497 | V6: =Q6-U6 | W6: =(Q6/U6-1)
A7: ='Cumul annuel'!A7 | C7: =D7-B7 | D7: 548844 | G7: 13285 | I7: =G7+H7 | N7: =J7+I7+F7+E7+L7+M7+K7 | O7: =N7+D7 | P7: ='Cumul annuel'!A7 | Q7: =D7 | R7: 50000000 | S7: =Q7-R7 | T7: =Q7/R7-1 | U7: 6288973 | V7: =Q7-U7 | W7: =(Q7/U7-1)
A8: ='Cumul annuel'!A8 | C8: =D8-B8 | E8: 1108440 | G8: 2208067 | I8: =G8+H8 | N8: =J8+I8+F8+E8+L8+M8+K8 | O8: =N8+D8 | P8: ='Cumul annuel'!A8 | Q8: =D8 | R8: 0 | S8: =Q8-R8 | T8: =Q8/R8-1 | U8: 227325702 | V8: =Q8-U8 | W8: =(Q8/U8-1)
A9: ='Cumul annuel'!A9 | C9: =D9-B9 | D9: 39426584 | I9: =G9+H9 | N9: =J9+I9+F9+E9+L9+M9+K9 | O9: =N9+D9 | P9: ='Cumul annuel'!A9 | Q9: =D9 | R9: 833333.33 | S9: =Q9-R9 | T9: =Q9/R9-1 | U9: 0 | V9: =Q9-U9 | W9: =(Q9/U9-1)
A10: ='Cumul annuel'!A10 | C10: =D10-B10 | D10: 1952178 | I10: =G10+H10 | N10: =J10+I10+F10+E10+L10+M10+K10 | O10: =N10+D10 | P10: ='Cumul annuel'!A10 | Q10: =D10 | R10: 4600000 | S10: =Q10-R10 | T10: =Q10/R10-1 | U10: 3901923 | V10: =Q10-U10 | W10: =(Q10/U10-1)
A11: ='Cumul annuel'!A11 | C11: =D11-B11 | E11: 2323630 | I11: =G11+H11 | N11: =J11+I11+F11+E11+L11+M11+K11 | O11: =N11+D11 | P11: ='Cumul annuel'!A11 | Q11: =D11 | R11: 5833333.3 | S11: =Q11-R11 | T11: =Q11/R11-1 | U11: 935500 | V11: =Q11-U11 | W11: =(Q11/U11-1)
A12: ='Cumul annuel'!A12 | C12: =D12-B12 | G12: 141359 | I12: =G12+H12 | N12: =J12+I12+F12+E12+L12+M12+K12 | O12: =N12+D12 | P12: ='Cumul annuel'!A12 | Q12: =D12 | R12: 44251612 | S12: =Q12-R12 | T12: =Q12/R12-1 | U12: 25000 | V12: =Q12-U12 | W12: =(Q12/U12-1)
A13: ='Cumul annuel'!A13 | C13: =D13-B13 | G13: 6583510 | I13: =G13+H13 | L13: 600000 | N13: =J13+I13+F13+E13+L13+M13+K13 | O13: =N13+D13 | P13: ='Cumul annuel'!A13 | Q13: =D13 | R13: 55100388 | S13: =Q13-R13 | T13: =Q13/R13-1 | U13: 0 | V13: =Q13-U13 | W13: =(Q13/U13-1)
A14: ='Cumul annuel'!A14 | C14: =D14-B14 | I14: =G14+H14 | N14: =J14+I14+F14+E14+L14+M14+K14 | O14: =N14+D14 | P14: ='Cumul annuel'!A14 | Q14: =D14 | R14: 0 | S14: =Q14-R14 | T14: =Q14/R14-1 | U14: 634000 | V14: =Q14-U14 | W14: =(Q14/U14-1)
A15: ='Cumul annuel'!A15 | C15: =D15-B15 | D15: 18364646 | G15: 825913 | I15: =G15+H15 | N15: =J15+I15+F15+E15+L15+M15+K15 | O15: =N15+D15 | P15: ='Cumul annuel'!A15 | Q15: =D15 | R15: 20833333 | S15: =Q15-R15 | T15: =Q15/R15-1 | U15: 25737948 | V15: =Q15-U15 | W15: =(Q15/U15-1)
A16: ='Cumul annuel'!A16 | C16: =D16-B16 | D16: 8521366 | I16: =G16+H16 | N16: =J16+I16+F16+E16+L16+M16+K16 | O16: =N16+D16 | P16: ='Cumul annuel'!A16 | Q16: =D16 | R16: 833333.33 | S16: =Q16-R16 | T16: =Q16/R16-1 | U16: -52578408 | V16: =Q16-U16 | W16: =(Q16/U16-1)
A17: ='Cumul annuel'!A17 | C17: =D17-B17 | D17: 59622025 | I17: =G17+H17 | K17: 18820000 | L17: 1650000 | N17: =J17+I17+F17+E17+L17+M17+K17 | O17: =N17+D17 | P17: ='Cumul annuel'!A17 | Q17: =D17 | R17: 175000000 | S17: =Q17-R17 | T17: =Q17/R17-1 | U17: 97211644 | V17: =Q17-U17 | W17: =(Q17/U17-1)
A18: ='Cumul annuel'!A18 | C18: =D18-B18 | I18: =G18+H18 | N18: =J18+I18+F18+E18+L18+M18+K18 | O18: =N18+D18 | P18: ='Cumul annuel'!A18 | Q18: =D18 | R18: 0 | S18: =Q18-R18 | T18: =Q18/R18-1 | U18: 0 | V18: =Q18-U18 | W18: =(Q18/U18-1)
A19: ='Cumul annuel'!A19 | B19: 2046000 | C19: =D19-B19 | D19: 3315804 | I19: =G19+H19 | N19: =J19+I19+F19+E19+L19+M19+K19 | O19: =N19+D19 | P19: ='Cumul annuel'!A19 | Q19: =D19 | R19: 5000000 | S19: =Q19-R19 | T19: =Q19/R19-1 | U19: 6935287 | V19: =Q19-U19 | W19: =(Q19/U19-1)
A20: ='Cumul annuel'!A20 | C20: =D20-B20 | D20: 19553800 | I20: =G20+H20 | N20: =J20+I20+F20+E20+L20+M20+K20 | O20: =N20+D20 | P20: ='Cumul annuel'!A20 | Q20: =D20 | R20: 0 | S20: =Q20-R20 | T20: =Q20/R20-1 | U20: 0 | V20: =Q20-U20 | W20: =(Q20/U20-1)
A21: ='Cumul annuel'!A21 | C21: =D21-B21 | D21: 17537053 | E21: 6908800 | F21: 1325000 | G21: 19213726 | I21: =G21+H21 | N21: =J21+I21+F21+E21+L21+M21+K21 | O21: =N21+D21 | P21: ='Cumul annuel'!A21 | Q21: =D21 | R21: 20833333 | S21: =Q21-R21 | T21: =Q21/R21-1 | U21: 46150057 | V21: =Q21-U21 | W21: =(Q21/U21-1)
A22: ='Cumul annuel'!A22 | B22: 1470000 | C22: =D22-B22 | D22: 4978298 | I22: =G22+H22 | N22: =J22+I22+F22+E22+L22+M22+K22 | O22: =N22+D22 | P22: ='Cumul annuel'!A22 | Q22: =D22 | R22: 13333333 | S22: =Q22-R22 | T22: =Q22/R22-1 | U22: 6296244 | V22: =Q22-U22 | W22: =(Q22/U22-1)
A23: ='Cumul annuel'!A23 | C23: =D23-B23 | I23: =G23+H23 | N23: =J23+I23+F23+E23+L23+M23+K23 | O23: =N23+D23 | P23: ='Cumul annuel'!A23 | Q23: =D23 | R23: 0 | S23: =Q23-R23 | T23: =Q23/R23-1 | U23: 0 | V23: =Q23-U23 | W23: =(Q23/U23-1)
A24: ='Cumul annuel'!A24 | C24: =D24-B24 | I24: =G24+H24 | N24: =J24+I24+F24+E24+L24+M24+K24 | O24: =N24+D24 | P24: ='Cumul annuel'!A24 | Q24: =D24 | R24: 0 | S24: =Q24-R24 | T24: =Q24/R24-1 | U24: 200000 | V24: =Q24-U24 | W24: =(Q24/U24-1)
A25: AFRILOG | C25: =D25-B25 | I25: =G25+H25 | N25: =J25+I25+F25+E25+L25+M25+K25 | O25: =N25+D25 | P25: ='Cumul annuel'!A25 | Q25: =D25 | R25: 0 | S25: =Q25-R25 | T25: =Q25/R25-1 | U25: 150000 | V25: =Q25-U25 | W25: =(Q25/U25-1)
A26: ='Cumul annuel'!A26 | C26: =D26-B26 | D26: 2841613 | I26: =G26+H26 | N26: =J26+I26+F26+E26+L26+M26+K26 | O26: =N26+D26 | P26: ='Cumul annuel'!A26 | Q26: =D26 | R26: 833333.33 | S26: =Q26-R26 | T26: =Q26/R26-1 | U26: 0 | V26: =Q26-U26 | W26: =(Q26/U26-1)
A27: ='Cumul annuel'!A27 | C27: =D27-B27 | I27: =G27+H27 | N27: =J27+I27+F27+E27+L27+M27+K27 | O27: =N27+D27 | P27: ='Cumul annuel'!A27 | Q27: =D27 | R27: 4166666.7 | S27: =Q27-R27 | T27: =Q27/R27-1 | U27: 0 | V27: =Q27-U27 | W27: =(Q27/U27-1)
A28: ='Cumul annuel'!A28 | C28: =D28-B28 | D28: 2053000 | I28: =G28+H28 | N28: =J28+I28+F28+E28+L28+M28+K28 | O28: =N28+D28 | P28: ='Cumul annuel'!A28 | Q28: =D28 | R28: 5000000 | S28: =Q28-R28 | T28: =Q28/R28-1 | U28: 3076500 | V28: =Q28-U28 | W28: =(Q28/U28-1)
A29: ='Cumul annuel'!A29 | C29: =D29-B29 | D29: 13636000 | I29: =G29+H29 | N29: =J29+I29+F29+E29+L29+M29+K29 | O29: =N29+D29 | P29: ='Cumul annuel'!A29 | Q29: =D29 | R29: 37500000 | S29: =Q29-R29 | T29: =Q29/R29-1 | U29: 56048000 | V29: =Q29-U29 | W29: =(Q29/U29-1)
A30: ='Cumul annuel'!A30 | C30: =D30-B30 | I30: =G30+H30 | N30: =J30+I30+F30+E30+L30+M30+K30 | O30: =N30+D30 | P30: ='Cumul annuel'!A30 | Q30: =D30 | R30: 0 | S30: =Q30-R30 | T30: =Q30/R30-1 | U30: 0 | V30: =Q30-U30 | W30: =(Q30/U30-1)
A31: ='Cumul annuel'!A31 | C31: =D31-B31 | I31: =G31+H31 | N31: =J31+I31+F31+E31+L31+M31+K31 | O31: =N31+D31 | P31: ='Cumul annuel'!A31 | Q31: =D31 | R31: 0 | S31: =Q31-R31 | T31: =Q31/R31-1 | U31: 0 | V31: =Q31-U31 | W31: =(Q31/U31-1)
A32: ='Cumul annuel'!A32 | C32: =D32-B32 | I32: =G32+H32 | N32: =J32+I32+F32+E32+L32+M32+K32 | O32: =N32+D32 | P32: ='Cumul annuel'!A32 | Q32: =D32 | R32: 0 | S32: =Q32-R32 | T32: =Q32/R32-1 | U32: 0 | V32: =Q32-U32 | W32: =(Q32/U32-1)
A33: ='Cumul annuel'!A33 | C33: =D33-B33 | I33: =G33+H33 | N33: =J33+I33+F33+E33+L33+M33+K33 | O33: =N33+D33 | P33: ='Cumul annuel'!A33 | Q33: =D33 | R33: 0 | S33: =Q33-R33 | T33: =Q33/R33-1 | U33: 0 | V33: =Q33-U33 | W33: =(Q33/U33-1)
A34: ='Cumul annuel'!A34 | C34: =D34-B34 | I34: =G34+H34 | N34: =J34+I34+F34+E34+L34+M34+K34 | O34: =N34+D34 | P34: ='Cumul annuel'!A34 | Q34: =D34 | R34: 0 | S34: =Q34-R34 | T34: =Q34/R34-1 | U34: 0 | V34: =Q34-U34 | W34: =(Q34/U34-1)
A35: ='Cumul annuel'!A35 | C35: =D35-B35 | I35: =G35+H35 | N35: =J35+I35+F35+E35+L35+M35+K35 | O35: =N35+D35 | P35: ='Cumul annuel'!A35 | Q35: =D35 | R35: 66666.667 | S35: =Q35-R35 | T35: =Q35/R35-1 | U35: 0 | V35: =Q35-U35 | W35: =(Q35/U35-1)
A36: ='Cumul annuel'!A36 | C36: =D36-B36 | D36: 8387683 | I36: =G36+H36 | N36: =J36+I36+F36+E36+L36+M36+K36 | O36: =N36+D36 | P36: ='Cumul annuel'!A36 | Q36: =D36 | R36: 0 | S36: =Q36-R36 | T36: =Q36/R36-1 | U36: 0 | V36: =Q36-U36 | W36: =(Q36/U36-1)
A37: ='Cumul annuel'!A37 | C37: =D37-B37 | I37: =G37+H37 | N37: =J37+I37+F37+E37+L37+M37+K37 | O37: =N37+D37 | P37: ='Cumul annuel'!A37 | Q37: =D37 | R37: 833333.33 | S37: =Q37-R37 | T37: =Q37/R37-1 | U37: 0 | V37: =Q37-U37 | W37: =(Q37/U37-1)
A38: ='Cumul annuel'!A38 | B38: 57500000 | C38: =D38-B38 | D38: 105856520 | I38: =G38+H38 | K38: 17200000 | N38: =J38+I38+F38+E38+L38+M38+K38 | O38: =N38+D38 | P38: ='Cumul annuel'!A38 | Q38: =D38 | R38: 55833333 | S38: =Q38-R38 | T38: =Q38/R38-1 | U38: 45757420 | V38: =Q38-U38 | W38: =(Q38/U38-1)
A39: ='Cumul annuel'!A39 | C39: =D39-B39 | I39: =G39+H39 | N39: =J39+I39+F39+E39+L39+M39+K39 | O39: =N39+D39 | P39: ='Cumul annuel'!A39 | Q39: =D39 | R39: 200000 | S39: =Q39-R39 | T39: =Q39/R39-1 | U39: 0 | V39: =Q39-U39 | W39: =(Q39/U39-1)
A40: ='Cumul annuel'!A40 | C40: =D40-B40 | I40: =G40+H40 | N40: =J40+I40+F40+E40+L40+M40+K40 | O40: =N40+D40 | P40: ='Cumul annuel'!A40 | Q40: =D40 | R40: 0 | S40: =Q40-R40 | T40: =Q40/R40-1 | U40: 0 | V40: =Q40-U40 | W40: =(Q40/U40-1)
A41: ='Cumul annuel'!A41 | C41: =D41-B41 | I41: =G41+H41 | N41: =J41+I41+F41+E41+L41+M41+K41 | O41: =N41+D41 | P41: ='Cumul annuel'!A41 | Q41: =D41 | R41: 0 | S41: =Q41-R41 | T41: =Q41/R41-1 | U41: 0 | V41: =Q41-U41 | W41: =(Q41/U41-1)
A42: ='Cumul annuel'!A42 | B42: 763750 | C42: =D42-B42 | D42: 763750 | I42: =G42+H42 | N42: =J42+I42+F42+E42+L42+M42+K42 | O42: =N42+D42 | P42: ='Cumul annuel'!A42 | Q42: =D42 | R42: 1000000 | S42: =Q42-R42 | T42: =Q42/R42-1 | U42: 763750 | V42: =Q42-U42 | W42: =(Q42/U42-1)
A43: ='Cumul annuel'!A43 | C43: =D43-B43 | I43: =G43+H43 | N43: =J43+I43+F43+E43+L43+M43+K43 | O43: =N43+D43 | P43: ='Cumul annuel'!A43 | Q43: =D43 | R43: 0 | S43: =Q43-R43 | T43: =Q43/R43-1 | U43: 0 | V43: =Q43-U43 | W43: =(Q43/U43-1)
A44: ='Cumul annuel'!A44 | C44: =D44-B44 | I44: =G44+H44 | N44: =J44+I44+F44+E44+L44+M44+K44 | O44: =N44+D44 | P44: ='Cumul annuel'!A44 | Q44: =D44 | R44: 0 | S44: =Q44-R44 | T44: =Q44/R44-1 | U44: 91600 | V44: =Q44-U44 | W44: =(Q44/U44-1)
A45: ='Cumul annuel'!A45 | C45: =D45-B45 | D45: 39389020 | I45: =G45+H45 | N45: =J45+I45+F45+E45+L45+M45+K45 | O45: =N45+D45 | P45: ='Cumul annuel'!A45 | Q45: =D45 | R45: 25000000 | S45: =Q45-R45 | T45: =Q45/R45-1 | U45: 0 | V45: =Q45-U45 | W45: =(Q45/U45-1)
A46: ='Cumul annuel'!A46 | C46: =D46-B46 | I46: =G46+H46 | N46: =J46+I46+F46+E46+L46+M46+K46 | O46: =N46+D46 | P46: ='Cumul annuel'!A46 | Q46: =D46 | R46: 0 | S46: =Q46-R46 | T46: =Q46/R46-1 | U46: 0 | V46: =Q46-U46 | W46: =(Q46/U46-1)
A47: ='Cumul annuel'!A47 | C47: =D47-B47 | D47: 18000000 | I47: =G47+H47 | N47: =J47+I47+F47+E47+L47+M47+K47 | O47: =N47+D47 | P47: ='Cumul annuel'!A47 | Q47: =D47 | R47: 17916667 | S47: =Q47-R47 | T47: =Q47/R47-1 | U47: 36000000 | V47: =Q47-U47 | W47: =(Q47/U47-1)
A48: ='Cumul annuel'!A48 | C48: =D48-B48 | I48: =G48+H48 | N48: =J48+I48+F48+E48+L48+M48+K48 | O48: =N48+D48 | P48: ='Cumul annuel'!A48 | Q48: =D48 | R48: 400000 | S48: =Q48-R48 | T48: =Q48/R48-1 | U48: 0 | V48: =Q48-U48 | W48: =(Q48/U48-1)
A49: ='Cumul annuel'!A49 | B49: 63046250 | C49: =D49-B49 | D49: 399472902 | I49: =G49+H49 | K49: 82000000 | L49: 3140000 | N49: =J49+I49+F49+E49+L49+M49+K49 | O49: =N49+D49 | P49: ='Cumul annuel'!A49 | Q49: =D49 | R49: 1.9133333e+08 | S49: =Q49-R49 | T49: =Q49/R49-1 | U49: 0 | V49: =Q49-U49 | W49: =(Q49/U49-1)
A50: ='Cumul annuel'!A50 | C50: =D50-B50 | I50: =G50+H50 | N50: =J50+I50+F50+E50+L50+M50+K50 | O50: =N50+D50 | P50: ='Cumul annuel'!A50 | Q50: =D50 | R50: 0 | S50: =Q50-R50 | T50: =Q50/R50-1 | U50: 0 | V50: =Q50-U50 | W50: =(Q50/U50-1)
A51: CA TOTAL | B51: =SUM(B4:B50) | C51: =D51-B51 | D51: =SUM(D4:D50) | E51: =SUM(E4:E50) | F51: =SUM(F4:F50) | H51: =SUM(H4:H50) | I51: =SUM(I4:I50) | J51: =SUM(J4:J50) | K51: =SUM(K4:K50) | L51: =SUM(L4:L50) | M51: =SUM(M5:M50) | N51: =J51+I51+F51+E51+L51+M51+K51 | O51: =N51+D51 | P51: ACTIVITE BASE | Q51: =D51 | R51: =SUM(R4:R50) | S51: =Q51-R51 | T51: =Q51/R51-1 | U51: =SUM(U4:U50) | V51: =Q51-U51 | W51: =(Q51/U51-1)
A52: Rétrocession | P52: Rétrocessions | Q52: =D52 | S52: =Q52-R52 | T52: =Q52/R52-1 | U52: 6361396
A53: Taux Rétrocession | E53: =E52/E51 | F53: =F52/F51 | I53: =I52/I51 | J53: =J52/J51 | N53: =N52/N51 | P53: IMAR | Q53: =E52 | S53: =Q53-R53 | T53: =Q53/R53-1 | U53: 0 | V53: =Q53-U53 | W53: =(Q53/U53-1)
A54: TOTAL Après rétrocession | D54: =D52+D51 | E54: =E51-E52 | F54: =F51-F52 | I54: =I51-I52 | J54: =J51-J52 | K54: =K51 | L54: =L51 | M54: =M51 | N54: =SUM(D54:M54) | P54: HINT | Q54: =F52 | S54: =Q54-R54 | T54: =Q54/R54-1 | U54: 3302234 | V54: =Q54-U54 | W54: =(Q54/U54-1)
P55: AER | Q55: =I52 | S55: =Q55-R55 | T55: =Q55/R55-1 | U55: 0 | V55: =Q55-U55 | W55: =(Q55/U55-1)
P56: EMAR | Q56: =J52 | S56: =Q56-R56 | T56: =Q56/R56-1 | U56: 3059162 | V56: =Q56-U56 | W56: =(Q56/U56-1)
B57: Loyer | C57: =B51 | D57: =C57/$C$60 | P57: ACTIVITE O&G | Q57: =Q51+Q52 | R57: =R51+R52 | S57: =S51+S53+S54+S55+S56 | T57: =Q57/R57-1 | U57: =U51+U52 | V57: =V51+V53+V54+V55+V56 | W57: =(Q57/U57-1)
B58: LOGP | C58: =C51 | D58: =C58/$C$60 | P58: R26 | R58: Variation Réel 26 / B26 | U58: Variation Réel 26 / Réel 25
B59: Rétros | C59: =D52 | D59: =C59/$C$60
B60: TOTAL CAP | C60: =D54 | D60: =C60/$C$60
R63: =R60-R57

Sheet Mars
B1: CAP Mars | P1: VARIATION R 26 sur B26 & R25
B2: BASE | E2: CA GENERE | P2: R26 | R2: Variation Réel 26 / B26 | U2: 2046 | X2: Commentaires
B3: LOYER | C3: Plog & Divers | D3: Total BASE | E3: IMAR | F3: HINT | G3: IAER | H3: EAER | I3: AERIEN | J3: EXPORT | K3: SIRT | L3: Afritramp | M3: Meet & Greet | N3: CA GENERE Autres département | O3: CA TOTAL GENERE PAR CLIENT | P3: Sources revenus | Q3: REEL BASE 2026 | R3: Budget 2026 | S3: VAR (FCFA) | T3: Var (%) | U3: Réel BASE 2025 | V3: VAR (FCFA) | W3: Var (%)
A4: ='Cumul annuel'!A4 | C4: =D4-B4 | I4: =G4+H4 | N4: =J4+I4+F4+E4+L4+M4+K4 | O4: =N4+D4 | P4: ='Cumul annuel'!A4 | Q4: =D4 | R4: 0 | S4: =Q4-R4 | T4: =Q4/R4-1 | U4: 0 | V4: =Q4-U4 | W4: =(Q4/U4-1)
A5: ='Cumul annuel'!A5 | C5: =D5-B5 | D5: 1137418 | I5: =G5+H5 | N5: =J5+I5+F5+E5+L5+M5+K5 | O5: =N5+D5 | P5: ='Cumul annuel'!A5 | Q5: =D5 | R5: 6666666.7 | S5: =Q5-R5 | T5: =Q5/R5-1 | U5: 0 | V5: =Q5-U5 | W5: =(Q5/U5-1)
A6: ='Cumul annuel'!A6 | C6: =D6-B6 | D6: 22000000 | I6: =G6+H6 | N6: =J6+I6+F6+E6+L6+M6+K6 | O6: =N6+D6 | P6: ='Cumul annuel'!A6 | Q6: =D6 | R6: 10750000 | S6: =Q6-R6 | T6: =Q6/R6-1 | U6: 0 | V6: =Q6-U6 | W6: =(Q6/U6-1)
A7: ='Cumul annuel'!A7 | B7: 38715900 | C7: =D7-B7 | D7: 60825072 | I7: =G7+H7 | N7: =J7+I7+F7+E7+L7+M7+K7 | O7: =N7+D7 | P7: ='Cumul annuel'!A7 | Q7: =D7 | R7: 50000000 | S7: =Q7-R7 | T7: =Q7/R7-1 | U7: 25000 | V7: =Q7-U7 | W7: =(Q7/U7-1)
A8: ='Cumul annuel'!A8 | C8: =D8-B8 | I8: =G8+H8 | N8: =J8+I8+F8+E8+L8+M8+K8 | O8: =N8+D8 | P8: ='Cumul annuel'!A8 | Q8: =D8 | R8: 0 | S8: =Q8-R8 | T8: =Q8/R8-1 | U8: 55340648 | V8: =Q8-U8 | W8: =(Q8/U8-1)
A9: ='Cumul annuel'!A9 | C9: =D9-B9 | D9: 21871979 | I9: =G9+H9 | N9: =J9+I9+F9+E9+L9+M9+K9 | O9: =N9+D9 | P9: ='Cumul annuel'!A9 | Q9: =D9 | R9: 833333.33 | S9: =Q9-R9 | T9: =Q9/R9-1 | U9: 0 | V9: =Q9-U9 | W9: =(Q9/U9-1)
A10: ='Cumul annuel'!A10 | C10: =D10-B10 | D10: 1587400 | I10: =G10+H10 | N10: =J10+I10+F10+E10+L10+M10+K10 | O10: =N10+D10 | P10: ='Cumul annuel'!A10 | Q10: =D10 | R10: 4600000 | S10: =Q10-R10 | T10: =Q10/R10-1 | U10: 2541480 | V10: =Q10-U10 | W10: =(Q10/U10-1)
A11: ='Cumul annuel'!A11 | C11: =D11-B11 | G11: 301740 | I11: =G11+H11 | L11: 3300000 | N11: =J11+I11+F11+E11+L11+M11+K11 | O11: =N11+D11 | P11: ='Cumul annuel'!A11 | Q11: =D11 | R11: 5833333.3 | S11: =Q11-R11 | T11: =Q11/R11-1 | U11: 300000 | V11: =Q11-U11 | W11: =(Q11/U11-1)
A12: ='Cumul annuel'!A12 | C12: =D12-B12 | G12: 781245 | I12: =G12+H12 | L12: 544444 | N12: =J12+I12+F12+E12+L12+M12+K12 | O12: =N12+D12 | P12: ='Cumul annuel'!A12 | Q12: =D12 | R12: 44251612 | S12: =Q12-R12 | T12: =Q12/R12-1 | U12: 0 | V12: =Q12-U12 | W12: =(Q12/U12-1)
A13: ='Cumul annuel'!A13 | C13: =D13-B13 | I13: =G13+H13 | N13: =J13+I13+F13+E13+L13+M13+K13 | O13: =N13+D13 | P13: ='Cumul annuel'!A13 | Q13: =D13 | R13: 55100388 | S13: =Q13-R13 | T13: =Q13/R13-1 | U13: 10675000 | V13: =Q13-U13 | W13: =(Q13/U13-1)
A14: ='Cumul annuel'!A14 | C14: =D14-B14 | I14: =G14+H14 | N14: =J14+I14+F14+E14+L14+M14+K14 | O14: =N14+D14 | P14: ='Cumul annuel'!A14 | Q14: =D14 | R14: 0 | S14: =Q14-R14 | T14: =Q14/R14-1 | U14: 0 | V14: =Q14-U14 | W14: =(Q14/U14-1)
A15: ='Cumul annuel'!A15 | C15: =D15-B15 | D15: 12461220 | I15: =G15+H15 | N15: =J15+I15+F15+E15+L15+M15+K15 | O15: =N15+D15 | P15: ='Cumul annuel'!A15 | Q15: =D15 | R15: 20833333 | S15: =Q15-R15 | T15: =Q15/R15-1 | U15: 8157185 | V15: =Q15-U15 | W15: =(Q15/U15-1)
A16: ='Cumul annuel'!A16 | C16: =D16-B16 | D16: 11769763 | I16: =G16+H16 | N16: =J16+I16+F16+E16+L16+M16+K16 | O16: =N16+D16 | P16: ='Cumul annuel'!A16 | Q16: =D16 | R16: 833333.33 | S16: =Q16-R16 | T16: =Q16/R16-1 | U16: 23780000 | V16: =Q16-U16 | W16: =(Q16/U16-1)
A17: ='Cumul annuel'!A17 | B17: 54314000 | C17: =D17-B17 | D17: 193586525 | I17: =G17+H17 | K17: 60000000 | L17: 4850000 | N17: =J17+I17+F17+E17+L17+M17+K17 | O17: =N17+D17 | P17: ='Cumul annuel'!A17 | Q17: =D17 | R17: 175000000 | S17: =Q17-R17 | T17: =Q17/R17-1 | U17: 58902025 | V17: =Q17-U17 | W17: =(Q17/U17-1)
A18: ='Cumul annuel'!A18 | C18: =D18-B18 | I18: =G18+H18 | N18: =J18+I18+F18+E18+L18+M18+K18 | O18: =N18+D18 | P18: ='Cumul annuel'!A18 | Q18: =D18 | R18: 0 | S18: =Q18-R18 | T18: =Q18/R18-1 | U18: 0 | V18: =Q18-U18 | W18: =(Q18/U18-1)
A19: ='Cumul annuel'!A19 | B19: 2046000 | C19: =D19-B19 | D19: 3811974 | I19: =G19+H19 | N19: =J19+I19+F19+E19+L19+M19+K19 | O19: =N19+D19 | P19: ='Cumul annuel'!A19 | Q19: =D19 | R19: 5000000 | S19: =Q19-R19 | T19: =Q19/R19-1 | U19: 3379953 | V19: =Q19-U19 | W19: =(Q19/U19-1)
A20: ='Cumul annuel'!A20 | C20: =D20-B20 | I20: =G20+H20 | N20: =J20+I20+F20+E20+L20+M20+K20 | O20: =N20+D20 | P20: ='Cumul annuel'!A20 | Q20: =D20 | R20: 0 | S20: =Q20-R20 | T20: =Q20/R20-1 | U20: 12505800 | V20: =Q20-U20 | W20: =(Q20/U20-1)
A21: ='Cumul annuel'!A21 | C21: =D21-B21 | D21: 1665045 | E21: 193500 | G21: 6053268 | I21: =G21+H21 | N21: =J21+I21+F21+E21+L21+M21+K21 | O21: =N21+D21 | P21: ='Cumul annuel'!A21 | Q21: =D21 | R21: 20833333 | S21: =Q21-R21 | T21: =Q21/R21-1 | U21: 38411761 | V21: =Q21-U21 | W21: =(Q21/U21-1)
A22: ='Cumul annuel'!A22 | B22: 1470000 | C22: =D22-B22 | D22: 7540258 | I22: =G22+H22 | N22: =J22+I22+F22+E22+L22+M22+K22 | O22: =N22+D22 | P22: ='Cumul annuel'!A22 | Q22: =D22 | R22: 13333333 | S22: =Q22-R22 | T22: =Q22/R22-1 | U22: 5483988 | V22: =Q22-U22 | W22: =(Q22/U22-1)
A23: ='Cumul annuel'!A23 | C23: =D23-B23 | I23: =G23+H23 | N23: =J23+I23+F23+E23+L23+M23+K23 | O23: =N23+D23 | P23: ='Cumul annuel'!A23 | Q23: =D23 | R23: 0 | S23: =Q23-R23 | T23: =Q23/R23-1 | U23: 0 | V23: =Q23-U23 | W23: =(Q23/U23-1)
A24: ='Cumul annuel'!A24 | C24: =D24-B24 | I24: =G24+H24 | N24: =J24+I24+F24+E24+L24+M24+K24 | O24: =N24+D24 | P24: ='Cumul annuel'!A24 | Q24: =D24 | R24: 0 | S24: =Q24-R24 | T24: =Q24/R24-1 | U24: 0 | V24: =Q24-U24 | W24: =(Q24/U24-1)
A25: ='Cumul annuel'!A25 | C25: =D25-B25 | I25: =G25+H25 | N25: =J25+I25+F25+E25+L25+M25+K25 | O25: =N25+D25 | P25: ='Cumul annuel'!A25 | Q25: =D25 | R25: 0 | S25: =Q25-R25 | T25: =Q25/R25-1 | U25: 0 | V25: =Q25-U25 | W25: =(Q25/U25-1)
A26: ='Cumul annuel'!A26 | B26: 2500000 | C26: =D26-B26 | D26: 7980890 | I26: =G26+H26 | N26: =J26+I26+F26+E26+L26+M26+K26 | O26: =N26+D26 | P26: ='Cumul annuel'!A26 | Q26: =D26 | R26: 833333.33 | S26: =Q26-R26 | T26: =Q26/R26-1 | U26: 0 | V26: =Q26-U26 | W26: =(Q26/U26-1)
A27: ='Cumul annuel'!A27 | C27: =D27-B27 | I27: =G27+H27 | N27: =J27+I27+F27+E27+L27+M27+K27 | O27: =N27+D27 | P27: ='Cumul annuel'!A27 | Q27: =D27 | R27: 4166666.7 | S27: =Q27-R27 | T27: =Q27/R27-1 | U27: 0 | V27: =Q27-U27 | W27: =(Q27/U27-1)
A28: ='Cumul annuel'!A28 | B28: 1450000 | C28: =D28-B28 | D28: 1977000 | I28: =G28+H28 | N28: =J28+I28+F28+E28+L28+M28+K28 | O28: =N28+D28 | P28: ='Cumul annuel'!A28 | Q28: =D28 | R28: 5000000 | S28: =Q28-R28 | T28: =Q28/R28-1 | U28: 2888500 | V28: =Q28-U28 | W28: =(Q28/U28-1)
A29: ='Cumul annuel'!A29 | C29: =D29-B29 | D29: 67993200 | I29: =G29+H29 | N29: =J29+I29+F29+E29+L29+M29+K29 | O29: =N29+D29 | P29: ='Cumul annuel'!A29 | Q29: =D29 | R29: 37500000 | S29: =Q29-R29 | T29: =Q29/R29-1 | U29: 148941900 | V29: =Q29-U29 | W29: =(Q29/U29-1)
A30: ='Cumul annuel'!A30 | C30: =D30-B30 | I30: =G30+H30 | N30: =J30+I30+F30+E30+L30+M30+K30 | O30: =N30+D30 | P30: ='Cumul annuel'!A30 | Q30: =D30 | R30: 0 | S30: =Q30-R30 | T30: =Q30/R30-1 | U30: 0 | V30: =Q30-U30 | W30: =(Q30/U30-1)
A31: ='Cumul annuel'!A31 | C31: =D31-B31 | I31: =G31+H31 | N31: =J31+I31+F31+E31+L31+M31+K31 | O31: =N31+D31 | P31: ='Cumul annuel'!A31 | Q31: =D31 | R31: 0 | S31: =Q31-R31 | T31: =Q31/R31-1 | U31: 1400000 | V31: =Q31-U31 | W31: =(Q31/U31-1)
A32: ='Cumul annuel'!A32 | C32: =D32-B32 | I32: =G32+H32 | N32: =J32+I32+F32+E32+L32+M32+K32 | O32: =N32+D32 | P32: ='Cumul annuel'!A32 | Q32: =D32 | R32: 0 | S32: =Q32-R32 | T32: =Q32/R32-1 | U32: 0 | V32: =Q32-U32 | W32: =(Q32/U32-1)
A33: ='Cumul annuel'!A33 | C33: =D33-B33 | I33: =G33+H33 | N33: =J33+I33+F33+E33+L33+M33+K33 | O33: =N33+D33 | P33: ='Cumul annuel'!A33 | Q33: =D33 | R33: 0 | S33: =Q33-R33 | T33: =Q33/R33-1 | U33: 0 | V33: =Q33-U33 | W33: =(Q33/U33-1)
A34: ='Cumul annuel'!A34 | C34: =D34-B34 | I34: =G34+H34 | N34: =J34+I34+F34+E34+L34+M34+K34 | O34: =N34+D34 | P34: ='Cumul annuel'!A34 | Q34: =D34 | R34: 0 | S34: =Q34-R34 | T34: =Q34/R34-1 | U34: 0 | V34: =Q34-U34 | W34: =(Q34/U34-1)
A35: ='Cumul annuel'!A35 | C35: =D35-B35 | I35: =G35+H35 | N35: =J35+I35+F35+E35+L35+M35+K35 | O35: =N35+D35 | P35: ='Cumul annuel'!A35 | Q35: =D35 | R35: 66666.667 | S35: =Q35-R35 | T35: =Q35/R35-1 | U35: 0 | V35: =Q35-U35 | W35: =(Q35/U35-1)
A36: ='Cumul annuel'!A36 | C36: =D36-B36 | D36: 2400000 | I36: =G36+H36 | N36: =J36+I36+F36+E36+L36+M36+K36 | O36: =N36+D36 | P36: ='Cumul annuel'!A36 | Q36: =D36 | R36: 0 | S36: =Q36-R36 | T36: =Q36/R36-1 | U36: 2090000 | V36: =Q36-U36 | W36: =(Q36/U36-1)
A37: ='Cumul annuel'!A37 | C37: =D37-B37 | I37: =G37+H37 | N37: =J37+I37+F37+E37+L37+M37+K37 | O37: =N37+D37 | P37: ='Cumul annuel'!A37 | Q37: =D37 | R37: 833333.33 | S37: =Q37-R37 | T37: =Q37/R37-1 | U37: 23230000 | V37: =Q37-U37 | W37: =(Q37/U37-1)
A38: ='Cumul annuel'!A38 | C38: =D38-B38 | D38: 37724123 | I38: =G38+H38 | K38: 6400000 | N38: =J38+I38+F38+E38+L38+M38+K38 | O38: =N38+D38 | P38: ='Cumul annuel'!A38 | Q38: =D38 | R38: 55833333 | S38: =Q38-R38 | T38: =Q38/R38-1 | U38: 19758000 | V38: =Q38-U38 | W38: =(Q38/U38-1)
A39: ='Cumul annuel'!A39 | C39: =D39-B39 | I39: =G39+H39 | N39: =J39+I39+F39+E39+L39+M39+K39 | O39: =N39+D39 | P39: ='Cumul annuel'!A39 | Q39: =D39 | R39: 200000 | S39: =Q39-R39 | T39: =Q39/R39-1 | U39: 1800000 | V39: =Q39-U39 | W39: =(Q39/U39-1)
A40: ='Cumul annuel'!A40 | C40: =D40-B40 | I40: =G40+H40 | N40: =J40+I40+F40+E40+L40+M40+K40 | O40: =N40+D40 | P40: ='Cumul annuel'!A40 | Q40: =D40 | R40: 0 | S40: =Q40-R40 | T40: =Q40/R40-1 | U40: 103434481 | V40: =Q40-U40 | W40: =(Q40/U40-1)
A41: ='Cumul annuel'!A41 | C41: =D41-B41 | I41: =G41+H41 | N41: =J41+I41+F41+E41+L41+M41+K41 | O41: =N41+D41 | P41: ='Cumul annuel'!A41 | Q41: =D41 | R41: 0 | S41: =Q41-R41 | T41: =Q41/R41-1 | U41: 0 | V41: =Q41-U41 | W41: =(Q41/U41-1)
A42: ='Cumul annuel'!A42 | B42: 763750 | C42: =D42-B42 | D42: 2233030 | I42: =G42+H42 | N42: =J42+I42+F42+E42+L42+M42+K42 | O42: =N42+D42 | P42: ='Cumul annuel'!A42 | Q42: =D42 | R42: 1000000 | S42: =Q42-R42 | T42: =Q42/R42-1 | U42: 763750 | V42: =Q42-U42 | W42: =(Q42/U42-1)
A43: ='Cumul annuel'!A43 | C43: =D43-B43 | I43: =G43+H43 | N43: =J43+I43+F43+E43+L43+M43+K43 | O43: =N43+D43 | P43: ='Cumul annuel'!A43 | Q43: =D43 | R43: 0 | S43: =Q43-R43 | T43: =Q43/R43-1 | U43: 0 | V43: =Q43-U43 | W43: =(Q43/U43-1)
A44: ='Cumul annuel'!A44 | C44: =D44-B44 | I44: =G44+H44 | K44: 13000000 | L44: 951268 | N44: =J44+I44+F44+E44+L44+M44+K44 | O44: =N44+D44 | P44: ='Cumul annuel'!A44 | Q44: =D44 | R44: 0 | S44: =Q44-R44 | T44: =Q44/R44-1 | U44: 0 | V44: =Q44-U44 | W44: =(Q44/U44-1)
A45: ='Cumul annuel'!A45 | C45: =D45-B45 | I45: =G45+H45 | J45: 4500000 | N45: =J45+I45+F45+E45+L45+M45+K45 | O45: =N45+D45 | P45: ='Cumul annuel'!A45 | Q45: =D45 | R45: 25000000 | S45: =Q45-R45 | T45: =Q45/R45-1 | U45: 70513299 | V45: =Q45-U45 | W45: =(Q45/U45-1)
A46: ='Cumul annuel'!A46 | C46: =D46-B46 | I46: =G46+H46 | N46: =J46+I46+F46+E46+L46+M46+K46 | O46: =N46+D46 | P46: ='Cumul annuel'!A46 | Q46: =D46 | R46: 0 | S46: =Q46-R46 | T46: =Q46/R46-1 | U46: 0 | V46: =Q46-U46 | W46: =(Q46/U46-1)
A47: ='Cumul annuel'!A47 | B47: 18000000 | C47: =D47-B47 | D47: 19200000 | I47: =G47+H47 | N47: =J47+I47+F47+E47+L47+M47+K47 | O47: =N47+D47 | P47: ='Cumul annuel'!A47 | Q47: =D47 | R47: 17916667 | S47: =Q47-R47 | T47: =Q47/R47-1 | U47: 18000000 | V47: =Q47-U47 | W47: =(Q47/U47-1)
A48: ='Cumul annuel'!A48 | C48: =D48-B48 | I48: =G48+H48 | N48: =J48+I48+F48+E48+L48+M48+K48 | O48: =N48+D48 | P48: ='Cumul annuel'!A48 | Q48: =D48 | R48: 400000 | S48: =Q48-R48 | T48: =Q48/R48-1 | U48: 0 | V48: =Q48-U48 | W48: =(Q48/U48-1)
A49: ='Cumul annuel'!A49 | B49: 48545000 | C49: =D49-B49 | D49: 383216160 | I49: =G49+H49 | K49: 82000000 | L49: 2835000 | N49: =J49+I49+F49+E49+L49+M49+K49 | O49: =N49+D49 | P49: ='Cumul annuel'!A49 | Q49: =D49 | R49: 1.9133333e+08 | S49: =Q49-R49 | T49: =Q49/R49-1 | U49: 0 | V49: =Q49-U49 | W49: =(Q49/U49-1)
A50: ='Cumul annuel'!A50 | B50: 11000000 | C50: =D50-B50 | D50: 11914080 | I50: =G50+H50 | N50: =J50+I50+F50+E50+L50+M50+K50 | O50: =N50+D50 | P50: ='Cumul annuel'!A50 | Q50: =D50 | R50: 0 | S50: =Q50-R50 | T50: =Q50/R50-1 | U50: 0 | V50: =Q50-U50 | W50: =(Q50/U50-1)
A51: CA TOTAL | B51: =SUM(B4:B50) | C51: =SUM(C4:C50) | D51: =SUM(D4:D50) | E51: =SUM(E4:E50) | F51: =SUM(F5:F50) | G51: =SUM(G5:G50) | H51: =SUM(H5:H50) | I51: =SUM(I5:I50) | J51: =SUM(J5:J50) | K51: =SUM(K4:K50) | L51: =SUM(L5:L50) | M51: =SUM(M5:M50) | N51: =J51+I51+F51+E51+L51+M51+K51 | O51: =N51+D51 | P51: ACTIVITE BASE | Q51: =SUM(Q4:Q50) | R51: =SUM(R4:R50) | S51: =Q51-R51 | T51: =Q51/R51-1 | U51: =SUM(U4:U50) | V51: =Q51-U51 | W51: =(Q51/U51-1)
A52: Rétrocession | P52: Rétrocessions
A53: Taux Rétrocession | E53: =E52/E51 | F53: =F52/F51 | I53: =I52/I51 | J53: =J52/J51 | N53: =N52/N51 | P53: IMAR | Q53: =E52 | S53: =Q53-R53 | T53: =Q53/R53-1 | U53: 0 | V53: =Q53-U53 | W53: =(Q53/U53-1)
A54: TOTAL Après rétrocession | D54: =D52+D51 | E54: =E51-E52 | F54: =F51-F52 | I54: =I51-I52 | J54: =J51-J52 | K54: =K51 | L54: =L51 | M54: =M51 | N54: =SUM(D54:M54) | P54: HINT | Q54: =F52 | S54: =Q54-R54 | T54: =Q54/R54-1 | U54: 392000 | V54: =Q54-U54 | W54: =(Q54/U54-1)
P55: AER | Q55: =I52 | S55: =Q55-R55 | T55: =Q55/R55-1 | U55: 0 | V55: =Q55-U55 | W55: =(Q55/U55-1)
P56: EMAR | Q56: =J52 | S56: =Q56-R56 | T56: =Q56/R56-1 | U56: 3359312 | V56: =Q56-U56 | W56: =(Q56/U56-1)
B57: Loyer | C57: =B51 | D57: =C57/$D$54 | P57: ACTIVITE O&G | Q57: =Q51+Q53+Q54+Q55+Q56 | R57: =R51+R52 | S57: =S51+S53+S54+S55+S56 | T57: =Q57/R57-1 | U57: =U51+U53+U54+U55+U56 | V57: =V51+V53+V54+V55+V56 | W57: =(Q57/U57-1)
B58: LOGP | C58: =C51 | D58: =C58/$D$54 | P58: R26 | R58: Variation Réel 26 / B26 | U58: Variation Réel 26 / Réel 25
B59: Rétrocession | C59: =D52 | D59: =C59/$D$54

Sheet Avril
B1: CAP Avril | P1: VARIATION R 26 sur B26 & R25
B2: BASE | E2: CA GENERE | P2: R25 | R2: Variation Réel 26 / B26 | U2: Variation Réel 26 / Réel 25 | X2: Commentaires
B3: LOYER | C3: Plog & Divers | D3: Total BASE | E3: IMAR | F3: HINT | G3: IAER | H3: EAER | I3: AERIEN | J3: EXPORT | K3: SIRT | L3: Afritramp | M3: Meet & Greet | N3: CA GENERE Autres département | O3: CA TOTAL GENERE PAR CLIENT | P3: Sources revenus | Q3: REEL BASE 2026 | R3: Budget 2026 | S3: VAR (FCFA) | T3: Var (%) | U3: Réel BASE 2025 | V3: VAR (FCFA) | W3: Var (%)
A4: ='Cumul annuel'!A4 | C4: =D4-B4 | I4: =G4+H4 | N4: =J4+I4+F4+E4+L4+M4+K4 | O4: =N4+D4 | P4: ='Cumul annuel'!A4 | Q4: =D4 | R4: 0 | S4: =Q4-R4 | U4: 0 | V4: =Q4-U4 | W4: =(Q4/U4-1)
A5: ='Cumul annuel'!A5 | B5: 18600000 | C5: =D5-B5 | D5: 20284056 | I5: =G5+H5 | N5: =J5+I5+F5+E5+L5+M5+K5 | O5: =N5+D5 | P5: ='Cumul annuel'!A5 | Q5: =D5 | R5: 6666666.7 | S5: =Q5-R5 | T5: =Q5/R5-1 | U5: 3407668 | V5: =Q5-U5 | W5: =(Q5/U5-1)
A6: ='Cumul annuel'!A6 | B6: 33000000 | C6: =D6-B6 | D6: 33000000 | I6: =G6+H6 | N6: =J6+I6+F6+E6+L6+M6+K6 | O6: =N6+D6 | P6: ='Cumul annuel'!A6 | Q6: =D6 | R6: 10750000 | S6: =Q6-R6 | T6: =Q6/R6-1 | U6: 0 | V6: =Q6-U6 | W6: =(Q6/U6-1)
A7: ='Cumul annuel'!A7 | C7: =D7-B7 | D7: 6059636 | E7: 86210 | I7: =G7+H7 | N7: =J7+I7+F7+E7+L7+M7+K7 | O7: =N7+D7 | P7: ='Cumul annuel'!A7 | Q7: =D7 | R7: 50000000 | S7: =Q7-R7 | T7: =Q7/R7-1 | U7: 29175497 | V7: =Q7-U7 | W7: =(Q7/U7-1)
A8: ='Cumul annuel'!A8 | C8: =D8-B8 | I8: =G8+H8 | N8: =J8+I8+F8+E8+L8+M8+K8 | O8: =N8+D8 | P8: ='Cumul annuel'!A8 | Q8: =D8 | R8: 0 | S8: =Q8-R8 | T8: =Q8/R8-1 | U8: 424255825 | V8: =Q8-U8 | W8: =(Q8/U8-1)
A9: ='Cumul annuel'!A9 | C9: =D9-B9 | D9: 32183413 | I9: =G9+H9 | K9: 4888000 | N9: =J9+I9+F9+E9+L9+M9+K9 | O9: =N9+D9 | P9: ='Cumul annuel'!A9 | Q9: =D9 | R9: 833333.33 | S9: =Q9-R9 | T9: =Q9/R9-1 | U9: 0 | V9: =Q9-U9 | W9: =(Q9/U9-1)
A10: ='Cumul annuel'!A10 | C10: =D10-B10 | D10: 1279104 | G10: 927331 | I10: =G10+H10 | N10: =J10+I10+F10+E10+L10+M10+K10 | O10: =N10+D10 | P10: ='Cumul annuel'!A10 | Q10: =D10 | R10: 4600000 | S10: =Q10-R10 | T10: =Q10/R10-1 | U10: 1700358 | V10: =Q10-U10 | W10: =(Q10/U10-1)
A11: ='Cumul annuel'!A11 | C11: =D11-B11 | D11: 97395200 | I11: =G11+H11 | N11: =J11+I11+F11+E11+L11+M11+K11 | O11: =N11+D11 | P11: ='Cumul annuel'!A11 | Q11: =D11 | R11: 5833333.3 | S11: =Q11-R11 | T11: =Q11/R11-1 | U11: 2301000 | V11: =Q11-U11 | W11: =(Q11/U11-1)
A12: ='Cumul annuel'!A12 | C12: =D12-B12 | I12: =G12+H12 | L12: 327979 | N12: =J12+I12+F12+E12+L12+M12+K12 | O12: =N12+D12 | P12: ='Cumul annuel'!A12 | Q12: =D12 | R12: 44251279 | S12: =Q12-R12 | T12: =Q12/R12-1 | U12: 176311 | V12: =Q12-U12 | W12: =(Q12/U12-1)
A13: ='Cumul annuel'!A13 | C13: =D13-B13 | I13: =G13+H13 | L13: 5350000 | N13: =J13+I13+F13+E13+L13+M13+K13 | O13: =N13+D13 | P13: ='Cumul annuel'!A13 | Q13: =D13 | R13: 55100388 | S13: =Q13-R13 | T13: =Q13/R13-1 | U13: 0 | V13: =Q13-U13 | W13: =(Q13/U13-1)
A14: ='Cumul annuel'!A14 | C14: =D14-B14 | I14: =G14+H14 | N14: =J14+I14+F14+E14+L14+M14+K14 | O14: =N14+D14 | P14: ='Cumul annuel'!A14 | Q14: =D14 | R14: 0 | S14: =Q14-R14 | T14: =Q14/R14-1 | U14: 0 | V14: =Q14-U14 | W14: =(Q14/U14-1)
A15: ='Cumul annuel'!A15 | C15: =D15-B15 | I15: =G15+H15 | N15: =J15+I15+F15+E15+L15+M15+K15 | O15: =N15+D15 | P15: ='Cumul annuel'!A15 | Q15: =D15 | R15: 20833333 | S15: =Q15-R15 | T15: =Q15/R15-1 | U15: 4429153 | V15: =Q15-U15 | W15: =(Q15/U15-1)
A16: ='Cumul annuel'!A16 | C16: =D16-B16 | D16: -1290000 | I16: =G16+H16 | N16: =J16+I16+F16+E16+L16+M16+K16 | O16: =N16+D16 | P16: ='Cumul annuel'!A16 | Q16: =D16 | R16: 833333.33 | S16: =Q16-R16 | T16: =Q16/R16-1 | U16: -1800000 | V16: =Q16-U16 | W16: =(Q16/U16-1)
A17: ='Cumul annuel'!A17 | B17: 27649000 | C17: =D17-B17 | D17: 59262025 | I17: =G17+H17 | K17: 43750000 | L17: 4311221 | N17: =J17+I17+F17+E17+L17+M17+K17 | O17: =N17+D17 | P17: ='Cumul annuel'!A17 | Q17: =D17 | R17: 86111111 | S17: =Q17-R17 | T17: =Q17/R17-1 | U17: 58902025 | V17: =Q17-U17 | W17: =(Q17/U17-1)
A18: ='Cumul annuel'!A18 | C18: =D18-B18 | D18: 28504800 | I18: =G18+H18 | N18: =J18+I18+F18+E18+L18+M18+K18 | O18: =N18+D18 | P18: ='Cumul annuel'!A18 | Q18: =D18 | R18: 0 | S18: =Q18-R18 | T18: =Q18/R18-1 | U18: 0 | V18: =Q18-U18 | W18: =(Q18/U18-1)
A19: ='Cumul annuel'!A19 | B19: 2046000 | C19: =D19-B19 | D19: 4018187 | I19: =G19+H19 | N19: =J19+I19+F19+E19+L19+M19+K19 | O19: =N19+D19 | P19: ='Cumul annuel'!A19 | Q19: =D19 | R19: 5000000 | S19: =Q19-R19 | T19: =Q19/R19-1 | U19: 6165645 | V19: =Q19-U19 | W19: =(Q19/U19-1)
A20: ='Cumul annuel'!A20 | C20: =D20-B20 | I20: =G20+H20 | N20: =J20+I20+F20+E20+L20+M20+K20 | O20: =N20+D20 | P20: ='Cumul annuel'!A20 | Q20: =D20 | R20: 0 | S20: =Q20-R20 | T20: =Q20/R20-1 | U20: 3748000 | V20: =Q20-U20 | W20: =(Q20/U20-1)
A21: ='Cumul annuel'!A21 | B21: 16700000 | C21: =D21-B21 | D21: 18338359 | E21: 1898500 | F21: 1095960 | G21: 2949442 | H21: 1194813 | I21: =G21+H21 | J21: 4292900 | N21: =J21+I21+F21+E21+L21+M21+K21 | O21: =N21+D21 | P21: ='Cumul annuel'!A21 | Q21: =D21 | R21: 20833333 | S21: =Q21-R21 | T21: =Q21/R21-1 | U21: 34527991 | V21: =Q21-U21 | W21: =(Q21/U21-1)
A22: ='Cumul annuel'!A22 | B22: 1470000 | C22: =D22-B22 | D22: 6286030 | I22: =G22+H22 | N22: =J22+I22+F22+E22+L22+M22+K22 | O22: =N22+D22 | P22: ='Cumul annuel'!A22 | Q22: =D22 | R22: 13333333 | S22: =Q22-R22 | T22: =Q22/R22-1 | U22: 6047358 | V22: =Q22-U22 | W22: =(Q22/U22-1)
A23: ='Cumul annuel'!A23 | B23: 450000 | C23: =D23-B23 | D23: 450000 | I23: =G23+H23 | N23: =J23+I23+F23+E23+L23+M23+K23 | O23: =N23+D23 | P23: ='Cumul annuel'!A23 | Q23: =D23 | R23: 0 | S23: =Q23-R23 | T23: =Q23/R23-1 | U23: 450000 | V23: =Q23-U23 | W23: =(Q23/U23-1)
A24: ='Cumul annuel'!A24 | C24: =D24-B24 | I24: =G24+H24 | N24: =J24+I24+F24+E24+L24+M24+K24 | O24: =N24+D24 | P24: ='Cumul annuel'!A24 | Q24: =D24 | R24: 0 | S24: =Q24-R24 | T24: =Q24/R24-1 | U24: 0 | V24: =Q24-U24 | W24: =(Q24/U24-1)
A25: ='Cumul annuel'!A25 | C25: =D25-B25 | I25: =G25+H25 | N25: =J25+I25+F25+E25+L25+M25+K25 | O25: =N25+D25 | P25: ='Cumul annuel'!A25 | Q25: =D25 | R25: 0 | S25: =Q25-R25 | T25: =Q25/R25-1 | U25: 0 | V25: =Q25-U25 | W25: =(Q25/U25-1)
A26: ='Cumul annuel'!A26 | C26: =D26-B26 | D26: 2361292 | I26: =G26+H26 | N26: =J26+I26+F26+E26+L26+M26+K26 | O26: =N26+D26 | P26: ='Cumul annuel'!A26 | Q26: =D26 | R26: 833333.33 | S26: =Q26-R26 | T26: =Q26/R26-1 | U26: 8000000 | V26: =Q26-U26 | W26: =(Q26/U26-1)
A27: ='Cumul annuel'!A27 | C27: =D27-B27 | I27: =G27+H27 | N27: =J27+I27+F27+E27+L27+M27+K27 | O27: =N27+D27 | P27: ='Cumul annuel'!A27 | Q27: =D27 | R27: 4166666.7 | S27: =Q27-R27 | T27: =Q27/R27-1 | U27: 0 | V27: =Q27-U27 | W27: =(Q27/U27-1)
A28: ='Cumul annuel'!A28 | C28: =D28-B28 | D28: 2240500 | I28: =G28+H28 | N28: =J28+I28+F28+E28+L28+M28+K28 | O28: =N28+D28 | P28: ='Cumul annuel'!A28 | Q28: =D28 | R28: 5000000 | S28: =Q28-R28 | T28: =Q28/R28-1 | U28: 2130000 | V28: =Q28-U28 | W28: =(Q28/U28-1)
A29: ='Cumul annuel'!A29 | C29: =D29-B29 | D29: 15456200 | I29: =G29+H29 | N29: =J29+I29+F29+E29+L29+M29+K29 | O29: =N29+D29 | P29: ='Cumul annuel'!A29 | Q29: =D29 | R29: 37500000 | S29: =Q29-R29 | T29: =Q29/R29-1 | U29: 25793038 | V29: =Q29-U29 | W29: =(Q29/U29-1)
A30: ='Cumul annuel'!A30 | C30: =D30-B30 | D30: -137142 | I30: =G30+H30 | N30: =J30+I30+F30+E30+L30+M30+K30 | O30: =N30+D30 | P30: ='Cumul annuel'!A30 | Q30: =D30 | R30: 0 | S30: =Q30-R30 | T30: =Q30/R30-1 | U30: 0 | V30: =Q30-U30 | W30: =(Q30/U30-1)
A31: ='Cumul annuel'!A31 | C31: =D31-B31 | I31: =G31+H31 | N31: =J31+I31+F31+E31+L31+M31+K31 | O31: =N31+D31 | P31: ='Cumul annuel'!A31 | Q31: =D31 | R31: 0 | S31: =Q31-R31 | T31: =Q31/R31-1 | U31: 14343663 | V31: =Q31-U31 | W31: =(Q31/U31-1)
A32: ='Cumul annuel'!A32 | C32: =D32-B32 | I32: =G32+H32 | N32: =J32+I32+F32+E32+L32+M32+K32 | O32: =N32+D32 | P32: ='Cumul annuel'!A32 | Q32: =D32 | R32: 0 | S32: =Q32-R32 | T32: =Q32/R32-1 | U32: 0 | V32: =Q32-U32 | W32: =(Q32/U32-1)
A33: ='Cumul annuel'!A33 | C33: =D33-B33 | I33: =G33+H33 | N33: =J33+I33+F33+E33+L33+M33+K33 | O33: =N33+D33 | P33: ='Cumul annuel'!A33 | Q33: =D33 | R33: 0 | S33: =Q33-R33 | T33: =Q33/R33-1 | U33: 0 | V33: =Q33-U33 | W33: =(Q33/U33-1)
A34: ='Cumul annuel'!A34 | C34: =D34-B34 | I34: =G34+H34 | N34: =J34+I34+F34+E34+L34+M34+K34 | O34: =N34+D34 | P34: ='Cumul annuel'!A34 | Q34: =D34 | R34: 0 | S34: =Q34-R34 | T34: =Q34/R34-1 | U34: 0 | V34: =Q34-U34 | W34: =(Q34/U34-1)
A35: ='Cumul annuel'!A35 | C35: =D35-B35 | H35: 282860 | I35: =G35+H35 | N35: =J35+I35+F35+E35+L35+M35+K35 | O35: =N35+D35 | P35: ='Cumul annuel'!A35 | Q35: =D35 | R35: 66666.667 | S35: =Q35-R35 | T35: =Q35/R35-1 | U35: 0 | V35: =Q35-U35 | W35: =(Q35/U35-1)
A36: ='Cumul annuel'!A36 | C36: =D36-B36 | I36: =G36+H36 | N36: =J36+I36+F36+E36+L36+M36+K36 | O36: =N36+D36 | P36: ='Cumul annuel'!A36 | Q36: =D36 | R36: 0 | S36: =Q36-R36 | T36: =Q36/R36-1 | U36: 0 | V36: =Q36-U36 | W36: =(Q36/U36-1)
A37: ='Cumul annuel'!A37 | C37: =D37-B37 | I37: =G37+H37 | N37: =J37+I37+F37+E37+L37+M37+K37 | O37: =N37+D37 | P37: ='Cumul annuel'!A37 | Q37: =D37 | R37: 833333.33 | S37: =Q37-R37 | T37: =Q37/R37-1 | U37: 14535000 | V37: =Q37-U37 | W37: =(Q37/U37-1)
A38: ='Cumul annuel'!A38 | B38: 20000000 | C38: =D38-B38 | D38: 182096640 | I38: =G38+H38 | K38: 6200000 | N38: =J38+I38+F38+E38+L38+M38+K38 | O38: =N38+D38 | P38: ='Cumul annuel'!A38 | Q38: =D38 | R38: 55833333 | S38: =Q38-R38 | T38: =Q38/R38-1 | U38: 17705390 | V38: =Q38-U38 | W38: =(Q38/U38-1)
A39: ='Cumul annuel'!A39 | C39: =D39-B39 | I39: =G39+H39 | N39: =J39+I39+F39+E39+L39+M39+K39 | O39: =N39+D39 | P39: ='Cumul annuel'!A39 | Q39: =D39 | R39: 200000 | S39: =Q39-R39 | T39: =Q39/R39-1 | U39: 0 | V39: =Q39-U39 | W39: =(Q39/U39-1)
A40: ='Cumul annuel'!A40 | C40: =D40-B40 | I40: =G40+H40 | N40: =J40+I40+F40+E40+L40+M40+K40 | O40: =N40+D40 | P40: ='Cumul annuel'!A40 | Q40: =D40 | R40: 0 | S40: =Q40-R40 | T40: =Q40/R40-1 | U40: 0 | V40: =Q40-U40 | W40: =(Q40/U40-1)
A41: ='Cumul annuel'!A41 | C41: =D41-B41 | I41: =G41+H41 | N41: =J41+I41+F41+E41+L41+M41+K41 | O41: =N41+D41 | P41: ='Cumul annuel'!A41 | Q41: =D41 | R41: 0 | S41: =Q41-R41 | T41: =Q41/R41-1 | U41: 0 | V41: =Q41-U41 | W41: =(Q41/U41-1)
A42: ='Cumul annuel'!A42 | B42: 763750 | C42: =D42-B42 | D42: 763750 | I42: =G42+H42 | N42: =J42+I42+F42+E42+L42+M42+K42 | O42: =N42+D42 | P42: ='Cumul annuel'!A42 | Q42: =D42 | R42: 1000000 | S42: =Q42-R42 | T42: =Q42/R42-1 | U42: 763750 | V42: =Q42-U42 | W42: =(Q42/U42-1)
A43: ='Cumul annuel'!A43 | C43: =D43-B43 | I43: =G43+H43 | N43: =J43+I43+F43+E43+L43+M43+K43 | O43: =N43+D43 | P43: ='Cumul annuel'!A43 | Q43: =D43 | R43: 0 | S43: =Q43-R43 | T43: =Q43/R43-1 | U43: 0 | V43: =Q43-U43 | W43: =(Q43/U43-1)
A44: ='Cumul annuel'!A44 | C44: =D44-B44 | I44: =G44+H44 | L44: 8757420 | N44: =J44+I44+F44+E44+L44+M44+K44 | O44: =N44+D44 | P44: ='Cumul annuel'!A44 | Q44: =D44 | R44: 0 | S44: =Q44-R44 | T44: =Q44/R44-1 | U44: 0 | V44: =Q44-U44 | W44: =(Q44/U44-1)
A45: ='Cumul annuel'!A45 | C45: =D45-B45 | D45: 57612190 | I45: =G45+H45 | N45: =J45+I45+F45+E45+L45+M45+K45 | O45: =N45+D45 | P45: ='Cumul annuel'!A45 | Q45: =D45 | R45: 47222222 | S45: =Q45-R45 | T45: =Q45/R45-1 | U45: 43465797 | V45: =Q45-U45 | W45: =(Q45/U45-1)
A46: ='Cumul annuel'!A46 | C46: =D46-B46 | I46: =G46+H46 | N46: =J46+I46+F46+E46+L46+M46+K46 | O46: =N46+D46 | P46: ='Cumul annuel'!A46 | Q46: =D46 | R46: 0 | S46: =Q46-R46 | T46: =Q46/R46-1 | U46: 0 | V46: =Q46-U46 | W46: =(Q46/U46-1)
A47: ='Cumul annuel'!A47 | B47: 18000000 | C47: =D47-B47 | D47: 18000000 | I47: =G47+H47 | N47: =J47+I47+F47+E47+L47+M47+K47 | O47: =N47+D47 | P47: ='Cumul annuel'!A47 | Q47: =D47 | R47: 17916667 | S47: =Q47-R47 | T47: =Q47/R47-1 | U47: 3024400 | V47: =Q47-U47 | W47: =(Q47/U47-1)
A48: ='Cumul annuel'!A48 | C48: =D48-B48 | I48: =G48+H48 | N48: =J48+I48+F48+E48+L48+M48+K48 | O48: =N48+D48 | P48: ='Cumul annuel'!A48 | Q48: =D48 | R48: 400000 | S48: =Q48-R48 | T48: =Q48/R48-1 | U48: 0 | V48: =Q48-U48 | W48: =(Q48/U48-1)
A49: ='Cumul annuel'!A49 | B49: 43912500 | C49: =D49-B49 | D49: 385671429 | I49: =G49+H49 | K49: 82000000 | L49: 5115866 | N49: =J49+I49+F49+E49+L49+M49+K49 | O49: =N49+D49 | P49: ='Cumul annuel'!A49 | Q49: =D49 | R49: 1.9133333e+08 | S49: =Q49-R49 | T49: =Q49/R49-1 | U49: 0 | V49: =Q49-U49 | W49: =(Q49/U49-1)
A50: ='Cumul annuel'!A50 | B50: 3673359 | C50: =D50-B50 | D50: 6931259 | I50: =G50+H50 | N50: =J50+I50+F50+E50+L50+M50+K50 | O50: =N50+D50 | P50: ='Cumul annuel'!A50 | Q50: =D50 | R50: 0 | S50: =Q50-R50 | T50: =Q50/R50-1 | U50: 0 | V50: =Q50-U50 | W50: =(Q50/U50-1)
A51: CA TOTAL | B51: =SUM(B4:B50) | C51: =SUM(C4:C50) | D51: =SUM(D4:D50) | E51: =SUM(E4:E50) | F51: =SUM(F4:F50) | G51: =SUM(G4:G50) | H51: =SUM(H4:H50) | I51: =SUM(I4:I50) | ... R51: =SUM(R4:R50) | S51: =Q51-R51 | T51: =Q51/R51-1 | U51: =SUM(U4:U50) | V51: =Q51-U51 | W51: =(Q51/U51-1)
A52: Rétrocession | N52: =J52+I52+F52+E52 | P52: Rétrocessions | Q52: =Q53+Q54+Q55+Q56 | R52: =R53+R54+R55+R56 | S52: =Q52-R52 | T52: =Q52/R52-1 | U52: 12243509 | W52: =(Q52/U52-1)
A53: Taux Rétrocession | E53: =E52/E51 | F53: =F52/F51 | I53: =I52/I51 | J53: =J52/J51 | N53: =N52/N51 | P53: IMAR | Q53: =E52 | S53: =Q53-R53 | T53: =Q53/R53-1 | U53: 0 | V53: =Q53-U53 | W53: =(Q53/U53-1)
A54: TOTAL Après rétrocession | D54: =D52+D51 | E54: =E51-E52 | F54: =F51-F52 | I54: =I51-I52 | J54: =J51-J52 | K54: =K51 | L54: =L51 | M54: =M51 | N54: =SUM(D54:M54) | P54: HINT | Q54: =F52 | S54: =Q54-R54 | T54: =Q54/R54-1 | U54: 190750 | V54: =Q54-U54 | W54: =(Q54/U54-1)
P55: AER | Q55: =I52 | S55: =Q55-R55 | T55: =Q55/R55-1 | U55: 0 | V55: =Q55-U55 | W55: =(Q55/U55-1)
P56: EMAR | Q56: =J52 | S56: =Q56-R56 | T56: =Q56/R56-1 | U56: 12052759 | V56: =Q56-U56 | W56: =(Q56/U56-1)
C57: =B51 | D57: =C57/$C$60 | E57: Loyer | P57: ACTIVITE O&G | Q57: =Q51+Q53+Q54+Q55+Q56 | R57: =R51+R52 | S57: =Q57-R57 | T57: =Q57/R57-1 | U57: =U51+U52 | V57: =V51+V53+V54+V55+V56 | W57: =(Q57/U57-1)
C58: =C51 | D58: =C58/$C$60 | E58: LOGP | P58: R26 | U58: Variation Réel 26/ Réel 25
C59: =D52 | D59: =C59/$C$60 | E59: Rétrocession
C60: =D54 | D60: =C60/$C$60 | R60: 687285000
R62: =R60-R51

Sheet Mai
B1: CAP Mai | P1: VARIATION R 26 sur B26 & R25
B2: BASE | E2: CA GENERE | P2: R26 | R2: Variation Réel 26 / B26 | U2: Variation Réel 26 / Réel 25 | X2: Commentaires
B3: LOYER | C3: Plog & Divers | D3: Total BASE | E3: IMAR | F3: HINT | G3: IAER | H3: EAER | I3: AERIEN | J3: EXPORT | K3: SIRT | L3: Afritramp | M3: Meet & Greet | N3: CA GENERE Autres département | O3: CA TOTAL GENERE PAR CLIENT | P3: Sources revenus | Q3: REEL BASE 2026 | R3: Budget 2026 | S3: VAR (FCFA) | T3: Var (%) | U3: Réel BASE 2025 | V3: VAR (FCFA) | W3: Var (%)
A4: ='Cumul annuel'!A4 | C4: =D4-B4 | D4: 17214000 | I4: =G4+H4 | N4: =J4+I4+F4+E4+L4+M4+K4 | O4: =N4+D4 | P4: ='Cumul annuel'!A4 | Q4: =D4 | R4: 0 | S4: =Q4-R4 | T4: =Q4/R4-1 | U4: 5400000 | V4: =Q4-U4 | W4: =(Q4/U4-1)
A5: ='Cumul annuel'!A5 | C5: =D5-B5 | I5: =G5+H5 | N5: =J5+I5+F5+E5+L5+M5+K5 | O5: =N5+D5 | P5: ='Cumul annuel'!A5 | Q5: =D5 | R5: 6666666.7 | S5: =Q5-R5 | T5: =Q5/R5-1 | U5: 1640536 | V5: =Q5-U5 | W5: =(Q5/U5-1)
A6: ='Cumul annuel'!A6 | B6: 22000000 | C6: =D6-B6 | D6: 22453000 | I6: =G6+H6 | N6: =J6+I6+F6+E6+L6+M6+K6 | O6: =N6+D6 | P6: ='Cumul annuel'!A6 | Q6: =D6 | R6: 10750000 | S6: =Q6-R6 | T6: =Q6/R6-1 | U6: 55069559 | V6: =Q6-U6 | W6: =(Q6/U6-1)
A7: ='Cumul annuel'!A7 | C7: =D7-B7 | D7: 11176613 | I7: =G7+H7 | N7: =J7+I7+F7+E7+L7+M7+K7 | O7: =N7+D7 | P7: ='Cumul annuel'!A7 | Q7: =D7 | R7: 50000000 | S7: =Q7-R7 | T7: =Q7/R7-1 | U7: 25540109 | V7: =Q7-U7 | W7: =(Q7/U7-1)
A8: ='Cumul annuel'!A8 | C8: =D8-B8 | E8: -1108440 | G8: -3580880 | I8: =G8+H8 | N8: =J8+I8+F8+E8+L8+M8+K8 | O8: =N8+D8 | P8: ='Cumul annuel'!A8 | Q8: =D8 | R8: 0 | S8: =Q8-R8 | T8: =Q8/R8-1 | U8: 110721461 | V8: =Q8-U8 | W8: =(Q8/U8-1)
